Workbook

Sheet Seguimiento
B3: Estado semanal
B6: 1. Estado captación integradores
B8: Estado | C8: Empresa | D8: % sobre total | E8: Observaciones
B9: 0. Pendiente contactar | C9: =+INDEX('Summary Captación INT >>'!$C$5:$E$19,MATCH($B9,'Summary Captación INT >>'!$B$5:$B$19,0),MATCH(C$8,'Summary Captación INT >>'!$C$4:$E$4,0)) -> 437 | D9: =+INDEX('Summary Captación INT >>'!$C$5:$E$19,MATCH($B9,'Summary Captación INT >>'!$B$5:$B$19,0),MATCH(D$8,'Summary Captación INT >>'!$C$4:$E$4,0)) -> 0.22261844
B10: 0. Contacto fallido (sin descuelgue) | C10: =+INDEX('Summary Captación INT >>'!$C$5:$E$19,MATCH($B10,'Summary Captación INT >>'!$B$5:$B$19,0),MATCH(C$8,'Summary Captación INT >>'!$C$4:$E$4,0)) -> #N/A | D10: =+INDEX('Summary Captación INT >>'!$C$5:$E$19,MATCH($B10,'Summary Captación INT >>'!$B$5:$B$19,0),MATCH(D$8,'Summary Captación INT >>'!$C$4:$E$4,0)) -> #N/A
B11: 1. Contactado con interés | C11: =+INDEX('Summary Captación INT >>'!$C$5:$E$19,MATCH($B11,'Summary Captación INT >>'!$B$5:$B$19,0),MATCH(C$8,'Summary Captación INT >>'!$C$4:$E$4,0)) -> #N/A | D11: =+INDEX('Summary Captación INT >>'!$C$5:$E$19,MATCH($B11,'Summary Captación INT >>'!$B$5:$B$19,0),MATCH(D$8,'Summary Captación INT >>'!$C$4:$E$4,0)) -> #N/A
B12: 2. Rechazados / muertos (KO) | C12: =+INDEX('Summary Captación INT >>'!$C$5:$E$19,MATCH($B12,'Summary Captación INT >>'!$B$5:$B$19,0),MATCH(C$8,'Summary Captación INT >>'!$C$4:$E$4,0)) -> #N/A | D12: =+INDEX('Summary Captación INT >>'!$C$5:$E$19,MATCH($B12,'Summary Captación INT >>'!$B$5:$B$19,0),MATCH(D$8,'Summary Captación INT >>'!$C$4:$E$4,0)) -> #N/A | E12: =+INDEX('Summary Captación INT >>'!$C$5:$E$19,MATCH($B12,'Summary Captación INT >>'!$B$5:$B$19,0),MATCH(E$8,'Summary Captación INT >>'!$C$4:$E$4,0)) -> #N/A
B13: 3. Sesión agendada | C13: =+INDEX('Summary Captación INT >>'!$C$5:$E$19,MATCH($B13,'Summary Captación INT >>'!$B$5:$B$19,0),MATCH(C$8,'Summary Captación INT >>'!$C$4:$E$4,0)) -> #N/A | D13: =+INDEX('Summary Captación INT >>'!$C$5:$E$19,MATCH($B13,'Summary Captación INT >>'!$B$5:$B$19,0),MATCH(D$8,'Summary Captación INT >>'!$C$4:$E$4,0)) -> #N/A | E13: =+INDEX('Summary Captación INT >>'!$C$5:$E$19,MATCH($B13,'Summary Captación INT >>'!$B$5:$B$19,0),MATCH(E$8,'Summary Captación INT >>'!$C$4:$E$4,0)) -> #N/A
B14: 4. Interés en evaluación | C14: =+INDEX('Summary Captación INT >>'!$C$5:$E$19,MATCH($B14,'Summary Captación INT >>'!$B$5:$B$19,0),MATCH(C$8,'Summary Captación INT >>'!$C$4:$E$4,0)) -> #N/A | D14: =+INDEX('Summary Captación INT >>'!$C$5:$E$19,MATCH($B14,'Summary Captación INT >>'!$B$5:$B$19,0),MATCH(D$8,'Summary Captación INT >>'!$C$4:$E$4,0)) -> #N/A | E14: =+INDEX('Summary Captación INT >>'!$C$5:$E$19,MATCH($B14,'Summary Captación INT >>'!$B$5:$B$19,0),MATCH(E$8,'Summary Captación INT >>'!$C$4:$E$4,0)) -> #N/A
B15: 4. Interés confirmado | C15: =+INDEX('Summary Captación INT >>'!$C$5:$E$19,MATCH($B15,'Summary Captación INT >>'!$B$5:$B$19,0),MATCH(C$8,'Summary Captación INT >>'!$C$4:$E$4,0)) -> #N/A | D15: =+INDEX('Summary Captación INT >>'!$C$5:$E$19,MATCH($B15,'Summary Captación INT >>'!$B$5:$B$19,0),MATCH(D$8,'Summary Captación INT >>'!$C$4:$E$4,0)) -> #N/A | E15: =+INDEX('Summary Captación INT >>'!$C$5:$E$19,MATCH($B15,'Summary Captación INT >>'!$B$5:$B$19,0),MATCH(E$8,'Summary Captación INT >>'!$C$4:$E$4,0)) -> #N/A
B16: 5. Documentación de firma en proceso | C16: =+INDEX('Summary Captación INT >>'!$C$5:$E$19,MATCH($B16,'Summary Captación INT >>'!$B$5:$B$19,0),MATCH(C$8,'Summary Captación INT >>'!$C$4:$E$4,0)) -> #N/A | D16: =+INDEX('Summary Captación INT >>'!$C$5:$E$19,MATCH($B16,'Summary Captación INT >>'!$B$5:$B$19,0),MATCH(D$8,'Summary Captación INT >>'!$C$4:$E$4,0)) -> #N/A | E16: =+INDEX('Summary Captación INT >>'!$C$5:$E$19,MATCH($B16,'Summary Captación INT >>'!$B$5:$B$19,0),MATCH(E$8,'Summary Captación INT >>'!$C$4:$E$4,0)) -> #N/A
B17: 6. Firmado | C17: =+INDEX('Summary Captación INT >>'!$C$5:$E$19,MATCH($B17,'Summary Captación INT >>'!$B$5:$B$19,0),MATCH(C$8,'Summary Captación INT >>'!$C$4:$E$4,0)) -> #N/A | D17: =+INDEX('Summary Captación INT >>'!$C$5:$E$19,MATCH($B17,'Summary Captación INT >>'!$B$5:$B$19,0),MATCH(D$8,'Summary Captación INT >>'!$C$4:$E$4,0)) -> #N/A | E17: =+INDEX('Summary Captación INT >>'!$C$5:$E$19,MATCH($B17,'Summary Captación INT >>'!$B$5:$B$19,0),MATCH(E$8,'Summary Captación INT >>'!$C$4:$E$4,0)) -> #N/A
B18: 97. Churn | C18: =+INDEX('Summary Captación INT >>'!$C$5:$E$20,MATCH($B18,'Summary Captación INT >>'!$B$5:$B$20,0),MATCH(C$8,'Summary Captación INT >>'!$C$4:$E$4,0)) -> #N/A | D18: =+INDEX('Summary Captación INT >>'!$C$5:$E$20,MATCH($B18,'Summary Captación INT >>'!$B$5:$B$20,0),MATCH(D$8,'Summary Captación INT >>'!$C$4:$E$4,0)) -> #N/A | E18: =+INDEX('Summary Captación INT >>'!$C$5:$E$19,MATCH($B18,'Summary Captación INT >>'!$B$5:$B$19,0),MATCH(E$8,'Summary Captación INT >>'!$C$4:$E$4,0)) -> #N/A
B19: 98. Descartado del proceso | C19: =+INDEX('Summary Captación INT >>'!$C$5:$E$20,MATCH($B19,'Summary Captación INT >>'!$B$5:$B$20,0),MATCH(C$8,'Summary Captación INT >>'!$C$4:$E$4,0)) -> #N/A | D19: =+INDEX('Summary Captación INT >>'!$C$5:$E$20,MATCH($B19,'Summary Captación INT >>'!$B$5:$B$20,0),MATCH(D$8,'Summary Captación INT >>'!$C$4:$E$4,0)) -> #N/A | E19: =+INDEX('Summary Captación INT >>'!$C$5:$E$19,MATCH($B19,'Summary Captación INT >>'!$B$5:$B$19,0),MATCH(E$8,'Summary Captación INT >>'!$C$4:$E$4,0)) -> #N/A
B20: Total | C20: =+INDEX('Summary Captación INT >>'!$C$5:$E$19,MATCH($B20,'Summary Captación INT >>'!$B$5:$B$19,0),MATCH(C$8,'Summary Captación INT >>'!$C$4:$E$4,0)) -> #N/A
B21: Total captados | C21: =SUM(C15:C17) -> #N/A
B23: Highlights
B24: Nuevo integrador con interés en evaluación (INFORNET)
B28: Aspectos a movilizar | C28: Fecha esperada | D28: Nueva fecha | E28: Criticidad | F28: Responsable
B29: Hacer seguimiento al grupo de 2 empezando el proceso de firma | C29: Continuo | F29: Accenture
B33: 2. Estado contratos
B35: Integrador | C35: Envío documentación | D35: Revisión legal | E35: Firma contrato | F35: Creación SFID | G35: Comentarios
B36: Cover Net | C36: Finalizado | D36: Finalizado | E36: Finalizado | F36: Finalizado
B37: Maxen | C37: Finalizado | D37: Finalizado | E37: Finalizado | F37: Finalizado
B38: Deiteco | C38: Finalizado | D38: Finalizado | E38: En curso | F38: Pendiente
B39: Duo IT | C39: En curso | D39: Pendiente | E39: Pendiente | F39: Pendiente
B40: Land M | C40: Pendiente | D40: Pendiente | E40: Pendiente | F40: Pendiente
B41: Dataqu | C41: Pendiente | D41: Pendiente | E41: Pendiente | F41: Pendiente
B42: Octivitas | C42: Pendiente | D42: Pendiente | E42: Pendiente | F42: Pendiente | G42: Pendiente envío contrato + anexo renovación (pendiente finalización legal)
B43: Paperlabs | G43: Retraso en participación
B44: Ox-one | C44: Pendiente | D44: Pendiente | E44: Pendiente | F44: Pendiente
B45: Microsip | C45: Pendiente | D45: Pendiente | E45: Pendiente | F45: Pendiente
B46: SICTEMAS | C46: Pendiente | D46: Pendiente | E46: Pendiente | F46: Pendiente
B47: Fedesoft | C47: Pendiente | D47: Pendiente | E47: Pendiente | F47: Pendiente
B51: Highlights
B52: + 3 sesiones presenciales agendadas: Ox-one (10.12); Fedesoft (13.01); SICTEMAS (09.01)
B55: Aspectos a movilizar | C55: Fecha esperada | D55: Nueva fecha | E55: Criticidad | F55: Responsable
B56: Nuevo modelo contrato Colaborador de Leads | C56: 45996 | D56: 46000 | E56: Alta | F56: Legal
B57: Anexo económico Colaborador de Leads | C57: 45996 | D57: 46000 | E57: Alta | F57: ACN, Finanzas
B58: Envío del contrato de Leadgen + anexo renovación a Octivitas | C58: 45981 | D58: 46000 | E58: Alta | F58: Legal, Eloy
B59: Simplificación de contratos | D59: 46000 | E59: Alta | F59: Legal
B62: Estado venta cliente final
B65: Integrador | C65: Leads identificados (no +O) | D65: Leads contactados | E65: Contactados s/identificados (%) | F65: Ofertas | G65: Ofertas s/contactados (%) | H65: Ventas | I65: Ventas s/ofertas (%)
B66: Cover Net | C66: 5 | D66: 3 | E66: =+IFERROR(D66/C66,"0") -> 0.6 | F66: 3 | G66: =+IFERROR(F66/D66,"0") -> 1 | H66: 0 | I66: =+IFERROR(H66/F66,"0") -> 0
B67: Maxen | C67: 14 | D67: 2 | E67: =+IFERROR(D67/C67,"0") -> 0.14285714 | F67: 2 | G67: =+IFERROR(F67/D67,"0") -> 1 | H67: 0 | I67: =+IFERROR(H67/F67,"0") -> 0
B68: Deiteco | C68: En curso | D68: 0 | E68: =+IFERROR(D68/C68,"0") -> 0 | F68: 0 | G68: =+IFERROR(F68/D68,"0") -> 0 | H68: 0 | I68: =+IFERROR(H68/F68,"0") -> 0
B69: Duo IT | C69: 2 | D69: 0 | E69: =+IFERROR(D69/C69,"0") -> 0 | F69: 0 | G69: =+IFERROR(F69/D69,"0") -> 0 | H69: 0 | I69: =+IFERROR(H69/F69,"0") -> 0
B70: Land M | C70: 1 | D70: 0 | E70: =+IFERROR(D70/C70,"0") -> 0 | F70: 0 | G70: =+IFERROR(F70/D70,"0") -> 0 | H70: 0 | I70: =+IFERROR(H70/F70,"0") -> 0
B71: Dataqu | C71: n.a. | D71: 0 | E71: =+IFERROR(D71/C71,"0") -> 0 | F71: 0 | G71: =+IFERROR(F71/D71,"0") -> 0 | H71: 0 | I71: =+IFERROR(H71/F71,"0") -> 0
B72: Octivitas | C72: n.a. | D72: 0 | E72: =+IFERROR(D72/C72,"0") -> 0 | F72: 0 | G72: =+IFERROR(F72/D72,"0") -> 0 | H72: 0 | I72: =+IFERROR(H72/F72,"0") -> 0
B73: Total | C73: =+SUBTOTAL(9,C66:C72) -> 22 | D73: =+SUBTOTAL(9,D66:D72) -> 5 | E73: =+D73/C73 -> 0.22727273 | F73: =+SUBTOTAL(9,F66:F72) -> 5 | G73: =+F73/D73 -> 1 | H73: =+SUBTOTAL(9,H66:H72) -> 0 | I73: =+H73/F73 -> 0
C74: =+C73/300 -> 0.073333333 | E74: s/ leads identificados | G74: s/leads contactados | I74: s/ofertas realizadas
B76: Highlights
B77: Maxen: 2 ofertas pendiente de firma 10.12
B78: Cover Net: 3 leads hot > pendiente agendar visitas 22.12 / 09.01
B82: Aspectos a movilizar | C82: Fecha esperada | D82: Nueva fecha | E82: Criticidad | F82: Responsable
B83: Soporte a generación oferta Signa | C83: 45982 | D83: 45982 | E83: Alta | F83: Pablo, Alicia
B84: Material para integradores: Tablets | C84: 45989 | E84: Media | F84: Javier Carrasco
B87: Otros temas prioritarios
B89: Aspecto a movilizar | C89: Fecha esperada | D89: Nueva fecha | E89: Criticidad | F89: Responsable
B90: Elaboración del kit de Marketing | C90: 45967 | D90: 45996 | E90: Alta | F90: María de Sebastián / Pendiente OK final RRLL
B91: Simplificación kit de onboarding (aplicativos y htas. Usuarios & contraseñas) y modelo operativo | C91: 45981 | D91: 45989 | E91: Alta | F91: Accenture, Pablo
B92: Convocar formaciones pendientes (Big Pyme, Signa & web penalizaciones, Portal DHO & Formulario BOC, DO y Business Time) | C92: 45981 | D92: 46029 | E92: Media | F92: Fátima, Carlos

Sheet Summary Captación INT >>
B2: Leads priorizados
B4: Estado | C4: Empresa | D4: % sobre total | E4: Observaciones
B5: 0. Pendiente contactar | C5: =+IFERROR(_xlfn.XLOOKUP(B5,$B$24:$B$38,$C$24:$C$38),"0") -> 437 | D5: =+C5/$C$20 -> 0.22261844
B6: 1.0. Contacto fallido (sin descuelgue) | C6: =+IFERROR(_xlfn.XLOOKUP(B6,$B$24:$B$38,$C$24:$C$38),"0") -> 190 | D6: =+C6/$C$20 -> 0.096790627
B7: 1.1 Contactado: propuesta "rechazada" | C7: =+IFERROR(_xlfn.XLOOKUP(B7,$B$24:$B$38,$C$24:$C$38),"0") -> 206 | D7: =+C7/$C$20 -> 0.10494142
B8: 1.2 Contactado: propuesta "en valoración" | C8: =+IFERROR(_xlfn.XLOOKUP(B8,$B$24:$B$38,$C$24:$C$38),"0") -> 407 | D8: =+C8/$C$20 -> 0.20733571
B9: 1.3 Contactado "muerto" | C9: =+IFERROR(_xlfn.XLOOKUP(B9,$B$24:$B$38,$C$24:$C$38),"0") -> 154 | D9: =+C9/$C$20 -> 0.07845135
B10: 2.1 Acepta Sesión 1:1 - pendiente agendar | C10: =+IFERROR(_xlfn.XLOOKUP(B10,$B$24:$B$38,$C$24:$C$38),"0") -> 1 | D10: =+C10/$C$20 -> 0.00050942435
B11: 2.2 Acepta Sesión 1:1 - agendada | C11: =+IFERROR(_xlfn.XLOOKUP(B11,$B$24:$B$38,$C$24:$C$38),"0") -> 3 | D11: =+C11/$C$20 -> 0.0015282731
B12: 2.3 Rechaza tras Sesión 1:1 | C12: =+IFERROR(_xlfn.XLOOKUP(B12,$B$24:$B$38,$C$24:$C$38),"0") -> 19 | D12: =+C12/$C$20 -> 0.0096790627
B13: 3.1 Interés confirmado: pendiente agendar KO | C13: =+IFERROR(_xlfn.XLOOKUP(B13,$B$24:$B$38,$C$24:$C$38),"0") -> 8 | D13: =+C13/$C$20 -> 0.0040753948
B14: 3.2 Interés confirmado: agendado KO | C14: =+IFERROR(_xlfn.XLOOKUP(B14,$B$24:$B$38,$C$24:$C$38),"0") -> 4 | D14: =+C14/$C$20 -> 0.0020376974
B15: 3.3 Interés confirmado: on hold | C15: =+IFERROR(_xlfn.XLOOKUP(B15,$B$24:$B$38,$C$24:$C$38),"0") -> 4 | D15: =+C15/$C$20 -> 0.0020376974
B16: 4.1 Activado: en proceso de firma | C16: =+IFERROR(_xlfn.XLOOKUP(B16,$B$24:$B$38,$C$24:$C$38),"0") -> 17 | D16: =+C16/$C$20 -> 0.008660214
... B19: 99. Descartado | C19: =+IFERROR(_xlfn.XLOOKUP(B19,$B$24:$B$38,$C$24:$C$38),"0") -> 499 | D19: =+C19/$C$20 -> 0.25420275
B20: Grand Total | C20: =+SUM(C5:C19) -> 1963
B23: Row Labels | C23: Count of Empresa
B24: 0. Pendiente contactar | C24: 437
B25: 1.0. Contacto fallido (sin descuelgue) | C25: 190
B26: 1.1 Contactado: propuesta "rechazada" | C26: 206
B27: 1.2 Contactado: propuesta "en valoración" | C27: 407
B28: 1.3 Contactado "muerto" | C28: 154
B29: 2.1 Acepta Sesión 1:1 - pendiente agendar | C29: 1
B30: 2.2 Acepta Sesión 1:1 - agendada | C30: 3
B31: 2.3 Rechaza tras Sesión 1:1 | C31: 19
B32: 3.1 Interés confirmado: pendiente agendar KO | C32: 8
B33: 3.2 Interés confirmado: agendado KO | C33: 4
B34: 3.3 Interés confirmado: on hold | C34: 4
B35: 4.1 Activado: en proceso de firma | C35: 17
... B39: Grand Total | C39: 1963
B49: 0. Pendiente contactar
B50: 1.0. Contacto fallido (sin descuelgue)
B51: 1.1 Contactado: propuesta "rechazada"
B52: 1.2 Contactado: propuesta "en valoración"
B53: 1.3 Contactado "muerto"
B54: 2.1 Acepta Sesión 1:1 - pendiente agendar
B55: 2.2 Acepta Sesión 1:1 - agendada
B56: 2.3 Rechaza tras Sesión 1:1
B57: 3.1 Interés confirmado: pendiente agendar KO
B58: 3.2 Interés confirmado: agendado KO
B59: 3.3 Interés confirmado: on hold
B60: 4.1 Activado: en proceso de firma
... B63: 99. Descartado

Sheet Resumen Estados
B2: Hito | C2: Nombre | D2: Definición | E2: #integradores | G2: % | L2: 0. Pendiente contactar | M2: 0. Pendiente contactar
C3: Total Fishing Pool Integradores | D3: Total de integradores en el fishing pool | E3: =+COUNTA('BBDD Completa'!E2:E5125) -> 5124 | F3: Suma todos | L3: 0. Contacto fallido (sin descuelgue) | M3: 1.0 Contacto fallido (sin descuelgue)
C4: Fishing Pool Priorizada Fase Lanzamiento | D4: Total de integradores priorizados para esta primera ronda de contactos | E4: =+COUNTA('Leads Priorizados INT'!B4:B1436) -> 1433 | F4: Suma todos en esta BBDD | L4: 1. Contactado | M4: 1.2 Contactado: propuesta "en valoración"
C5: Descartados | D5: Descartados por (1) número no disponible, (2) cierre, (3) no encaja en programa | E5: =+GETPIVOTDATA("Empresa",'Summary Captación INT >>'!$B$23,"Estado","99. Descartado") -> 499 | F5: 99. Descartado | L5: 1. Contactado "con interés" | M5: 1.2 Contactado: propuesta "en valoración"
C6: Pendientes de contactar | E6: =+GETPIVOTDATA("Empresa",'Summary Captación INT >>'!$B$23,"Estado","0. Pendiente contactar") -> 437 | F6: 0. Pendiente contactar | L6: 1. Contactado "muerto" | M6: 1.3 Contactado: "muerto"
C7: Contacto fallido | D7: Se ha realizado un primer contacto telefónico sin éxito: (1) sin descuelgue, (2) volver a llamar por contacto erróneo | E7: =+GETPIVOTDATA("Empresa",'Summary Captación INT >>'!$B$23,"Estado","1.0. Contacto fallido (sin descuelgue)") -> 190 | F7: 0. Contacto fallido (sin descuelgue) | L7: 2. Rechazado | M7: 1.1 Contactado: propuesta "rechazada"
B8: Hito 1: contacto establecido | C8: Primer contacto (telefónico) | D8: Hemos conseguido establecer contacto con la persona adecuada de la organización del integrador | E8: =+GETPIVOTDATA("Empresa",'Summary Captación INT >>'!$B$23)-GETPIVOTDATA("Empresa",'Summary Captación INT >>'!$B$23,"Estado","0. Pendiente contactar")-GETPIVOTDATA("Empresa",'Summary Captación INT >>'!$B$23,"Estado","1.0. Contacto fallido (sin descuelgue)")-GETPIVOTDATA("Empresa",'Summary Captación INT >>'!$B$23,"Estado","99. Descartado") -> 837 | F8: Todos - 99 - 98 - 0 | G8: =+E8/E3 -> 0.16334895 | H8: Sobre el total | L8: 3.0 Quiere sesión 1:1 - pendiente agendar | M8: 2.1 Acepta Sesión 1:1 - pendiente agendar
C9: Rechazado / No contesta | D9: Propuesta rechazada por (1) falta de interés en propuesta, (2) sin encaje con modelo de negocio; o por no haber recibido respuesta después de 3 intentos de contacto | E9: =+GETPIVOTDATA("Empresa",'Summary Captación INT >>'!$B$23,"Estado","1.1 Contactado: propuesta ""rechazada""")+GETPIVOTDATA("Empresa",'Summary Captación INT >>'!$B$23,"Estado","1.3 Contactado ""muerto""") -> 360 | F9: 1. Contactado "muerto" & 2. Rechazado (KO) | L9: 3. Sesión agendada | M9: 2.2 Acepta Sesión 1:1 - agendada
C10: Requiere re-contacto | D10: Interés mostrado en propuesta, pendiente recontactar para mantener interés y cerrar sesión 1:1 | E10: =+GETPIVOTDATA("Empresa",'Summary Captación INT >>'!$B$23,"Estado","1.2 Contactado: propuesta ""en valoración""") -> 407 | F10: 1. Contactado & 1. Contactado "con interés" | L10: 3.1 Rechazado tras sesión online 1:1 | M10: 2.3 Rechaza tras Sesión 1:1 | N10: No continúa en proceso de onboarding tras la sesión informativa del programa
B11: Hito 2: Lead con Interés | C11: Acepta Sesión Informativa 1:1 (online) | E11: =+GETPIVOTDATA("Empresa",'Summary Captación INT >>'!$B$23)-GETPIVOTDATA("Empresa",'Summary Captación INT >>'!$B$23,"Estado","0. Pendiente contactar")-GETPIVOTDATA("Empresa",'Summary Captación INT >>'!$B$23,"Estado","1.0. Contacto fallido (sin descuelgue)")-GETPIVOTDATA("Empresa",'Summary Captación INT >>'!$B$23,"Estado","1.1 Contactado: propuesta ""rechazada""")-GETPIVOTDATA("Empresa",'Summary Captación INT >>'!$B$23,"Estado","1.2 Contactado: propuesta ""en valoración""")-GETPIVOTDATA("Empresa",'Summary Captación INT >>'!$B$23,"Estado","1.3 Contactado ""muerto""")-GETPIVOTDATA("Empresa",'Summary Captación INT >>'!$B$23,"Estado","99. Descartado") -> 70 | F11: Todos - los anteriores | L11: 4.1 Interés confirmado: pendiente agendar | M11: 3.1 Interés confirmado: pendiente agendar KO
C12: Pendiente sesión: sin agendar | D12: Acepta sesión informativa 1:1 pero está pendiente de agendar | E12: =+GETPIVOTDATA("Empresa",'Summary Captación INT >>'!$B$23,"Estado","2.1 Acepta Sesión 1:1 - pendiente agendar") -> 1 | F12: 3.0 Pendiente agendar | L12: 4.2 Interés confirmado: agendada | M12: 3.2 Interés confirmado: agendado KO
C13: Pendiente sesión: agendada | D13: Acepta sesión informativa 1:1 y está agendada | E13: =+GETPIVOTDATA("Empresa",'Summary Captación INT >>'!$B$23,"Estado","2.2 Acepta Sesión 1:1 - agendada") -> 3 | F13: 3. Sesión agendada | L13: 5. En proceso de firma | M13: 4.1 Activado: en proceso de firma
C14: Rechazado post sesión | D14: Rechaza propuesta por falta de interés o no encaje con modelo | E14: =+GETPIVOTDATA("Empresa",'Summary Captación INT >>'!$B$23,"Estado","2.3 Rechaza tras Sesión 1:1") -> 19 | F14: 3.1 Rechazado tras sesión online | L14: 6. Firmado | M14: 4.2 Activado: Firmado
B15: Hito 3: Integrador Captado | C15: Acepta sesión Kick Off (presencial) | D15: Acepta reunión presencial | E15: =+GETPIVOTDATA("Empresa",'Summary Captación INT >>'!$B$23,"Estado","3.1 Interés confirmado: pendiente agendar KO")+IFERROR(GETPIVOTDATA("Empresa",'Summary Captación INT >>'!$B$23,"Estado","3.2 Interés confirmado: agendado KO"),0)+GETPIVOTDATA("Empresa",'Summary Captación INT >>'!$B$23,"Estado","4.1 Activado: en proceso de firma")+GETPIVOTDATA("Empresa",'Summary Captación INT >>'!$B$23,"Estado","4.2 Activado: Firmado")+GETPIVOTDATA("Empresa",'Summary Captación INT >>'!$B$23,"Estado","98. Churn")+GETPIVOTDATA("Empresa",'Summary Captación INT >>'!$B$23,"Estado","3.3 Interés confirmado: on hold") -> 47 | F15: 3.1+3.2+98+4.1+4.2 | G15: =+E15/$E$8 -> 0.056152927 | H15: Sobre los contactados | L15: 97. Churn | M15: 4.3 Churn | N15: Hace churn después de sesión de kick-off
C16: Pendiente sesión: sin agendar | D16: Acepta reunión presencial, pendiente de agendar | E16: =+GETPIVOTDATA("Empresa",'Summary Captación INT >>'!$B$23,"Estado","3.1 Interés confirmado: pendiente agendar KO") -> 8 | F16: 3.1 | L16: 98. Descartado del proceso | M16: 99. Descartado | N16: Lo descartamos del proceso por (1) cierre, (2) objeto social no aplicable o (3) xxxx
C17: Pendiente sesión: agendada | D17: Acepta reunión presencial, agendada | E17: =+IFERROR(GETPIVOTDATA("Empresa",'Summary Captación INT >>'!$B$23,"Estado","3.2 Interés confirmado: agendado KO"),0) -> 4 | F17: 3.2 | L17: 99. Descartado por objeto social
C18: Pendiente sesión: sin contacto | D18: Acepta reunión presencial/online, pero no se consigue continuar contacto | E18: =+IFERROR(GETPIVOTDATA("Empresa",'Summary Captación INT >>'!$B$23,"Estado","3.3 Interés confirmado: on hold"),0) -> 4
C19: Churn post kick off | D19: Rechazo de propuesta después de la reunión presencial | E19: =+GETPIVOTDATA("Empresa",'Summary Captación INT >>'!$B$23,"Estado","98. Churn") -> 8 | F19: 98
B20: Hito 4: Integrador Activado | C20: ACTIVADO | E20: =+GETPIVOTDATA("Empresa",'Summary Captación INT >>'!$B$23,"Estado","4.1 Activado: en proceso de firma")+GETPIVOTDATA("Empresa",'Summary Captación INT >>'!$B$23,"Estado","4.2 Activado: Firmado") -> 23 | F20: SUMA DE 5 Y 6 | G20: =+E20/$E$8 -> 0.027479092 | H20: Sobre los contactados
C21: En proceso de firma | E21: =+GETPIVOTDATA("Empresa",'Summary Captación INT >>'!$B$23,"Estado","4.1 Activado: en proceso de firma") -> 17
B22: Hito 5: Firma de contrato | C22: Firmado | E22: =+GETPIVOTDATA("Empresa",'Summary Captación INT >>'!$B$23,"Estado","4.2 Activado: Firmado") -> 6
B27: Definición por estado
B29: Estado | C29: Definición
B30: 0. Pendiente contactar | C30: Empresa sin contactar
B31: 1.0 Contacto fallido (sin descuelgue) | C31: Contacto sin descuelgue. Volver a contactar
B32: 1.2 Contactado: propuesta "rechazado" | C32: Primer contacto establecido, integrador no interesado en la propuesta (e.g. no encaje con su modelo de negocio, no interesado en colaborar en este momento, etc.)
B33: 1.2 Contactado: propuesta "en valoración" | C33: Primer contacto establecido, integrador interesado en la propuesta. Se envía correo informativo y se agenda sesión 1:1 o se solicita disponibilidad para agendar dicha sesión
B34: 1.3 Contactado: "muerto" | C34: Contacto perdido. Previo estado 1.2) pero no ha vuelto a contestar en +3 semanas, incluyendo recontacto
B35: 2.1 Acepta Sesión 1:1 - pendiente agendar | C35: Pendiente agendar sesión online 1:1, sujeta a disponibilidad de la empresa
B36: 2.2 Acepta Sesión 1:1 - agendada | C36: Sesión online 1:1 aceptada y agendada
B37: 2.3 Rechaza tras Sesión 1:1 | C37: No continúa en proceso de onboarding tras la sesión informativa del programa
B38: 3.1 Interés confirmado: pendiente agendar KO | C38: Después de la sesión online, sigue con interés en el modelo y en mantener una sesión presencial de KickOff. Pendiente agendar el KickOff
B39: 3.2 Interés confirmado: agendado KO | C39: Sesión KickOff agendada (presencial u online)
B40: 4.1 Activado: en proceso de firma | C40: Integrador activado, en proceso de firma de contrato
... B43: 99. Descartado | C43: Lo descartamos del proceso por (1) cierre, (2) objeto social no aplicable o (3) compañía no activa, (4) etc.

Sheet Leads
B2: Funnel leads
E3: Correo
C4: Leads potenciales | D4: Leads pendientes de identificar | E4: Leads activados | F4: Ventas realizadas | G4: Leads en curso | H4: Pendiente info para realizar oferta | I4: KO
C5: =+COUNTA(B11:B217) -> 53 | D5: =+C5-E5 -> 0 | E5: =+COUNTA(G11:G217) -> 53 | F5: =+COUNTIF($I$11:$I$1048576,"Venta realizada") -> 6 | G5: =+COUNTIF($I$11:$I$1048576,"En curso") -> 11 | H5: =+COUNTIFS($G$11:$G$1048576,"<>",$I$11:$I$1048576,"Pendiente") -> 28 | I5: =+COUNTIF($I$11:$I$1048576,"ko") -> 8 | J5: =+SUM(F5:I5)=E5 -> TRUE
D6: =+D5/$C$5 -> 0 | E6: =+E5/$C$5 -> 1 | F6: =+F5/$E$5 -> 0.11320755 | G6: =+G5/$E$5 -> 0.20754717 | H6: =+H5/E5 -> 0.52830189 | I6: =+I5/E5 -> 0.1509434
H7: 9
H8: =+H7/G5 -> 0.81818182
B10: Id | C10: Nombre del lead | D10: CIF lead | E10: Integrador | F10: Modelo | G10: Fecha de generación lead | H10: Comercial asignado | I10: Estado de oferta | J10: Fecha de firma oferta | K10: Segmento | L10: Siguiente paso - Equipo gestión | M10: Fecha | N10: Siguiente paso comercial | O10: Fecha | P10: Venta mes | Q10: Tipos de productos | R10: Variable ACN
B11: 1 | C11: Autocars Barrera | D11: B60416302 | E11: MAXEN TECHNOLOGIES SL | F11: Tier 2 | G11: 45966 | H11: Didac | I11: Venta realizada | J11: 46011 | L11: N/A | M11: N/A | N11: N/A | O11: N/A | P11: 361 | Q11: 9 líneas móviles, 3 líneas FBB, Con Centralita | S11: dato no disponible - pedir a CB
B12: 2 | C12: Lead 10 | E12: MAXEN TECHNOLOGIES SL | F12: Tier 2 | G12: 45966 | H12: Didac | I12: Pendiente | L12: Pendiente lead | N12: Pendiente lead
B13: 3 | C13: Lead 11 | E13: MAXEN TECHNOLOGIES SL | F13: Tier 2 | G13: 45966 | H13: Didac | I13: Pendiente | L13: Pendiente lead | N13: Pendiente lead
B14: 4 | C14: Lead 12 | E14: MAXEN TECHNOLOGIES SL | F14: Tier 2 | G14: 45966 | H14: Didac | I14: Pendiente | L14: Pendiente lead | N14: Pendiente lead
B15: 5 | C15: Lead 13 | E15: MAXEN TECHNOLOGIES SL | F15: Tier 2 | G15: 45966 | H15: Didac | I15: Pendiente | L15: Pendiente lead | N15: Pendiente lead
B16: 6 | C16: Lead 14 | E16: MAXEN TECHNOLOGIES SL | F16: Tier 2 | G16: 45966 | H16: Didac | I16: Pendiente | L16: Pendiente lead | N16: Pendiente lead
B17: 7 | C17: Lead 15 | E17: MAXEN TECHNOLOGIES SL | F17: Tier 2 | G17: 45966 | H17: Didac | I17: Pendiente | L17: Pendiente lead | N17: Pendiente lead
B18: 8 | C18: Lead 16 | E18: MAXEN TECHNOLOGIES SL | F18: Tier 2 | G18: 45966 | H18: Didac | I18: Pendiente | L18: Pendiente lead | N18: Pendiente lead
B19: 9 | C19: Lead 17 | E19: MAXEN TECHNOLOGIES SL | F19: Tier 2 | G19: 45966 | H19: Didac | I19: Pendiente | L19: Pendiente lead | N19: Pendiente lead
B20: 10 | C20: Lead 18 | E20: MAXEN TECHNOLOGIES SL | F20: Tier 2 | G20: 45966 | H20: Didac | I20: Pendiente | L20: Pendiente lead | N20: Pendiente lead
B21: 11 | C21: Lead 19 | E21: MAXEN TECHNOLOGIES SL | F21: Tier 2 | G21: 45966 | H21: Didac | I21: Pendiente | L21: Pendiente lead | N21: Pendiente lead
B22: 12 | C22: Magnetron | D22: A28325785 | E22: OX-ONE NETWORKS SL | F22: Tier 1 | G22: 46374 | H22: Jonathan Macías | I22: KO | L22: N/A | M22: N/A | N22: Alta complejidad técnica | O22: N/A
B23: 13 | C23: RUT PERFIL | E23: MAXEN TECHNOLOGIES SL | F23: Tier 2 | G23: 46009 | H23: Didac | I23: KO | L23: Seguimiento | M23: 46069 | N23: Nueva oferta con centralita enviada a cliente 20.02. Pendiente re-contacto con cliente | O23: 46081
B24: 14 | C24: Grupo Calillo | D24: B85380186 | E24: COVERNET | F24: Tier 2 | G24: 46376 | H24: Didac | I24: Venta realizada | J24: 46053 | K24: SoHo | L24: N/A | M24: 46065 | N24: N/A | O24: N/A | P24: 176.59 | Q24: 4 líneas móviles, 1 líneas FBB, 3 dispositivos, 3 terminales, Sin Centralita
B25: 15 | C25: AREXPRESS | D25: B86054921 | E25: COVERNET | F25: Tier 2 | G25: 46376 | H25: Didac | I25: Venta realizada | J25: 46053 | K25: SoHo | L25: N/A | M25: 46065 | N25: N/A | O25: N/A | P25: 243 | Q25: 5 líneas móviles, 1 líneas FBB, 3 dispositivos, 3 terminales, Con Centralita
B26: 16 | C26: RAIL 28 | D26: B87253795 | E26: COVERNET | F26: Tier 2 | G26: 46376 | H26: Didac | I26: Venta realizada | J26: TBD | K26: PYME | L26: Ampliación PYME. Nos pasa info para darle el OK semana que viene. | M26: 46105 | N26: Pendiente bloqueo operativo por proceso ampliaciones. | O26: TBD | P26: 304 | Q26: 9 líneas móviles, 1 línea FBB, Con Centralita
B27: 17 | C27: VPLATAS ASESORES FISCALES | D27: B83768366 | E27: COVERNET | F27: Tier 2 | G27: 46376 | H27: Didac | I27: En curso | K27: PYME | L27: Seguimiento dudas a resolver | M27: 46101 | N27: Pendiente respuesta dudas por Didac | O27: 46101
B28: 18 | C28: Florflex (vecino RUTPERFIL) | E28: MAXEN TECHNOLOGIES SL | F28: Tier 2 | G28: 46054 | H28: Didac | I28: KO | L28: Seguimiento | N28: Pendiente respuesta cliente (Rut). Ligado a la oferta RUTPERFIL | O28: 46069
B29: 19 | C29: KEIM ECOPAINT IBERICA SL | E29: MAXEN TECHNOLOGIES SL | F29: Tier 2 | G29: 46062 | H29: Didac | I29: Pendiente | L29: Seguimiento | N29: Pendiente re-contacto con cliente semana 23.02 | O29: 46081
B30: 20 | C30: Asociación Apromar | D30: G78295748 | E36115814 (Cliente +O) | E30: Dataqu | F30: Tier 1 | G30: 46035 | H30: Jonathan Macías | I30: En curso | L30: Preparar webinar junto a Dataqu. Pendiente datos Maria Sebastián y oferta Carmen Sánchez para descuento especial para socios. | M30: 46097 | N30: =+L30 -> Preparar webinar junto a Dataqu. Pendiente datos Maria Sebastián y oferta Carmen Sánchez para descuento especial para socios. | O30: =+M30 -> 46097
B31: 21 | C31: Schreiber Foods | D31: B82690082 (Cliente hasta 12/2025) | E31: Dataqu | F31: Tier 1 | G31: 46035 | H31: Jonathan Macías | I31: Pendiente | L31: Sesión presencial en +O el 13.02 | M31: 46066 | N31: Sesión presencial en +O el 13.02 | O31: 46066
B32: 22 | C32: Armadora Pereira | D32: A36630028 | E32: Dataqu | F32: Tier 1 | G32: 46035 | H32: Jonathan Macías | I32: Pendiente | L32: Pendiente reactivación por reestructuración interna. | M32: 46070 | N32: Pendiente reorganización interna y ajuste de cuotas de pesca para activación de lead. | O32: 46136
B33: 23 | C33: Grupo Adarsa | D33: Múltiples CIFs [TBD] | E33: Dataqu | F33: Tier 1 | G33: 46035 | H33: Jonathan Macías | I33: En curso | L33: Seguimiento. Habla 18.03 con ellos para organizar sesión online | M33: 46099 | N33: Pendiente fecha por Dataqu para visita presencial (semana 16.03) | O33: 46097
B34: 24 | C34: Lead 1 | D34: B95601795 | E34: DuoIT | F34: Tier 1 | G34: 46058 | H34: Jonathan Macías | I34: KO | L34: Pendiente enviar oferta a Angel (Jonathan) | M34: 46073 | N34: Asegurar aplicación máximo descuento sobre oferta - Jonathan hace PT (15/20%). Miércoles Carmen Sanchez Arias debería pasar oferta a 24 meses (ahora la tiene Jonathan a 36) | O34: 46070
B35: 25 | C35: Lead 1 | E35: OX-ONE NETWORKS SL | F35: Tier 1 | G35: 46062 | H35: Jonathan Macías | I35: KO | L35: Mail con precio licencias google competitivas compartido con Gonzalo por Jonathan el 18.02. Pendiente respuesta | M35: 46071 | N35: Gestión con GGCC [ 27 licencias Business plus de Google (el cliente paga 25,3€ actualmente) + centralita cisco (ox-one hace mantenimiento). Acaba permanencia 01.03] - Pendiente feedback | O35: 46087
B36: 26 | C36: Conchi | E36: Cobitratel | F36: Tier 1 | G36: 46065 | H36: Nazaret | I36: KO | L36: Pendiente Nazaret | M36: 46071 | N36: Pendiente reagendar reunión (inicialmente esperada para viernes 27.02) | O36: 46084
B37: 27 | C37: Lead 2 | E37: OX-ONE NETWORKS SL | F37: Tier 1 | G37: 46023 | H37: Jonathan Macías | I37: Pendiente | L37: Pendiente recibir lead (despacho abogados) | M37: 46066 | N37: Pendiente recibir lead | O37: 46066
B38: 28 | C38: Lead 3 | E38: OX-ONE NETWORKS SL | F38: Tier 1 | G38: 46023 | H38: Jonathan Macías | I38: Pendiente | L38: Pendiente recibir lead | M38: 46066 | N38: Pendiente recibir lead | O38: 46066
B39: 29 | C39: Duino Inversiones SL | E39: OX-ONE NETWORKS SL | F39: Tier 1 | G39: 46070 | H39: Jonathan Macías | I39: En curso | L39: Seguimiento | M39: 46090 | N39: Jonathan le envía la oferta 18.02 - 11 líneas móviles + 2 fibras 1GB + backup. Visita comercial pendiente de agendar desde semana 23.02). Llamada lunes 09.03 | O39: 46090
B40: 30 | C40: Adrián | E40: Cobitratel | F40: Tier 1 | G40: 46072 | H40: Sergio Mena | I40: KO | L40: N/A | M40: N/A | N40: Cliente no interesado en oferta con descuento | O40: N/A
B41: 31 | C41: Wecolors | E41: MAXEN TECHNOLOGIES SL | F41: Tier 2 | G41: 46070 | H41: Didac | I41: Pendiente | L41: Seguimiento | N41: Pendiente reagendar visita comercial (inicialmente planeada para 24.02) | O41: 46083
B42: 32 | C42: Expansiva | E42: MAXEN TECHNOLOGIES SL | F42: Tier 2 | G42: 46076 | H42: Didac | I42: En curso | L42: Seguimiento. Preguntar a Fernando Cifo si podemos venderle M2M (SIM para alarmas) a una empresa de seguridad pyme. A razon del mail q le envió a Didac, va a ir él con el integrador y quiere saber si le podemos proporcionar eso | M42: 46104 | N42: Primera visita el 25.03 | O42: 46106
B43: 33 | C43: Llorens Vila | E43: MAXEN TECHNOLOGIES SL | F43: Tier 2 | G43: 46076 | H43: Didac | I43: En curso | L43: Seguimiento | M43: 46104 | N43: Oferta preparada. Visita el 25.03 | O43: 46106
B44: 34 | C44: Plantas VADA | E44: MAXEN TECHNOLOGIES SL | F44: Tier 2 | G44: 46076 | H44: Didac | I44: Pendiente | L44: Seguimiento | M44: 46104 | N44: Pendiente cliente. Conecta empresa con líneas móviles. | O44: 46104
B45: 35 | C45: Fernando Pedroviejo (Autoescuela San Cristobal) | D45: A19120385 | E45: Cobitratel | F45: Tier 1 | G45: 46083 | H45: Álvaro María García | I45: Venta realizada | L45: Seguimiento con Álvaro | M45: 46090 | N45: 35 movil, 5 conecta, centralita, 2 dispositivos, etc. Oferta presentada +9K anual. En revisión por cliente. | O45: 46090 | P45: =9072/12 -> 756 | Q45: 35 líneas móviles, 5 Conecta Pyme 1Gb + IP fija + Fibra Oro, 1 Fibra Big con centralita y grabación
B46: 36 | C46: AREXPRESS | D46: B86054921 | E46: COVERNET | F46: Tier 2 | G46: 46083 | H46: Didac | I46: Venta realizada | K46: SoHo | L46: Ampliación SoHo | M46: 46091 | N46: Ampliación hecha, penidente cliente | O46: 46091 | P46: 120
B47: 37 | C47: Lead 1 | E47: SISYTEC | F47: Tier 1 | G47: 46084 | H47: Sergio Mena | I47: En curso | L47: Pendiente integrador | M47: 46106 | N47: Contacto con integrador. Posible cliente que está con Movistar y aunque quiere seguir con ellos, necesita una línea adicional para instalar una VPN. Información enviada a integrador para que la trasladen al cliente. Pendiente feedback. | O47: 46106
B48: 38 | C48: URBEQUIPO, S.L. | D48: B81990764 | E48: COVERNET | F48: Tier 2 | G48: 46083 | H48: Didac | I48: Pendiente | L48: Seguimiento renove | M48: 46127 | N48: Pendiente vencimiento permanencia para hacer renove | O48: 46127
B49: 39 | C49: COVER SPI, S.L. | D49: B81846792 | E49: COVERNET | F49: Tier 2 | G49: 46083 | H49: Didac | I49: Pendiente | L49: Seguimiento renove | M49: 46127 | N49: Pendiente vencimiento permanencia para hacer renove | O49: 46127
B50: 40 | C50: COVER NET, S.L. | D50: B82483280 | E50: COVERNET | F50: Tier 2 | G50: 46083 | H50: Didac | I50: Pendiente | L50: Seguimiento renove | M50: 46127 | N50: Pendiente vencimiento permanencia para hacer renove | O50: 46127
B51: 41 | C51: Lead 1 | E51: Sictemas | F51: Tier 1 | G51: 46089 | H51: Jonathan Macías | I51: Pendiente | L51: Seguimiento potencial lead. Movido a abril. | M51: 46113 | N51: Pendiente recibir lead | O51: 46113
B52: 42 | C52: Lead 2 | E52: Sictemas | F52: Tier 1 | G52: 46089 | H52: Jonathan Macías | I52: Pendiente | L52: Seguimiento potencial lead. Movido a abril. | M52: 46113 | N52: Pendiente recibir lead | O52: 46113
B53: 43 | C53: Lead 3 | E53: Sictemas | F53: Tier 1 | G53: 46089 | H53: Jonathan Macías | I53: Pendiente | L53: Seguimiento potencial lead (líneas propias) | M53: 46143 | N53: Pendiente recibir lead | O53: 46143
B54: 44 | C54: Poleplants | E54: MAXEN TECHNOLOGIES SL | F54: Tier 2 | G54: 46090 | H54: Didac | I54: En curso | L54: Seguimiento | N54: Oferta preparada. Visita el 25.03 | O54: 46106
B55: 45 | C55: Clínica Dental Ortiz-Vigón | D55: B95027165 | E55: DuoIT | F55: Tier 1 | G55: 46090 | H55: Jonathan Macías | I55: En curso | L55: Lead recibido, seguimiento (cliente Euskaltel 2 clínicas) | M55: 46100 | N55: Preparando oferta | O55: 46100
B56: 46 | C56: Lead 3 | E56: DuoIT | F56: Tier 1 | G56: 46090 | H56: Jonathan Macías | I56: Pendiente | L56: Seguimiento potencial lead. Nos lo pasa Angel esta semana (09.03). | M56: 46094 | N56: Pendiente recibir lead | O56: 46094
B57: 47 | C57: Lead 1 | E57: MARISKALNET | F57: Tier 1 | G57: 46092 | H57: Jonathan Macías | I57: KO | L57: N/A | M57: N/A | N57: N/A | O57: N/A
B58: 48 | C58: Lead 2 | E58: MASRISKALNET | F58: Tier 1 | G58: 46092 | H58: Jonathan Macías | I58: Pendiente | L58: Seguimiento potencial lead. Nos lo pasa Emilio esta semana (09.03). | M58: 46094 | N58: Pendiente recibir lead | O58: 46094
B59: 49 | C59: Lead 3 | E59: MASRISKALNET | F59: Tier 1 | G59: 46092 | H59: Jonathan Macías | I59: Pendiente | L59: Seguimiento potencial lead. Nos lo pasa Emilio esta semana (09.03). | M59: 46094 | N59: Pendiente recibir lead | O59: 46094
B60: 50 | C60: Lead 1 | D60: Múltiples CIFs [5] | E60: PAPERLABS | F60: Tier 1 | G60: 46098 | H60: Jonathan Macías | I60: En curso | L60: Lead recibido, seguimiento | M60: 46098 | N60: Jonathan llama a Carlos para entender situación y preparar oferta. | O60: 46099
B61: 51 | C61: NSK | E61: OX-ONE NETWORKS SL | F61: Tier 1 | G61: 46098 | H61: Jonathan Macías | I61: En curso | L61: Seguimiento | M61: 46099 | N61: Jonathan prepara número rápido y llama a Gonzalo. | O61: 46099
B62: 52 | C62: Cliente de Argentona | E62: Lisot | F62: Tier 1 | G62: 46099 | H62: Jonathan Macías | I62: Pendiente | L62: Seguimiento - cliente elaborado la lista de requerimientos. | M62: 46107 | N62: Pendiente recibir lead | O62: 46107
B63: 53 | C63: Academia | E63: Aideea | F63: Tier 1 | G63: 46105 | H63: Jonathan Macías | I63: Pendiente | L63: Seguimiento - academia 2 sedes, pendiente confirmar por integrador | M63: 46108 | N63: Pendiente recibir lead | O63: 46108

Sheet Integradores Captados
B2: Funnel integradores
B3: 4.1 Activado: en proceso de firma
B4: 4.2 Activado: Firmado
B5: 3.1 Interés confirmado: pendiente agendar KO
B6: 3.2 Interés confirmado: agendado KO | P6: =+P8/L8 -> 0.41025641
H7: Integradores captados | I7: Integradores activados | J7: Contratos firmados | L7: Oportunidades en pipeline | N7: Visitas comerciales realizadas | P7: Ofertas realizadas | R7: Ventas formalizadas
H8: =+COUNTA(H13:H207) -> 34 | I8: =+COUNTIF(I13:I306,"Realizado")+COUNTIF(I13:I306,"En curso") -> 23 | J8: =+COUNTIF(J13:J306,"Realizado") -> 6 | L8: =+SUM(L13:L1048576) -> 39 | N8: =+SUM(N13:N1048576) -> 17 | P8: =+SUM(P13:P1048576) -> 16 | R8: =+SUM(R13:R1048576) -> 6
J9: =+J8/I8 -> 0.26086957 | N9: =+N8/L8 -> 0.43589744 | P9: =+P8/N8 -> 0.94117647 | R9: =+R8/P8 -> 0.375
F11: Primer contacto (telefónico) | G11: Acepta Sesión Informativa 1:1 (online) | H11: Acepta sesión Kick Off (presencial) | I11: ACTIVADO | T11: Formaciones
B12: # | C12: Integrador | D12: Estado | E12: Siguiente paso | F12: Hito #1: Contacto establecido | G12: Hito #2: Lead con interés | H12: Hito #3: Integrador captado | I12: Hito #4: Integrador activado | J12: Hito #5: Contrato firmado | K12: Modelo de colaboración | L12: Clientes potenciales identificados | M12: Visitas / clientes (%) | N12: Visitas comerciales (#) | O12: Ofertas / visitas (%) | P12: Ofertas (#) | Q12: Ventas / ofertas (%) | R12: Ventas (#) | S12: Responsable | T12: Producto SoHo | U12: Producto PYME (fijo y móvil) | V12: Producto PYME convergente (BIG PYME) | W12: Producto PYME (conecta empresas y ciberseguridad) | X12: Soluciones digitales PYME | Y12: Portal DHO | Z12: SIGNA | AA12: Mundo B2B PYME | AB12: Formulario BOC | AC12: Web Penalizaciones | AD12: ATAC | AE12: ATENCO | AF12: DEO, Parrilla, BT | AG12: PANGEA y ÁGORA | AH12: Alega
B13: =+_xlfn.XLOOKUP($C13,'Leads Priorizados INT'!$B:$B,'Leads Priorizados INT'!$A:$A) -> 85 | C13: OX-ONE NETWORKS SL | D13: =+_xlfn.XLOOKUP($C13,'Leads Priorizados INT'!$B:$B,'Leads Priorizados INT'!$E:$E) -> 4.1 Activado: en proceso de firma | E13: VVDD descarta la oportunidad. Pendiente recibir nuevos leads | F13: =+IF(OR($D13=$B$3,$D13=$B$4,$D13=$B$5,$D13=$B$6),"Realizado","Sin comenzar") -> Realizado | G13: =+IF(OR($D13=$B$3,$D13=$B$4,$D13=$B$5,$D13=$B$6),"Realizado","Sin comenzar") -> Realizado | H13: =+IF($D13=$B$5,"Pendiente",IF($D13=$B$6,"Agendado",IF(OR($D13=$B$3,$D13=$B$4),"Realizado"))) -> Realizado | I13: =+IF(OR($D13=$B$5,$D13=$B$6),"Sin comenzar",IF(OR($D13=$B$3,$D13=$B$4),"Realizado")) -> Realizado | J13: =+IF(OR($D13=$B$5,$D13=$B$6),"Sin comenzar",IF($D13=$B$3,"En curso",IF($D13=$B$4,"Realizado"))) -> En curso | K13: Tier 1 | L13: 3 | M13: 1 | N13: 1 | O13: 0 | P13: =IFERROR( COUNTIFS(Leads!$E$11:$E$5015,$C13,Leads!$I$11:$I$5015,"En curso") + COUNTIFS(Leads!$E$11:$E$5015,$C13,Leads!$I$11:$I$5015,"Venta realizada"),0) -> 2 | Q13: - | R13: =IFERROR( COUNTIFS(Leads!$E$11:$E$5015,$C13,Leads!$I$11:$I$5015,"Venta realizada"),0) -> 0 | S13: =+C13 -> OX-ONE NETWORKS SL | T13: Sin comenzar | U13: Sin comenzar | V13: Sin comenzar | W13: Sin comenzar | X13: Sin comenzar | Y13: Sin comenzar | Z13: Sin comenzar | AA13: Sin comenzar | AB13: Sin comenzar | AC13: Sin comenzar | AD13: Sin comenzar | AE13: Sin comenzar | AF13: Sin comenzar | AG13: Sin comenzar | AH13: Sin comenzar
B14: =+_xlfn.XLOOKUP($C14,'Leads Priorizados INT'!$B:$B,'Leads Priorizados INT'!$A:$A) -> 108 | C14: MAXEN TECHNOLOGIES SL | D14: =+_xlfn.XLOOKUP($C14,'Leads Priorizados INT'!$B:$B,'Leads Priorizados INT'!$E:$E) -> 4.2 Activado: Firmado | E14: Reunión con Didac 15.01 para ver más leads | F14: =+IF(OR($D14=$B$3,$D14=$B$4,$D14=$B$5,$D14=$B$6),"Realizado","Sin comenzar") -> Realizado | G14: =+IF(OR($D14=$B$3,$D14=$B$4,$D14=$B$5,$D14=$B$6),"Realizado","Sin comenzar") -> Realizado | H14: =+IF($D14=$B$5,"Pendiente",IF($D14=$B$6,"Agendado",IF(OR($D14=$B$3,$D14=$B$4),"Realizado"))) -> Realizado | I14: =+IF(OR($D14=$B$5,$D14=$B$6),"Sin comenzar",IF(OR($D14=$B$3,$D14=$B$4),"Realizado")) -> Realizado | J14: =+IF(OR($D14=$B$5,$D14=$B$6),"Sin comenzar",IF($D14=$B$3,"En curso",IF($D14=$B$4,"Realizado"))) -> Realizado | K14: Tier 2 | L14: 19 | M14: 0.1 | N14: 11 | O14: 1 | P14: =IFERROR( COUNTIFS(Leads!$E$11:$E$5015,$C14,Leads!$I$11:$I$5015,"En curso") + COUNTIFS(Leads!$E$11:$E$5015,$C14,Leads!$I$11:$I$5015,"Venta realizada"),0) -> 4 | Q14: 0.5 | R14: =IFERROR( COUNTIFS(Leads!$E$11:$E$5015,$C14,Leads!$I$11:$I$5015,"Venta realizada"),0) -> 1 | S14: =+B55 -> MAXEN TECHNOLOGIES SL | T14: Sin comenzar | U14: Realizado | V14: Sin comenzar | W14: Sin comenzar | X14: Realizado | Y14: Realizado | Z14: Realizado | AA14: Sin comenzar | AB14: Realizado | AC14: Sin comenzar | AD14: Sin comenzar | AE14: Sin comenzar | AF14: Sin comenzar | AG14: Sin comenzar | AH14: Sin comenzar
B15: =+_xlfn.XLOOKUP($C15,'Leads Priorizados INT'!$B:$B,'Leads Priorizados INT'!$A:$A) -> 114 | C15: PAPER LABS DESIGN ESP SL | D15: =+_xlfn.XLOOKUP($C15,'Leads Priorizados INT'!$B:$B,'Leads Priorizados INT'!$E:$E) -> 4.2 Activado: Firmado | E15: Agendar KickOff. Siguen agobiados con su BaU | F15: =+IF(OR($D15=$B$3,$D15=$B$4,$D15=$B$5,$D15=$B$6),"Realizado","Sin comenzar") -> Realizado | G15: =+IF(OR($D15=$B$3,$D15=$B$4,$D15=$B$5,$D15=$B$6),"Realizado","Sin comenzar") -> Realizado | H15: =+IF($D15=$B$5,"Pendiente",IF($D15=$B$6,"Agendado",IF(OR($D15=$B$3,$D15=$B$4),"Realizado"))) -> Realizado | I15: =+IF(OR($D15=$B$5,$D15=$B$6),"Sin comenzar",IF(OR($D15=$B$3,$D15=$B$4),"Realizado")) -> Realizado | J15: =+IF(OR($D15=$B$5,$D15=$B$6),"Sin comenzar",IF($D15=$B$3,"En curso",IF($D15=$B$4,"Realizado"))) -> Realizado | K15: TBC | L15: 0 | M15: - | N15: 0 | O15: - | P15: =IFERROR( COUNTIFS(Leads!$E$11:$E$5015,$C15,Leads!$I$11:$I$5015,"En curso") + COUNTIFS(Leads!$E$11:$E$5015,$C15,Leads!$I$11:$I$5015,"Venta realizada"),0) -> 0 | Q15: - | R15: =IFERROR( COUNTIFS(Leads!$E$11:$E$5015,$C15,Leads!$I$11:$I$5015,"Venta realizada"),0) -> 0 | S15: =+B56 -> PAPER LABS DESIGN ESP SL | T15: Sin comenzar | U15: Sin comenzar | V15: Sin comenzar | W15: Sin comenzar | X15: Sin comenzar | Y15: Sin comenzar | Z15: Sin comenzar | AA15: Sin comenzar | AB15: Sin comenzar | AC15: Sin comenzar | AD15: Sin comenzar | AE15: Sin comenzar | AF15: Sin comenzar | AG15: Sin comenzar | AH15: Sin comenzar
B16: =+_xlfn.XLOOKUP($C16,'Leads Priorizados INT'!$B:$B,'Leads Priorizados INT'!$A:$A) -> 147 | C16: DEITECO | D16: =+_xlfn.XLOOKUP($C16,'Leads Priorizados INT'!$B:$B,'Leads Priorizados INT'!$E:$E) -> 4.2 Activado: Firmado | E16: De momento, sin leads adicionales identificados | F16: =+IF(OR($D16=$B$3,$D16=$B$4,$D16=$B$5,$D16=$B$6),"Realizado","Sin comenzar") -> Realizado | G16: =+IF(OR($D16=$B$3,$D16=$B$4,$D16=$B$5,$D16=$B$6),"Realizado","Sin comenzar") -> Realizado | H16: =+IF($D16=$B$5,"Pendiente",IF($D16=$B$6,"Agendado",IF(OR($D16=$B$3,$D16=$B$4),"Realizado"))) -> Realizado | I16: =+IF(OR($D16=$B$5,$D16=$B$6),"Sin comenzar",IF(OR($D16=$B$3,$D16=$B$4),"Realizado")) -> Realizado | J16: =+IF(OR($D16=$B$5,$D16=$B$6),"Sin comenzar",IF($D16=$B$3,"En curso",IF($D16=$B$4,"Realizado"))) -> Realizado | K16: Tier 2 | L16: 0 | M16: 0 | N16: 0 | O16: - | P16: =IFERROR( COUNTIFS(Leads!$E$11:$E$5015,$C16,Leads!$I$11:$I$5015,"En curso") + COUNTIFS(Leads!$E$11:$E$5015,$C16,Leads!$I$11:$I$5015,"Venta realizada"),0) -> 0 | Q16: - | R16: =IFERROR( COUNTIFS(Leads!$E$11:$E$5015,$C16,Leads!$I$11:$I$5015,"Venta realizada"),0) -> 0 | S16: =+B57 -> DEITECO | T16: Sin comenzar | U16: Realizado | V16: Sin comenzar | W16: Sin comenzar | X16: Realizado | Y16: Realizado | Z16: Sin comenzar | AA16: Sin comenzar | AB16: Sin comenzar | AC16: Sin comenzar | AD16: Sin comenzar | AE16: Sin comenzar | AF16: Sin comenzar | AG16: Sin comenzar | AH16: Sin comenzar
B17: =+_xlfn.XLOOKUP($C17,'Leads Priorizados INT'!$B:$B,'Leads Priorizados INT'!$A:$A) -> 148 | C17: COVERNET | D17: =+_xlfn.XLOOKUP($C17,'Leads Priorizados INT'!$B:$B,'Leads Priorizados INT'!$E:$E) -> 4.2 Activado: Firmado | E17: 4 ofertas potenciales. Cover Net pide documentación a clientes para formalizar oferta y firmar. | F17: =+IF(OR($D17=$B$3,$D17=$B$4,$D17=$B$5,$D17=$B$6),"Realizado","Sin comenzar") -> Realizado | G17: =+IF(OR($D17=$B$3,$D17=$B$4,$D17=$B$5,$D17=$B$6),"Realizado","Sin comenzar") -> Realizado | H17: =+IF($D17=$B$5,"Pendiente",IF($D17=$B$6,"Agendado",IF(OR($D17=$B$3,$D17=$B$4),"Realizado"))) -> Realizado | I17: =+IF(OR($D17=$B$5,$D17=$B$6),"Sin comenzar",IF(OR($D17=$B$3,$D17=$B$4),"Realizado")) -> Realizado | J17: =+IF(OR($D17=$B$5,$D17=$B$6),"Sin comenzar",IF($D17=$B$3,"En curso",IF($D17=$B$4,"Realizado"))) -> Realizado | K17: Tier 2 | L17: 9 | M17: 1 | N17: 4 | O17: 1 | P17: =IFERROR( COUNTIFS(Leads!$E$11:$E$5015,$C17,Leads!$I$11:$I$5015,"En curso") + COUNTIFS(Leads!$E$11:$E$5015,$C17,Leads!$I$11:$I$5015,"Venta realizada"),0) -> 5 | Q17: 0 | R17: =IFERROR( COUNTIFS(Leads!$E$11:$E$5015,$C17,Leads!$I$11:$I$5015,"Venta realizada"),0) -> 4 | S17: =+B58 -> COVERNET | T17: Sin comenzar | U17: Realizado | V17: Sin comenzar | W17: Sin comenzar | X17: Realizado | Y17: Realizado | Z17: Realizado | AA17: Sin comenzar | AB17: Realizado | AC17: Sin comenzar | AD17: Sin comenzar | AE17: Sin comenzar | AF17: Sin comenzar | AG17: Sin comenzar | AH17: Sin comenzar
B18: =+_xlfn.XLOOKUP($C18,'Leads Priorizados INT'!$B:$B,'Leads Priorizados INT'!$A:$A) -> 654 | C18: SICTEMAS SERVICIOS INFORMATICOS INTEGRALES | D18: =+_xlfn.XLOOKUP($C18,'Leads Priorizados INT'!$B:$B,'Leads Priorizados INT'!$E:$E) -> 4.2 Activado: Firmado | E18: Recontacto 03.03 - Pendiente contrato firmado y leads | F18: =+IF(OR($D18=$B$3,$D18=$B$4,$D18=$B$5,$D18=$B$6),"Realizado","Sin comenzar") -> Realizado | G18: =+IF(OR($D18=$B$3,$D18=$B$4,$D18=$B$5,$D18=$B$6),"Realizado","Sin comenzar") -> Realizado | H18: =+IF($D18=$B$5,"Pendiente",IF($D18=$B$6,"Agendado",IF(OR($D18=$B$3,$D18=$B$4),"Realizado"))) -> Realizado | I18: =+IF(OR($D18=$B$5,$D18=$B$6),"Sin comenzar",IF(OR($D18=$B$3,$D18=$B$4),"Realizado")) -> Realizado | J18: =+IF(OR($D18=$B$5,$D18=$B$6),"Sin comenzar",IF($D18=$B$3,"En curso",IF($D18=$B$4,"Realizado"))) -> Realizado | K18: Tier 2 | L18: 0 | M18: - | N18: 0 | O18: - | P18: =IFERROR( COUNTIFS(Leads!$E$11:$E$5015,$C18,Leads!$I$11:$I$5015,"En curso") + COUNTIFS(Leads!$E$11:$E$5015,$C18,Leads!$I$11:$I$5015,"Venta realizada"),0) -> 0 | Q18: - | R18: =IFERROR( COUNTIFS(Leads!$E$11:$E$5015,$C18,Leads!$I$11:$I$5015,"Venta realizada"),0) -> 0 | S18: =+C18 -> SICTEMAS SERVICIOS INFORMATICOS INTEGRALES | T18: Sin comenzar | U18: Sin comenzar | V18: Sin comenzar | W18: Sin comenzar | X18: Sin comenzar | Y18: Sin comenzar | Z18: Sin comenzar | AA18: Sin comenzar | AB18: Sin comenzar | AC18: Sin comenzar | AD18: Sin comenzar | AE18: Sin comenzar | AF18: Sin comenzar | AG18: Sin comenzar | AH18: Sin comenzar
B19: =+_xlfn.XLOOKUP($C19,'Leads Priorizados INT'!$B:$B,'Leads Priorizados INT'!$A:$A) -> 668 | C19: Dataqu | D19: =+_xlfn.XLOOKUP($C19,'Leads Priorizados INT'!$B:$B,'Leads Priorizados INT'!$E:$E) -> 4.1 Activado: en proceso de firma | E19: Pendiente recibir ok final de Dataqu | F19: =+IF(OR($D19=$B$3,$D19=$B$4,$D19=$B$5,$D19=$B$6),"Realizado","Sin comenzar") -> Realizado | G19: =+IF(OR($D19=$B$3,$D19=$B$4,$D19=$B$5,$D19=$B$6),"Realizado","Sin comenzar") -> Realizado | H19: =+IF($D19=$B$5,"Pendiente",IF($D19=$B$6,"Agendado",IF(OR($D19=$B$3,$D19=$B$4),"Realizado"))) -> Realizado | I19: =+IF(OR($D19=$B$5,$D19=$B$6),"Sin comenzar",IF(OR($D19=$B$3,$D19=$B$4),"Realizado")) -> Realizado | J19: =+IF(OR($D19=$B$5,$D19=$B$6),"Sin comenzar",IF($D19=$B$3,"En curso",IF($D19=$B$4,"Realizado"))) -> En curso | K19: Tier 1 (antiguo LeadGen) | L19: 4 | M19: - | N19: 0 | O19: - | P19: =IFERROR( COUNTIFS(Leads!$E$11:$E$5015,$C19,Leads!$I$11:$I$5015,"En curso") + COUNTIFS(Leads!$E$11:$E$5015,$C19,Leads!$I$11:$I$5015,"Venta realizada"),0) -> 2 | Q19: - | R19: =IFERROR( COUNTIFS(Leads!$E$11:$E$5015,$C19,Leads!$I$11:$I$5015,"Venta realizada"),0) -> 0 | S19: =+C19 -> Dataqu | T19: Sin comenzar | U19: Sin comenzar | V19: Sin comenzar | W19: Sin comenzar | X19: Sin comenzar | Y19: Sin comenzar | Z19: Sin comenzar | AA19: Sin comenzar | AB19: Sin comenzar | AC19: Sin comenzar | AD19: Sin comenzar | AE19: Sin comenzar | AF19: Sin comenzar | AG19: Sin comenzar | AH19: Sin comenzar
B20: =+_xlfn.XLOOKUP($C20,'Leads Priorizados INT'!$B:$B,'Leads Priorizados INT'!$A:$A) -> 669 | C20: Ocvistas | D20: =+_xlfn.XLOOKUP($C20,'Leads Priorizados INT'!$B:$B,'Leads Priorizados INT'!$E:$E) -> 4.1 Activado: en proceso de firma | E20: Recontacto 02.03 - Pendiente contrato firmado y leads | F20: =+IF(OR($D20=$B$3,$D20=$B$4,$D20=$B$5,$D20=$B$6),"Realizado","Sin comenzar") -> Realizado | G20: =+IF(OR($D20=$B$3,$D20=$B$4,$D20=$B$5,$D20=$B$6),"Realizado","Sin comenzar") -> Realizado | H20: =+IF($D20=$B$5,"Pendiente",IF($D20=$B$6,"Agendado",IF(OR($D20=$B$3,$D20=$B$4),"Realizado"))) -> Realizado | I20: =+IF(OR($D20=$B$5,$D20=$B$6),"Sin comenzar",IF(OR($D20=$B$3,$D20=$B$4),"Realizado")) -> Realizado | J20: =+IF(OR($D20=$B$5,$D20=$B$6),"Sin comenzar",IF($D20=$B$3,"En curso",IF($D20=$B$4,"Realizado"))) -> En curso | K20: Tier 1 (antiguo LeadGen) | L20: 0 | M20: - | N20: 0 | O20: - | P20: =IFERROR( COUNTIFS(Leads!$E$11:$E$5015,$C20,Leads!$I$11:$I$5015,"En curso") + COUNTIFS(Leads!$E$11:$E$5015,$C20,Leads!$I$11:$I$5015,"Venta realizada"),0) -> 0 | Q20: - | R20: =IFERROR( COUNTIFS(Leads!$E$11:$E$5015,$C20,Leads!$I$11:$I$5015,"Venta realizada"),0) -> 0 | S20: Legal (+O) | T20: Sin comenzar | U20: Sin comenzar | V20: Sin comenzar | W20: Sin comenzar | X20: Sin comenzar | Y20: Sin comenzar | Z20: Sin comenzar | AA20: Sin comenzar | AB20: Sin comenzar | AC20: Sin comenzar | AD20: Sin comenzar | AE20: Sin comenzar | AF20: Sin comenzar | AG20: Sin comenzar | AH20: Sin comenzar
B21: =+_xlfn.XLOOKUP($C21,'Leads Priorizados INT'!$B:$B,'Leads Priorizados INT'!$A:$A) -> 670 | C21: DuoIT | D21: =+_xlfn.XLOOKUP($C21,'Leads Priorizados INT'!$B:$B,'Leads Priorizados INT'!$E:$E) -> 4.1 Activado: en proceso de firma | E21: Pendiente confirmación últimos cambios Tier 1 y leads a ofertar | F21: =+IF(OR($D21=$B$3,$D21=$B$4,$D21=$B$5,$D21=$B$6),"Realizado","Sin comenzar") -> Realizado | G21: =+IF(OR($D21=$B$3,$D21=$B$4,$D21=$B$5,$D21=$B$6),"Realizado","Sin comenzar") -> Realizado | H21: =+IF($D21=$B$5,"Pendiente",IF($D21=$B$6,"Agendado",IF(OR($D21=$B$3,$D21=$B$4),"Realizado"))) -> Realizado | I21: =+IF(OR($D21=$B$5,$D21=$B$6),"Sin comenzar",IF(OR($D21=$B$3,$D21=$B$4),"Realizado")) -> Realizado | J21: =+IF(OR($D21=$B$5,$D21=$B$6),"Sin comenzar",IF($D21=$B$3,"En curso",IF($D21=$B$4,"Realizado"))) -> En curso | K21: Tier 1 | L21: 1 | M21: 0 | N21: 0 | O21: - | P21: 1 | Q21: - | R21: =IFERROR( COUNTIFS(Leads!$E$11:$E$5015,$C21,Leads!$I$11:$I$5015,"Venta realizada"),0) -> 0 | S21: =+C21 -> DuoIT | T21: Sin comenzar | U21: Sin comenzar | V21: Sin comenzar | W21: Sin comenzar | X21: Sin comenzar | Y21: Sin comenzar | Z21: Sin comenzar | AA21: Sin comenzar | AB21: Sin comenzar | AC21: Sin comenzar | AD21: Sin comenzar | AE21: Sin comenzar | AF21: Sin comenzar | AG21: Sin comenzar | AH21: Sin comenzar
A22: x | B22: =+_xlfn.XLOOKUP($C22,'Leads Priorizados INT'!$B:$B,'Leads Priorizados INT'!$A:$A) -> 702 | C22: A4I | D22: =+_xlfn.XLOOKUP($C22,'Leads Priorizados INT'!$B:$B,'Leads Priorizados INT'!$E:$E) -> 3.3 Interés confirmado: on hold | E22: Pendiente agendar KickOff (sesión 1:1 online 9.01) | F22: =+IF(OR($D22=$B$3,$D22=$B$4,$D22=$B$5,$D22=$B$6),"Realizado","Sin comenzar") -> Sin comenzar | G22: =+IF(OR($D22=$B$3,$D22=$B$4,$D22=$B$5,$D22=$B$6),"Realizado","Sin comenzar") -> Sin comenzar | H22: =+IF($D22=$B$5,"Pendiente",IF($D22=$B$6,"Agendado",IF(OR($D22=$B$3,$D22=$B$4),"Realizado"))) -> FALSE | I22: =+IF(OR($D22=$B$5,$D22=$B$6),"Sin comenzar",IF(OR($D22=$B$3,$D22=$B$4),"Realizado")) -> FALSE | J22: =+IF(OR($D22=$B$5,$D22=$B$6),"Sin comenzar",IF($D22=$B$3,"En curso",IF($D22=$B$4,"Realizado"))) -> FALSE | K22: Sin comenzar | L22: Sin comenzar | M22: Sin comenzar | N22: Sin comenzar | O22: Sin comenzar | P22: Sin comenzar | Q22: Sin comenzar | R22: Sin comenzar | S22: =+B64 -> INFORNET SOLUCIONES INFORMATICAS S.L | T22: Sin comenzar | U22: Sin comenzar | V22: Sin comenzar | W22: Sin comenzar | X22: Sin comenzar | Y22: Sin comenzar | Z22: Sin comenzar | AA22: Sin comenzar | AB22: Sin comenzar | AC22: Sin comenzar | AD22: Sin comenzar | AE22: Sin comenzar | AF22: Sin comenzar | AG22: Sin comenzar | AH22: Sin comenzar
B23: =+_xlfn.XLOOKUP($C23,'Leads Priorizados INT'!$B:$B,'Leads Priorizados INT'!$A:$A) -> 736 | C23: FEDESOFT SL | D23: =+_xlfn.XLOOKUP($C23,'Leads Priorizados INT'!$B:$B,'Leads Priorizados INT'!$E:$E) -> 4.1 Activado: en proceso de firma | E23: Pendiente recibir info para firmar contrato y leads | F23: =+IF(OR($D23=$B$3,$D23=$B$4,$D23=$B$5,$D23=$B$6),"Realizado","Sin comenzar") -> Realizado | G23: =+IF(OR($D23=$B$3,$D23=$B$4,$D23=$B$5,$D23=$B$6),"Realizado","Sin comenzar") -> Realizado | H23: =+IF($D23=$B$5,"Pendiente",IF($D23=$B$6,"Agendado",IF(OR($D23=$B$3,$D23=$B$4),"Realizado"))) -> Realizado | I23: =+IF(OR($D23=$B$5,$D23=$B$6),"Sin comenzar",IF(OR($D23=$B$3,$D23=$B$4),"Realizado")) -> Realizado | J23: =+IF(OR($D23=$B$5,$D23=$B$6),"Sin comenzar",IF($D23=$B$3,"En curso",IF($D23=$B$4,"Realizado"))) -> En curso | K23: Tier 1 | L23: 0 | M23: - | N23: 0 | O23: - | P23: =IFERROR( COUNTIFS(Leads!$E$11:$E$5015,$C23,Leads!$I$11:$I$5015,"En curso") + COUNTIFS(Leads!$E$11:$E$5015,$C23,Leads!$I$11:$I$5015,"Venta realizada"),0) -> 0 | Q23: - | R23: =IFERROR( COUNTIFS(Leads!$E$11:$E$5015,$C23,Leads!$I$11:$I$5015,"Venta realizada"),0) -> 0 | S23: =+C23 -> FEDESOFT SL | T23: Sin comenzar | U23: Sin comenzar | V23: Sin comenzar | W23: Sin comenzar | X23: Sin comenzar | Y23: Sin comenzar | Z23: Sin comenzar | AA23: Sin comenzar | AB23: Sin comenzar | AC23: Sin comenzar | AD23: Sin comenzar | AE23: Sin comenzar | AF23: Sin comenzar | AG23: Sin comenzar | AH23: Sin comenzar
B24: =+_xlfn.XLOOKUP($C24,'Leads Priorizados INT'!$B:$B,'Leads Priorizados INT'!$A:$A) -> 757 | C24: INFORNET SOLUCIONES INFORMATICAS S.L | D24: =+_xlfn.XLOOKUP($C24,'Leads Priorizados INT'!$B:$B,'Leads Priorizados INT'!$E:$E) -> 4.1 Activado: en proceso de firma | E24: Pendiente recibir info para firmar contrato y leads | F24: =+IF(OR($D24=$B$3,$D24=$B$4,$D24=$B$5,$D24=$B$6),"Realizado","Sin comenzar") -> Realizado | G24: =+IF(OR($D24=$B$3,$D24=$B$4,$D24=$B$5,$D24=$B$6),"Realizado","Sin comenzar") -> Realizado | H24: =+IF($D24=$B$5,"Pendiente",IF($D24=$B$6,"Agendado",IF(OR($D24=$B$3,$D24=$B$4),"Realizado"))) -> Realizado | I24: =+IF(OR($D24=$B$5,$D24=$B$6),"Sin comenzar",IF(OR($D24=$B$3,$D24=$B$4),"Realizado")) -> Realizado | J24: =+IF(OR($D24=$B$5,$D24=$B$6),"Sin comenzar",IF($D24=$B$3,"En curso",IF($D24=$B$4,"Realizado"))) -> En curso | K24: Tier 1 | L24: 0 | M24: - | N24: 0 | O24: - | P24: =IFERROR( COUNTIFS(Leads!$E$11:$E$5015,$C24,Leads!$I$11:$I$5015,"En curso") + COUNTIFS(Leads!$E$11:$E$5015,$C24,Leads!$I$11:$I$5015,"Venta realizada"),0) -> 0 | Q24: - | R24: =IFERROR( COUNTIFS(Leads!$E$11:$E$5015,$C24,Leads!$I$11:$I$5015,"Venta realizada"),0) -> 0 | S24: =+C24 -> INFORNET SOLUCIONES INFORMATICAS S.L | T24: Sin comenzar | U24: Sin comenzar | V24: Sin comenzar | W24: Sin comenzar | X24: Sin comenzar | Y24: Sin comenzar | Z24: Sin comenzar | AA24: Sin comenzar | AB24: Sin comenzar | AC24: Sin comenzar | AD24: Sin comenzar | AE24: Sin comenzar | AF24: Sin comenzar | AG24: Sin comenzar | AH24: Sin comenzar
B25: =+_xlfn.XLOOKUP($C25,'Leads Priorizados INT'!$B:$B,'Leads Priorizados INT'!$A:$A) -> 919 | C25: Micro Sip | D25: =+_xlfn.XLOOKUP($C25,'Leads Priorizados INT'!$B:$B,'Leads Priorizados INT'!$E:$E) -> 4.1 Activado: en proceso de firma | E25: Pendiente KO | F25: =+IF(OR($D25=$B$3,$D25=$B$4,$D25=$B$5,$D25=$B$6),"Realizado","Sin comenzar") -> Realizado | G25: =+IF(OR($D25=$B$3,$D25=$B$4,$D25=$B$5,$D25=$B$6),"Realizado","Sin comenzar") -> Realizado | H25: =+IF($D25=$B$5,"Pendiente",IF($D25=$B$6,"Agendado",IF(OR($D25=$B$3,$D25=$B$4),"Realizado"))) -> Realizado | I25: =+IF(OR($D25=$B$5,$D25=$B$6),"Sin comenzar",IF(OR($D25=$B$3,$D25=$B$4),"Realizado")) -> Realizado | J25: =+IF(OR($D25=$B$5,$D25=$B$6),"Sin comenzar",IF($D25=$B$3,"En curso",IF($D25=$B$4,"Realizado"))) -> En curso | K25: TBC | L25: Sin comenzar | M25: Sin comenzar | N25: Sin comenzar | O25: Sin comenzar | P25: Sin comenzar | Q25: Sin comenzar | R25: Sin comenzar | S25: =+B68 -> Cobitratel | T25: Sin comenzar | U25: Sin comenzar | V25: Sin comenzar | W25: Sin comenzar | X25: Sin comenzar | Y25: Sin comenzar | Z25: Sin comenzar | AA25: Sin comenzar | AB25: Sin comenzar | AC25: Sin comenzar | AD25: Sin comenzar | AE25: Sin comenzar | AF25: Sin comenzar | AG25: Sin comenzar | AH25: Sin comenzar
B26: =+_xlfn.XLOOKUP($C26,'Leads Priorizados INT'!$B:$B,'Leads Priorizados INT'!$A:$A) -> 1381 | C26: LOOMIS SPAIN DIGITAL SERVICES SL. | D26: =+_xlfn.XLOOKUP($C26,'Leads Priorizados INT'!$B:$B,'Leads Priorizados INT'!$E:$E) -> 98. Churn | E26: No alineado con estrategia acutal | F26: =+IF(OR($D26=$B$3,$D26=$B$4,$D26=$B$5,$D26=$B$6),"Realizado","Sin comenzar") -> Sin comenzar | G26: =+IF(OR($D26=$B$3,$D26=$B$4,$D26=$B$5,$D26=$B$6),"Realizado","Sin comenzar") -> Sin comenzar | H26: =+IF($D26=$B$5,"Pendiente",IF($D26=$B$6,"Agendado",IF(OR($D26=$B$3,$D26=$B$4),"Realizado"))) -> FALSE | I26: =+IF(OR($D26=$B$5,$D26=$B$6),"Sin comenzar",IF(OR($D26=$B$3,$D26=$B$4),"Realizado")) -> FALSE | J26: =+IF(OR($D26=$B$5,$D26=$B$6),"Sin comenzar",IF($D26=$B$3,"En curso",IF($D26=$B$4,"Realizado"))) -> FALSE | K26: Tier 1 | L26: 0 | M26: - | N26: 0 | O26: - | P26: =IFERROR( COUNTIFS(Leads!$E$11:$E$5015,$C26,Leads!$I$11:$I$5015,"En curso") + COUNTIFS(Leads!$E$11:$E$5015,$C26,Leads!$I$11:$I$5015,"Venta realizada"),0) -> 0 | Q26: - | R26: =IFERROR( COUNTIFS(Leads!$E$11:$E$5015,$C26,Leads!$I$11:$I$5015,"Venta realizada"),0) -> 0 | S26: =+C26 -> LOOMIS SPAIN DIGITAL SERVICES SL. | T26: Sin comenzar | U26: Sin comenzar | V26: Sin comenzar | W26: Sin comenzar | X26: Sin comenzar | Y26: Sin comenzar | Z26: Sin comenzar | AA26: Sin comenzar | AB26: Sin comenzar | AC26: Sin comenzar | AD26: Sin comenzar | AE26: Sin comenzar | AF26: Sin comenzar | AG26: Sin comenzar | AH26: Sin comenzar
B27: =+_xlfn.XLOOKUP($C27,'Leads Priorizados INT'!$B:$B,'Leads Priorizados INT'!$A:$A) -> 1431 | C27: Cobitratel | D27: =+_xlfn.XLOOKUP($C27,'Leads Priorizados INT'!$B:$B,'Leads Priorizados INT'!$E:$E) -> 4.1 Activado: en proceso de firma | E27: Pendiente confirmación últimos cambios Tier 1 y leads a ofertar | F27: =+IF(OR($D27=$B$3,$D27=$B$4,$D27=$B$5,$D27=$B$6),"Realizado","Sin comenzar") -> Realizado | G27: =+IF(OR($D27=$B$3,$D27=$B$4,$D27=$B$5,$D27=$B$6),"Realizado","Sin comenzar") -> Realizado | H27: =+IF($D27=$B$5,"Pendiente",IF($D27=$B$6,"Agendado",IF(OR($D27=$B$3,$D27=$B$4),"Realizado"))) -> Realizado | I27: =+IF(OR($D27=$B$5,$D27=$B$6),"Sin comenzar",IF(OR($D27=$B$3,$D27=$B$4),"Realizado")) -> Realizado | J27: =+IF(OR($D27=$B$5,$D27=$B$6),"Sin comenzar",IF($D27=$B$3,"En curso",IF($D27=$B$4,"Realizado"))) -> En curso | K27: Tier 1 | L27: 2 | M27: Churn | N27: 1 | O27: Churn | P27: 2 | Q27: Churn | R27: =IFERROR( COUNTIFS(Leads!$E$11:$E$5015,$C27,Leads!$I$11:$I$5015,"Venta realizada"),0) -> 1 | S27: =+C27 -> Cobitratel | T27: Sin comenzar | U27: Sin comenzar | V27: Sin comenzar | W27: Sin comenzar | X27: Sin comenzar | Y27: Sin comenzar | Z27: Sin comenzar | AA27: Sin comenzar | AB27: Sin comenzar | AC27: Sin comenzar | AD27: Sin comenzar | AE27: Sin comenzar | AF27: Sin comenzar | AG27: Sin comenzar | AH27: Sin comenzar
A28: x | B28: =+_xlfn.XLOOKUP($C28,'Leads Priorizados INT'!$B:$B,'Leads Priorizados INT'!$A:$A) -> 541 | C28: NEXT MOBILITY SOLUTIONS SL | D28: =+_xlfn.XLOOKUP($C28,'Leads Priorizados INT'!$B:$B,'Leads Priorizados INT'!$E:$E) -> 3.3 Interés confirmado: on hold | E28: Pendiente respuesta para agendar KO (enviado mail 8.01) | F28: =+IF(OR($D28=$B$3,$D28=$B$4,$D28=$B$5,$D28=$B$6),"Realizado","Sin comenzar") -> Sin comenzar | G28: =+IF(OR($D28=$B$3,$D28=$B$4,$D28=$B$5,$D28=$B$6),"Realizado","Sin comenzar") -> Sin comenzar | H28: =+IF($D28=$B$5,"Pendiente",IF($D28=$B$6,"Agendado",IF(OR($D28=$B$3,$D28=$B$4),"Realizado"))) -> FALSE | I28: =+IF(OR($D28=$B$5,$D28=$B$6),"Sin comenzar",IF(OR($D28=$B$3,$D28=$B$4),"Realizado")) -> FALSE | J28: =+IF(OR($D28=$B$5,$D28=$B$6),"Sin comenzar",IF($D28=$B$3,"En curso",IF($D28=$B$4,"Realizado"))) -> FALSE | K28: TBC | L28: Sin comenzar | M28: Sin comenzar | N28: Sin comenzar | O28: Sin comenzar | P28: Sin comenzar | Q28: Sin comenzar | R28: Sin comenzar | S28: =+C28 -> NEXT MOBILITY SOLUTIONS SL | T28: Sin comenzar | U28: Sin comenzar | V28: Sin comenzar | W28: Sin comenzar | X28: Sin comenzar | Y28: Sin comenzar | Z28: Sin comenzar | AA28: Sin comenzar | AB28: Sin comenzar | AC28: Sin comenzar | AD28: Sin comenzar | AE28: Sin comenzar | AF28: Sin comenzar | AG28: Sin comenzar | AH28: Sin comenzar
B29: =+_xlfn.XLOOKUP($C29,'Leads Priorizados INT'!$B:$B,'Leads Priorizados INT'!$A:$A) -> 1090 | C29: TWISTIC DIGITAL, SOCIEDAD LIMITADA. | D29: =+_xlfn.XLOOKUP($C29,'Leads Priorizados INT'!$B:$B,'Leads Priorizados INT'!$E:$E) -> 98. Churn | E29: No ven oportunidad de colaboración | F29: =+IF(OR($D29=$B$3,$D29=$B$4,$D29=$B$5,$D29=$B$6),"Realizado","Sin comenzar") -> Sin comenzar | G29: =+IF(OR($D29=$B$3,$D29=$B$4,$D29=$B$5,$D29=$B$6),"Realizado","Sin comenzar") -> Sin comenzar | H29: =+IF($D29=$B$5,"Pendiente",IF($D29=$B$6,"Agendado",IF(OR($D29=$B$3,$D29=$B$4),"Realizado"))) -> FALSE | I29: =+IF(OR($D29=$B$5,$D29=$B$6),"Sin comenzar",IF(OR($D29=$B$3,$D29=$B$4),"Realizado")) -> FALSE | J29: =+IF(OR($D29=$B$5,$D29=$B$6),"Sin comenzar",IF($D29=$B$3,"En curso",IF($D29=$B$4,"Realizado"))) -> FALSE | K29: TBC | L29: Sin comenzar | M29: Sin comenzar | N29: Sin comenzar | O29: Sin comenzar | P29: Sin comenzar | Q29: Sin comenzar | R29: Sin comenzar | S29: =+C29 -> TWISTIC DIGITAL, SOCIEDAD LIMITADA. | T29: Sin comenzar | U29: Sin comenzar | V29: Sin comenzar | W29: Sin comenzar | X29: Sin comenzar | Y29: Sin comenzar | Z29: Sin comenzar | AA29: Sin comenzar | AB29: Sin comenzar | AC29: Sin comenzar | AD29: Sin comenzar | AE29: Sin comenzar | AF29: Sin comenzar | AG29: Sin comenzar | AH29: Sin comenzar
B30: =+_xlfn.XLOOKUP($C30,'Leads Priorizados INT'!$B:$B,'Leads Priorizados INT'!$A:$A) -> 1514 | C30: TECNOLOGIA ESTRATEGICA | D30: =+_xlfn.XLOOKUP($C30,'Leads Priorizados INT'!$B:$B,'Leads Priorizados INT'!$E:$E) -> 98. Churn | E30: Recontacto 03.03 - Sin respuesta | F30: =+IF(OR($D30=$B$3,$D30=$B$4,$D30=$B$5,$D30=$B$6),"Realizado","Sin comenzar") -> Sin comenzar | G30: =+IF(OR($D30=$B$3,$D30=$B$4,$D30=$B$5,$D30=$B$6),"Realizado","Sin comenzar") -> Sin comenzar | H30: =+IF($D30=$B$5,"Pendiente",IF($D30=$B$6,"Agendado",IF(OR($D30=$B$3,$D30=$B$4),"Realizado"))) -> FALSE | I30: =+IF(OR($D30=$B$5,$D30=$B$6),"Sin comenzar",IF(OR($D30=$B$3,$D30=$B$4),"Realizado")) -> FALSE | J30: =+IF(OR($D30=$B$5,$D30=$B$6),"Sin comenzar",IF($D30=$B$3,"En curso",IF($D30=$B$4,"Realizado"))) -> FALSE | K30: TBC | L30: Sin comenzar | N30: Sin comenzar | P30: Sin comenzar | Q30: Sin comenzar | R30: Sin comenzar | S30: =+C30 -> TECNOLOGIA ESTRATEGICA | T30: Sin comenzar | U30: Sin comenzar | V30: Sin comenzar | W30: Sin comenzar | X30: Sin comenzar | Y30: Sin comenzar | Z30: Sin comenzar | AA30: Sin comenzar | AB30: Sin comenzar | AC30: Sin comenzar | AD30: Sin comenzar | AE30: Sin comenzar | AF30: Sin comenzar | AG30: Sin comenzar | AH30: Sin comenzar
B31: =+_xlfn.XLOOKUP($C31,'Leads Priorizados INT'!$B:$B,'Leads Priorizados INT'!$A:$A) -> 1405 | C31: SISYTEC NETWORKS SL. | D31: =+_xlfn.XLOOKUP($C31,'Leads Priorizados INT'!$B:$B,'Leads Priorizados INT'!$E:$E) -> 4.1 Activado: en proceso de firma | E31: Recontacto 03.03 - Pendiente contrato firmado y leads. Nos ha mandado 1 frio | F31: =+IF(OR($D31=$B$3,$D31=$B$4,$D31=$B$5,$D31=$B$6),"Realizado","Sin comenzar") -> Realizado | G31: =+IF(OR($D31=$B$3,$D31=$B$4,$D31=$B$5,$D31=$B$6),"Realizado","Sin comenzar") -> Realizado | H31: =+IF($D31=$B$5,"Pendiente",IF($D31=$B$6,"Agendado",IF(OR($D31=$B$3,$D31=$B$4),"Realizado"))) -> Realizado | I31: =+IF(OR($D31=$B$5,$D31=$B$6),"Sin comenzar",IF(OR($D31=$B$3,$D31=$B$4),"Realizado")) -> Realizado | J31: =+IF(OR($D31=$B$5,$D31=$B$6),"Sin comenzar",IF($D31=$B$3,"En curso",IF($D31=$B$4,"Realizado"))) -> En curso | K31: TBC | L31: 1 | N31: Sin comenzar | P31: Sin comenzar | Q31: Sin comenzar | R31: Sin comenzar | S31: =+C31 -> SISYTEC NETWORKS SL. | T31: Sin comenzar | U31: Sin comenzar | V31: Sin comenzar | W31: Sin comenzar | X31: Sin comenzar | Y31: Sin comenzar | Z31: Sin comenzar | AA31: Sin comenzar | AB31: Sin comenzar | AC31: Sin comenzar | AD31: Sin comenzar | AE31: Sin comenzar | AF31: Sin comenzar | AG31: Sin comenzar | AH31: Sin comenzar
B32: =+_xlfn.XLOOKUP($C32,'Leads Priorizados INT'!$B:$B,'Leads Priorizados INT'!$A:$A) -> 974 | C32: AUDINFOR SYSTEM SL. | D32: =+_xlfn.XLOOKUP($C32,'Leads Priorizados INT'!$B:$B,'Leads Priorizados INT'!$E:$E) -> 4.1 Activado: en proceso de firma | E32: Pendiente contrato firmado y leads | F32: =+IF(OR($D32=$B$3,$D32=$B$4,$D32=$B$5,$D32=$B$6),"Realizado","Sin comenzar") -> Realizado | G32: =+IF(OR($D32=$B$3,$D32=$B$4,$D32=$B$5,$D32=$B$6),"Realizado","Sin comenzar") -> Realizado | H32: =+IF($D32=$B$5,"Pendiente",IF($D32=$B$6,"Agendado",IF(OR($D32=$B$3,$D32=$B$4),"Realizado"))) -> Realizado | I32: =+IF(OR($D32=$B$5,$D32=$B$6),"Sin comenzar",IF(OR($D32=$B$3,$D32=$B$4),"Realizado")) -> Realizado | J32: =+IF(OR($D32=$B$5,$D32=$B$6),"Sin comenzar",IF($D32=$B$3,"En curso",IF($D32=$B$4,"Realizado"))) -> En curso | K32: TBC | L32: Sin comenzar | N32: Sin comenzar | P32: Sin comenzar | Q32: Sin comenzar | R32: Sin comenzar | S32: =+C32 -> AUDINFOR SYSTEM SL. | T32: Sin comenzar | U32: Sin comenzar | V32: Sin comenzar | W32: Sin comenzar | X32: Sin comenzar | Y32: Sin comenzar | Z32: Sin comenzar | AA32: Sin comenzar | AB32: Sin comenzar | AC32: Sin comenzar | AD32: Sin comenzar | AE32: Sin comenzar | AF32: Sin comenzar | AG32: Sin comenzar | AH32: Sin comenzar
B33: =+_xlfn.XLOOKUP($C33,'Leads Priorizados INT'!$B:$B,'Leads Priorizados INT'!$A:$A) -> 1571 | C33: Mariskalnet Informática | D33: =+_xlfn.XLOOKUP($C33,'Leads Priorizados INT'!$B:$B,'Leads Priorizados INT'!$E:$E) -> 4.1 Activado: en proceso de firma | E33: Recontacto 03.03 - Pendiente KO y leads. Respuesta: comentar semana que viene | F33: =+IF(OR($D33=$B$3,$D33=$B$4,$D33=$B$5,$D33=$B$6),"Realizado","Sin comenzar") -> Realizado | G33: =+IF(OR($D33=$B$3,$D33=$B$4,$D33=$B$5,$D33=$B$6),"Realizado","Sin comenzar") -> Realizado | H33: =+IF($D33=$B$5,"Pendiente",IF($D33=$B$6,"Agendado",IF(OR($D33=$B$3,$D33=$B$4),"Realizado"))) -> Realizado | I33: =+IF(OR($D33=$B$5,$D33=$B$6),"Sin comenzar",IF(OR($D33=$B$3,$D33=$B$4),"Realizado")) -> Realizado | J33: =+IF(OR($D33=$B$5,$D33=$B$6),"Sin comenzar",IF($D33=$B$3,"En curso",IF($D33=$B$4,"Realizado"))) -> En curso | K33: TBC | L33: Sin comenzar | N33: Sin comenzar | P33: Sin comenzar | Q33: Sin comenzar | R33: Sin comenzar | S33: =+C33 -> Mariskalnet Informática | T33: Sin comenzar | U33: Sin comenzar | V33: Sin comenzar | W33: Sin comenzar | X33: Sin comenzar | Y33: Sin comenzar | Z33: Sin comenzar | AA33: Sin comenzar | AB33: Sin comenzar | AC33: Sin comenzar | AD33: Sin comenzar | AE33: Sin comenzar | AF33: Sin comenzar | AG33: Sin comenzar | AH33: Sin comenzar
B34: =+_xlfn.XLOOKUP($C34,'Leads Priorizados INT'!$B:$B,'Leads Priorizados INT'!$A:$A) -> 1599 | C34: DOSYS | D34: =+_xlfn.XLOOKUP($C34,'Leads Priorizados INT'!$B:$B,'Leads Priorizados INT'!$E:$E) -> 4.1 Activado: en proceso de firma | E34: Recontacto 03.03 - Pendiente contrato firmado y leads | F34: =+IF(OR($D34=$B$3,$D34=$B$4,$D34=$B$5,$D34=$B$6),"Realizado","Sin comenzar") -> Realizado | G34: =+IF(OR($D34=$B$3,$D34=$B$4,$D34=$B$5,$D34=$B$6),"Realizado","Sin comenzar") -> Realizado | H34: =+IF($D34=$B$5,"Pendiente",IF($D34=$B$6,"Agendado",IF(OR($D34=$B$3,$D34=$B$4),"Realizado"))) -> Realizado | I34: =+IF(OR($D34=$B$5,$D34=$B$6),"Sin comenzar",IF(OR($D34=$B$3,$D34=$B$4),"Realizado")) -> Realizado | J34: =+IF(OR($D34=$B$5,$D34=$B$6),"Sin comenzar",IF($D34=$B$3,"En curso",IF($D34=$B$4,"Realizado"))) -> En curso | K34: TBC | L34: Sin comenzar | N34: Sin comenzar | P34: Sin comenzar | Q34: Sin comenzar | R34: Sin comenzar | S34: =+C34 -> DOSYS | T34: Sin comenzar | U34: Sin comenzar | V34: Sin comenzar | W34: Sin comenzar | X34: Sin comenzar | Y34: Sin comenzar | Z34: Sin comenzar | AA34: Sin comenzar | AB34: Sin comenzar | AC34: Sin comenzar | AD34: Sin comenzar | AE34: Sin comenzar | AF34: Sin comenzar | AG34: Sin comenzar | AH34: Sin comenzar
B35: =+_xlfn.XLOOKUP($C35,'Leads Priorizados INT'!$B:$B,'Leads Priorizados INT'!$A:$A) -> 1637 | C35: GNUO Consultores | D35: =+_xlfn.XLOOKUP($C35,'Leads Priorizados INT'!$B:$B,'Leads Priorizados INT'!$E:$E) -> 4.1 Activado: en proceso de firma | E35: Recontacto 03.03 - Pendiente KO y leads | F35: =+IF(OR($D35=$B$3,$D35=$B$4,$D35=$B$5,$D35=$B$6),"Realizado","Sin comenzar") -> Realizado | G35: =+IF(OR($D35=$B$3,$D35=$B$4,$D35=$B$5,$D35=$B$6),"Realizado","Sin comenzar") -> Realizado | H35: =+IF($D35=$B$5,"Pendiente",IF($D35=$B$6,"Agendado",IF(OR($D35=$B$3,$D35=$B$4),"Realizado"))) -> Realizado | I35: =+IF(OR($D35=$B$5,$D35=$B$6),"Sin comenzar",IF(OR($D35=$B$3,$D35=$B$4),"Realizado")) -> Realizado | J35: =+IF(OR($D35=$B$5,$D35=$B$6),"Sin comenzar",IF($D35=$B$3,"En curso",IF($D35=$B$4,"Realizado"))) -> En curso | K35: TBC | L35: Sin comenzar | N35: Sin comenzar | P35: Sin comenzar | Q35: Sin comenzar | R35: Sin comenzar | S35: =+C35 -> GNUO Consultores | T35: Sin comenzar | U35: Sin comenzar | V35: Sin comenzar | W35: Sin comenzar | X35: Sin comenzar | Y35: Sin comenzar | Z35: Sin comenzar | AA35: Sin comenzar | AB35: Sin comenzar | AC35: Sin comenzar | AD35: Sin comenzar | AE35: Sin comenzar | AF35: Sin comenzar | AG35: Sin comenzar | AH35: Sin comenzar
B36: =+_xlfn.XLOOKUP($C36,'Leads Priorizados INT'!$B:$B,'Leads Priorizados INT'!$A:$A) -> 1500 | C36: {=_xlfn.LET( _xlpm.nuevos, B60:B87, _xlpm.base, $C$13:C35, _xlfn._xlws.FILTER( _xlpm.nuevos, (_xlpm.nuevos<>"")*ISNA(MATCH(_xlpm.nuevos, _xlpm.base, 0)), "" ) )} -> PC SERVICES | D36: =+_xlfn.XLOOKUP($C36,'Leads Priorizados INT'!$B:$B,'Leads Priorizados INT'!$E:$E) -> 3.2 Interés confirmado: agendado KO | E36: KO el 06.03 | F36: =+IF(OR($D36=$B$3,$D36=$B$4,$D36=$B$5,$D36=$B$6),"Realizado","Sin comenzar") -> Realizado | G36: =+IF(OR($D36=$B$3,$D36=$B$4,$D36=$B$5,$D36=$B$6),"Realizado","Sin comenzar") -> Realizado | H36: =+IF($D36=$B$5,"Pendiente",IF($D36=$B$6,"Agendado",IF(OR($D36=$B$3,$D36=$B$4),"Realizado"))) -> Agendado | I36: =+IF(OR($D36=$B$5,$D36=$B$6),"Sin comenzar",IF(OR($D36=$B$3,$D36=$B$4),"Realizado")) -> Sin comenzar | J36: =+IF(OR($D36=$B$5,$D36=$B$6),"Sin comenzar",IF($D36=$B$3,"En curso",IF($D36=$B$4,"Realizado"))) -> Sin comenzar | K36: TBC | L36: Sin comenzar | N36: Sin comenzar | P36: Sin comenzar | Q36: Sin comenzar | R36: Sin comenzar | S36: =+C36 -> PC SERVICES | T36: Sin comenzar | U36: Sin comenzar | V36: Sin comenzar | W36: Sin comenzar | X36: Sin comenzar | Y36: Sin comenzar | Z36: Sin comenzar | AA36: Sin comenzar | AB36: Sin comenzar | AC36: Sin comenzar | AD36: Sin comenzar | AE36: Sin comenzar | AF36: Sin comenzar | AG36: Sin comenzar | AH36: Sin comenzar
B37: =+_xlfn.XLOOKUP($C37,'Leads Priorizados INT'!$B:$B,'Leads Priorizados INT'!$A:$A) -> 1668 | C37: DurnIA Tecnologías de la Información, S.L. | D37: =+_xlfn.XLOOKUP($C37,'Leads Priorizados INT'!$B:$B,'Leads Priorizados INT'!$E:$E) -> 4.1 Activado: en proceso de firma | E37: KO el 27.02 | F37: =+IF(OR($D37=$B$3,$D37=$B$4,$D37=$B$5,$D37=$B$6),"Realizado","Sin comenzar") -> Realizado | G37: =+IF(OR($D37=$B$3,$D37=$B$4,$D37=$B$5,$D37=$B$6),"Realizado","Sin comenzar") -> Realizado | H37: =+IF($D37=$B$5,"Pendiente",IF($D37=$B$6,"Agendado",IF(OR($D37=$B$3,$D37=$B$4),"Realizado"))) -> Realizado | I37: =+IF(OR($D37=$B$5,$D37=$B$6),"Sin comenzar",IF(OR($D37=$B$3,$D37=$B$4),"Realizado")) -> Realizado | J37: =+IF(OR($D37=$B$5,$D37=$B$6),"Sin comenzar",IF($D37=$B$3,"En curso",IF($D37=$B$4,"Realizado"))) -> En curso | K37: TBC | L37: Sin comenzar | N37: Sin comenzar | O37: Sin comenzar | P37: Sin comenzar | Q37: Sin comenzar | R37: Sin comenzar | S37: =+C37 -> DurnIA Tecnologías de la Información, S.L. | T37: Sin comenzar | U37: Sin comenzar | V37: Sin comenzar | W37: Sin comenzar | X37: Sin comenzar | Y37: Sin comenzar | Z37: Sin comenzar | AA37: Sin comenzar | AB37: Sin comenzar | AC37: Sin comenzar | AD37: Sin comenzar | AE37: Sin comenzar | AF37: Sin comenzar | AG37: Sin comenzar | AH37: Sin comenzar
B38: =+_xlfn.XLOOKUP($C38,'Leads Priorizados INT'!$B:$B,'Leads Priorizados INT'!$A:$A) -> 1672 | C38: Brain Hardware, S.L. | D38: =+_xlfn.XLOOKUP($C38,'Leads Priorizados INT'!$B:$B,'Leads Priorizados INT'!$E:$E) -> 4.1 Activado: en proceso de firma | E38: KO el 05.03 | F38: =+IF(OR($D38=$B$3,$D38=$B$4,$D38=$B$5,$D38=$B$6),"Realizado","Sin comenzar") -> Realizado | G38: =+IF(OR($D38=$B$3,$D38=$B$4,$D38=$B$5,$D38=$B$6),"Realizado","Sin comenzar") -> Realizado | H38: =+IF($D38=$B$5,"Pendiente",IF($D38=$B$6,"Agendado",IF(OR($D38=$B$3,$D38=$B$4),"Realizado"))) -> Realizado | I38: =+IF(OR($D38=$B$5,$D38=$B$6),"Sin comenzar",IF(OR($D38=$B$3,$D38=$B$4),"Realizado")) -> Realizado | J38: =+IF(OR($D38=$B$5,$D38=$B$6),"Sin comenzar",IF($D38=$B$3,"En curso",IF($D38=$B$4,"Realizado"))) -> En curso | K38: TBC | L38: Sin comenzar | N38: Sin comenzar | O38: Sin comenzar | P38: Sin comenzar | Q38: Sin comenzar | R38: Sin comenzar | S38: =+C38 -> Brain Hardware, S.L. | T38: Sin comenzar | U38: Sin comenzar | V38: Sin comenzar | W38: Sin comenzar | X38: Sin comenzar | Y38: Sin comenzar | Z38: Sin comenzar | AA38: Sin comenzar | AB38: Sin comenzar | AC38: Sin comenzar | AD38: Sin comenzar | AE38: Sin comenzar | AF38: Sin comenzar | AG38: Sin comenzar | AH38: Sin comenzar
B39: =+_xlfn.XLOOKUP($C39,'Leads Priorizados INT'!$B:$B,'Leads Priorizados INT'!$A:$A) -> 1685 | C39: Solventus Software, S.L. | D39: =+_xlfn.XLOOKUP($C39,'Leads Priorizados INT'!$B:$B,'Leads Priorizados INT'!$E:$E) -> 4.1 Activado: en proceso de firma | F39: =+IF(OR($D39=$B$3,$D39=$B$4,$D39=$B$5,$D39=$B$6),"Realizado","Sin comenzar") -> Realizado | G39: =+IF(OR($D39=$B$3,$D39=$B$4,$D39=$B$5,$D39=$B$6),"Realizado","Sin comenzar") -> Realizado | H39: =+IF($D39=$B$5,"Pendiente",IF($D39=$B$6,"Agendado",IF(OR($D39=$B$3,$D39=$B$4),"Realizado"))) -> Realizado | I39: =+IF(OR($D39=$B$5,$D39=$B$6),"Sin comenzar",IF(OR($D39=$B$3,$D39=$B$4),"Realizado")) -> Realizado | J39: =+IF(OR($D39=$B$5,$D39=$B$6),"Sin comenzar",IF($D39=$B$3,"En curso",IF($D39=$B$4,"Realizado"))) -> En curso | K39: TBC | L39: Sin comenzar | M39: Sin comenzar | N39: Sin comenzar | P39: Sin comenzar | R39: Sin comenzar | S39: =+C39 -> Solventus Software, S.L. | T39: Sin comenzar | U39: Sin comenzar | V39: Sin comenzar | W39: Sin comenzar | X39: Sin comenzar | Y39: Sin comenzar | Z39: Sin comenzar | AA39: Sin comenzar | AB39: Sin comenzar | AC39: Sin comenzar | AD39: Sin comenzar | AE39: Sin comenzar | AF39: Sin comenzar | AG39: Sin comenzar | AH39: Sin comenzar
B40: =+_xlfn.XLOOKUP($C40,'Leads Priorizados INT'!$B:$B,'Leads Priorizados INT'!$A:$A) -> 1690 | C40: NaimiTech, S.L. | D40: =+_xlfn.XLOOKUP($C40,'Leads Priorizados INT'!$B:$B,'Leads Priorizados INT'!$E:$E) -> 3.1 Interés confirmado: pendiente agendar KO | F40: =+IF(OR($D40=$B$3,$D40=$B$4,$D40=$B$5,$D40=$B$6),"Realizado","Sin comenzar") -> Realizado | G40: =+IF(OR($D40=$B$3,$D40=$B$4,$D40=$B$5,$D40=$B$6),"Realizado","Sin comenzar") -> Realizado | H40: =+IF($D40=$B$5,"Pendiente",IF($D40=$B$6,"Agendado",IF(OR($D40=$B$3,$D40=$B$4),"Realizado"))) -> Pendiente | I40: =+IF(OR($D40=$B$5,$D40=$B$6),"Sin comenzar",IF(OR($D40=$B$3,$D40=$B$4),"Realizado")) -> Sin comenzar | J40: =+IF(OR($D40=$B$5,$D40=$B$6),"Sin comenzar",IF($D40=$B$3,"En curso",IF($D40=$B$4,"Realizado"))) -> Sin comenzar | K40: TBC | L40: Sin comenzar | N40: Sin comenzar | P40: Sin comenzar | R40: Sin comenzar | S40: =+C40 -> NaimiTech, S.L. | T40: Sin comenzar | U40: Sin comenzar | V40: Sin comenzar | W40: Sin comenzar | X40: Sin comenzar | Y40: Sin comenzar | Z40: Sin comenzar | AA40: Sin comenzar | AB40: Sin comenzar | AC40: Sin comenzar | AD40: Sin comenzar | AE40: Sin comenzar | AF40: Sin comenzar | AG40: Sin comenzar | AH40: Sin comenzar
B41: =+_xlfn.XLOOKUP($C41,'Leads Priorizados INT'!$B:$B,'Leads Priorizados INT'!$A:$A) -> 1721 | C41: Ache Enseñanza e Informática SLL | D41: =+_xlfn.XLOOKUP($C41,'Leads Priorizados INT'!$B:$B,'Leads Priorizados INT'!$E:$E) -> 3.1 Interés confirmado: pendiente agendar KO | F41: =+IF(OR($D41=$B$3,$D41=$B$4,$D41=$B$5,$D41=$B$6),"Realizado","Sin comenzar") -> Realizado | G41: =+IF(OR($D41=$B$3,$D41=$B$4,$D41=$B$5,$D41=$B$6),"Realizado","Sin comenzar") -> Realizado | H41: =+IF($D41=$B$5,"Pendiente",IF($D41=$B$6,"Agendado",IF(OR($D41=$B$3,$D41=$B$4),"Realizado"))) -> Pendiente | I41: =+IF(OR($D41=$B$5,$D41=$B$6),"Sin comenzar",IF(OR($D41=$B$3,$D41=$B$4),"Realizado")) -> Sin comenzar | J41: =+IF(OR($D41=$B$5,$D41=$B$6),"Sin comenzar",IF($D41=$B$3,"En curso",IF($D41=$B$4,"Realizado"))) -> Sin comenzar | K41: TBC | L41: Sin comenzar | N41: Sin comenzar | P41: Sin comenzar | R41: Sin comenzar | S41: =+C41 -> Ache Enseñanza e Informática SLL | T41: Sin comenzar | U41: Sin comenzar | V41: Sin comenzar | W41: Sin comenzar | X41: Sin comenzar | Y41: Sin comenzar | Z41: Sin comenzar | AA41: Sin comenzar | AB41: Sin comenzar | AC41: Sin comenzar | AD41: Sin comenzar | AE41: Sin comenzar | AF41: Sin comenzar | AG41: Sin comenzar | AH41: Sin comenzar
B42: =+_xlfn.XLOOKUP($C42,'Leads Priorizados INT'!$B:$B,'Leads Priorizados INT'!$A:$A) -> 1737 | C42: Binfor Solutions | D42: =+_xlfn.XLOOKUP($C42,'Leads Priorizados INT'!$B:$B,'Leads Priorizados INT'!$E:$E) -> 4.1 Activado: en proceso de firma | F42: =+IF(OR($D42=$B$3,$D42=$B$4,$D42=$B$5,$D42=$B$6),"Realizado","Sin comenzar") -> Realizado | G42: =+IF(OR($D42=$B$3,$D42=$B$4,$D42=$B$5,$D42=$B$6),"Realizado","Sin comenzar") -> Realizado | H42: =+IF($D42=$B$5,"Pendiente",IF($D42=$B$6,"Agendado",IF(OR($D42=$B$3,$D42=$B$4),"Realizado"))) -> Realizado | I42: =+IF(OR($D42=$B$5,$D42=$B$6),"Sin comenzar",IF(OR($D42=$B$3,$D42=$B$4),"Realizado")) -> Realizado | J42: =+IF(OR($D42=$B$5,$D42=$B$6),"Sin comenzar",IF($D42=$B$3,"En curso",IF($D42=$B$4,"Realizado"))) -> En curso | K42: TBC | L42: Sin comenzar | N42: Sin comenzar | P42: Sin comenzar | R42: Sin comenzar | S42: =+C42 -> Binfor Solutions | T42: Sin comenzar | U42: Sin comenzar | V42: Sin comenzar | W42: Sin comenzar | X42: Sin comenzar | Y42: Sin comenzar | Z42: Sin comenzar | AA42: Sin comenzar | AB42: Sin comenzar | AC42: Sin comenzar | AD42: Sin comenzar | AE42: Sin comenzar | AF42: Sin comenzar | AG42: Sin comenzar | AH42: Sin comenzar
B43: =+_xlfn.XLOOKUP($C43,'Leads Priorizados INT'!$B:$B,'Leads Priorizados INT'!$A:$A) -> 1768 | C43: Omnia Soluciones (Soluciones Omnia 2024 S.L.) | D43: =+_xlfn.XLOOKUP($C43,'Leads Priorizados INT'!$B:$B,'Leads Priorizados INT'!$E:$E) -> 3.1 Interés confirmado: pendiente agendar KO | F43: =+IF(OR($D43=$B$3,$D43=$B$4,$D43=$B$5,$D43=$B$6),"Realizado","Sin comenzar") -> Realizado | G43: =+IF(OR($D43=$B$3,$D43=$B$4,$D43=$B$5,$D43=$B$6),"Realizado","Sin comenzar") -> Realizado | H43: =+IF($D43=$B$5,"Pendiente",IF($D43=$B$6,"Agendado",IF(OR($D43=$B$3,$D43=$B$4),"Realizado"))) -> Pendiente | I43: =+IF(OR($D43=$B$5,$D43=$B$6),"Sin comenzar",IF(OR($D43=$B$3,$D43=$B$4),"Realizado")) -> Sin comenzar | J43: =+IF(OR($D43=$B$5,$D43=$B$6),"Sin comenzar",IF($D43=$B$3,"En curso",IF($D43=$B$4,"Realizado"))) -> Sin comenzar | K43: TBC | L43: Sin comenzar | N43: Sin comenzar | P43: Sin comenzar | R43: Sin comenzar | S43: =+C43 -> Omnia Soluciones (Soluciones Omnia 2024 S.L.) | T43: Sin comenzar | U43: Sin comenzar | V43: Sin comenzar | W43: Sin comenzar | X43: Sin comenzar | Y43: Sin comenzar | Z43: Sin comenzar | AA43: Sin comenzar | AB43: Sin comenzar | AC43: Sin comenzar | AD43: Sin comenzar | AE43: Sin comenzar | AF43: Sin comenzar | AG43: Sin comenzar | AH43: Sin comenzar
B44: =+_xlfn.XLOOKUP($C44,'Leads Priorizados INT'!$B:$B,'Leads Priorizados INT'!$A:$A) -> 1772 | C44: Sur Computers, S.L. | D44: =+_xlfn.XLOOKUP($C44,'Leads Priorizados INT'!$B:$B,'Leads Priorizados INT'!$E:$E) -> 3.1 Interés confirmado: pendiente agendar KO | F44: =+IF(OR($D44=$B$3,$D44=$B$4,$D44=$B$5,$D44=$B$6),"Realizado","Sin comenzar") -> Realizado | G44: =+IF(OR($D44=$B$3,$D44=$B$4,$D44=$B$5,$D44=$B$6),"Realizado","Sin comenzar") -> Realizado | H44: =+IF($D44=$B$5,"Pendiente",IF($D44=$B$6,"Agendado",IF(OR($D44=$B$3,$D44=$B$4),"Realizado"))) -> Pendiente | I44: =+IF(OR($D44=$B$5,$D44=$B$6),"Sin comenzar",IF(OR($D44=$B$3,$D44=$B$4),"Realizado")) -> Sin comenzar | J44: =+IF(OR($D44=$B$5,$D44=$B$6),"Sin comenzar",IF($D44=$B$3,"En curso",IF($D44=$B$4,"Realizado"))) -> Sin comenzar | K44: TBC | L44: Sin comenzar | N44: Sin comenzar | P44: Sin comenzar | R44: Sin comenzar | S44: =+C44 -> Sur Computers, S.L. | T44: Sin comenzar | U44: Sin comenzar | V44: Sin comenzar | W44: Sin comenzar | X44: Sin comenzar | Y44: Sin comenzar | Z44: Sin comenzar | AA44: Sin comenzar | AB44: Sin comenzar | AC44: Sin comenzar | AD44: Sin comenzar | AE44: Sin comenzar | AF44: Sin comenzar | AG44: Sin comenzar | AH44: Sin comenzar
B45: =+_xlfn.XLOOKUP($C45,'Leads Priorizados INT'!$B:$B,'Leads Priorizados INT'!$A:$A) -> 1831 | C45: Elpis Informática, S.L. | D45: =+_xlfn.XLOOKUP($C45,'Leads Priorizados INT'!$B:$B,'Leads Priorizados INT'!$E:$E) -> 4.2 Activado: Firmado | F45: =+IF(OR($D45=$B$3,$D45=$B$4,$D45=$B$5,$D45=$B$6),"Realizado","Sin comenzar") -> Realizado | G45: =+IF(OR($D45=$B$3,$D45=$B$4,$D45=$B$5,$D45=$B$6),"Realizado","Sin comenzar") -> Realizado | H45: =+IF($D45=$B$5,"Pendiente",IF($D45=$B$6,"Agendado",IF(OR($D45=$B$3,$D45=$B$4),"Realizado"))) -> Realizado | I45: =+IF(OR($D45=$B$5,$D45=$B$6),"Sin comenzar",IF(OR($D45=$B$3,$D45=$B$4),"Realizado")) -> Realizado | J45: =+IF(OR($D45=$B$5,$D45=$B$6),"Sin comenzar",IF($D45=$B$3,"En curso",IF($D45=$B$4,"Realizado"))) -> Realizado | K45: TBC | L45: Sin comenzar | N45: Sin comenzar | P45: Sin comenzar | R45: Sin comenzar | S45: =+C45 -> Elpis Informática, S.L. | T45: Sin comenzar | U45: Sin comenzar | V45: Sin comenzar | W45: Sin comenzar | X45: Sin comenzar | Y45: Sin comenzar | Z45: Sin comenzar | AA45: Sin comenzar | AB45: Sin comenzar | AC45: Sin comenzar | AD45: Sin comenzar | AE45: Sin comenzar | AF45: Sin comenzar | AG45: Sin comenzar | AH45: Sin comenzar
B46: =+_xlfn.XLOOKUP($C46,'Leads Priorizados INT'!$B:$B,'Leads Priorizados INT'!$A:$A) -> 1841 | C46: Fi-4 Open Source, S.L. (Amiritmo) | D46: =+_xlfn.XLOOKUP($C46,'Leads Priorizados INT'!$B:$B,'Leads Priorizados INT'!$E:$E) -> 3.1 Interés confirmado: pendiente agendar KO | F46: =+IF(OR($D46=$B$3,$D46=$B$4,$D46=$B$5,$D46=$B$6),"Realizado","Sin comenzar") -> Realizado | G46: =+IF(OR($D46=$B$3,$D46=$B$4,$D46=$B$5,$D46=$B$6),"Realizado","Sin comenzar") -> Realizado | H46: =+IF($D46=$B$5,"Pendiente",IF($D46=$B$6,"Agendado",IF(OR($D46=$B$3,$D46=$B$4),"Realizado"))) -> Pendiente | I46: =+IF(OR($D46=$B$5,$D46=$B$6),"Sin comenzar",IF(OR($D46=$B$3,$D46=$B$4),"Realizado")) -> Sin comenzar | J46: =+IF(OR($D46=$B$5,$D46=$B$6),"Sin comenzar",IF($D46=$B$3,"En curso",IF($D46=$B$4,"Realizado"))) -> Sin comenzar | K46: TBC | L46: Sin comenzar | N46: Sin comenzar | P46: Sin comenzar | R46: Sin comenzar | S46: =+C46 -> Fi-4 Open Source, S.L. (Amiritmo) | T46: Sin comenzar | U46: Sin comenzar | V46: Sin comenzar | W46: Sin comenzar | X46: Sin comenzar | Y46: Sin comenzar | Z46: Sin comenzar | AA46: Sin comenzar | AB46: Sin comenzar | AC46: Sin comenzar | AD46: Sin comenzar | AE46: Sin comenzar | AF46: Sin comenzar | AG46: Sin comenzar | AH46: Sin comenzar
C47: MAICROSOFT EUROPE, S.L.
C48: Digital Hand Made, S.L.
C49: ISC Tech (Iván Sanz Cañamero)
C50: LISOT, S.L.
C51: AIDEEA INTELLIGENCE SL
B53: Funnel integradores
B54: {=_xlfn.LET( _xlpm.empresas,'Leads Priorizados INT'!B:B, _xlpm.estados,'Leads Priorizados INT'!E:E, _xlpm.ids,'Leads Priorizados INT'!A:A, _xlpm.estados_sel,$B$3:$B$6, _xlpm.ok,(_xlpm.empresas<>"")*ISNUMBER(MATCH(_xlpm.estados,_xlpm.estados_sel,0)), _xlfn.SORTBY( _xlfn._xlws.FILTER(_xlpm.empresas,_xlpm.ok,""), _xlfn._xlws.FILTER(_xlpm.ids,_xlpm.ok,""), 1 ) )} -> OX-ONE NETWORKS SL
B55: MAXEN TECHNOLOGIES SL
B56: PAPER LABS DESIGN ESP SL
B57: DEITECO
B58: COVERNET
B59: SICTEMAS SERVICIOS INFORMATICOS INTEGRALES
B60: Dataqu
B61: Ocvistas
B62: DuoIT
B63: FEDESOFT SL
B64: INFORNET SOLUCIONES INFORMATICAS S.L
B65: Micro Sip
B66: AUDINFOR SYSTEM SL.
... B89: INFORWARE, S.L.

Sheet Seguimiento interno
B3: Integrador | C3: Modelo de colaboración | D3: Último contacto | E3: Contexto | F3: Próximos pasos | G3: Teléfono | H3: Responsable asignado | I3: Estado
B4: OX-ONE | C4: LeadGen | D4: 05.03 | E4: Contacto: Gonzalo Gonzalez (La Finca, Madrid). Leads compartidos pero sin avance de momento. Visita a cliente pendiente. | F4: 09.03 llamar a Gonzalo para cuadrar visita Duino - Jonathan | G4: 607110458 | H4: Luis | I4: Pendiente VVDD
B5: PAPER LABS | C5: LeadGen | D5: 17.03 | E5: Contacto: Borja (Galicia). Interesado pero sin capacidad operativa para involucrarse en el modelo. Convencido en leadgen, pendiente de que le de una vuelta y empiece a identificar leads. | F5: Nos pasa 1 lead identificado. Cliente Orange, en análisis. | G5: 633160728 | H5: Luis | I5: Pendiente VVDD
B6: DEITECO | C6: Partner autorizado | D6: 24.03 | E6: Contacto: Jorge y Úrsula (Oliva, Valencia) Sin leads identificados para el modelo. Nos han solicitado más tiempo entre seguimientos (1 mes) ya que no pueden gestionarlo. Alta carga de trabajo en su rutina, peligro de churn si hay mucha insistencia. Les hemos preparado mail campaña para sus clientes Kit Digital, tienen que enviarlo. | F6: Deiteco pendiente mandar campaña a clientes Kit Digital | G6: 910263902 | H6: Luis | I6: Pendiente integrador
B7: SICTEMAS | C7: LeadGen | D7: 17.03 | E7: Contacto: Antonio (Málaga). Pendiente firma contrato LeadGen | F7: Quieren comenzar a mediados de abril. | G7: 654961741 | H7: Luis | I7: On hold
B8: DATAQU | C8: LeadGen | D8: 24.03 | E8: Parado Armadora Pereira. Preparar webinar durante marzo - convo finales de abril (27.04 a las 16h). Atacar Grupo Adarsa ahora. | F8: Nos pasan formatos webinar previo. Mañana 18.03 hablan con Adarsa. | G8: 619461670 | H8: Luis | I8: Pendiente Accenture e integrador
B9: Carlos García - Castellano | C9: LeadGen | D9: 02.02 | E9: Agendar reunión con Carlos García Castellano | F9: Javier le envía whatsapp para cerrar sesión. Sin respuesta 3.02 | G9: 619461670 | H9: Javier | I9: ¿?
B10: A4I | C10: LeadGen | D10: 11.03 | E10: Contacto: Alejandro Camacho & Jose Luis. Pendiente agendar KO | F10: 3.2 Lllamada realizada 3.2 y hablado con la secre: no han tenido tiempo para revisarlo todavía, se lo comenta a jose luis y alejandro. | Llamar el lunes 26.01 (no había podido ver el correo con el contrato y portfolio) - HORARIO 8-15H. Sin respuesta a recontacto el 05.03. Les hemos llamado, les pasan el aviso y llaman ellos. | G10: 956860077 | H10: Luis | I10: Pendiente integrador
B11: FEDESOFT | C11: LeadGen | D11: 10.03 | E11: Contacto: Fede (Puente Genil, Córdoba). KO realizado y contrato enviado. Quiere activar después de semana santa por temas personales (madre). | F11: Contacto primera quincena abril | G11: 625596462 | H11: Luis | I11: On hold
B12: INFORNET | C12: LeadGen | D12: 02.02 | E12: Contacto: Manuel (Gijón, Asturias). Pendiente envío de leads por integrador para verificar si son clientes MasOrange, y agendar sesión con VVDD | F12: 16.02 Se ha roto el coxis. Aplaza colaboración aunque muestra interés | 5.02 JC le envía whastapp | Muy interesado, ha estado de viaje. Nos responde entre 02.02 y 03.02. Si no ha enviado nada el 04.02, avisar a javier | G12: 663044288 | H12: Javier | I12: Pendiente Blanca
B13: MICRO SIP | C13: LeadGen | D13: 24.03 | E13: Contacto: Víctor (Cáceres). Sesión mantenida, identificadas potenciales oportunidades con lead grande (BD). | F13: Nos llama esta semana directamente desde BD. | G13: 651952717 | H13: Luis | I13: Pendiente integrador
B14: COBITRATEL | C14: LeadGen | D14: 02.03 | E14: Contacto: José Luis Abad. Nos está enviando leads | F14: Pendiente contrato. | G14: 609202122 | H14: Luis | I14: Pendiente Legal
B15: NEXT MOBILITY | C15: LeadGen | D15: 17.03 | E15: Contacto: Carolina Peña. Les enviamos el modelo de contrato. Pendiente agendar KO. | F15: 3.2 Llamada y hablado con secre, le pasa nota a Carolina | 2.2 Vovler a llamar, no contestan | Llamar lunes 26.01 y preguntar por Carolina. Recontacto el 09.03. | G15: 917895349 | H15: Luis | I15: Pendiente integrador
... B18: SISYTEC | C18: LeadGen | D18: 24.03 | E18: Contacto: Alfredo. | F18: Pendiente cliente. Alfredo pregunta. | G18: 699215704 | H18: Luis | I18: Pendiente integrador
B19: OCVISTAS | C19: LeadGen | D19: 06.03 | E19: Contacto: Sunny. En firma de contrato. | F19: Enviar contrato para su firma (Jonathan). Visita al integrador el 17.03. | H19: Luis | I19: Pendiente VVDD
B20: DUO IT | C20: LeadGen | D20: 16.03 | E20: Contacto: Ángel. Seguimiento 09.03. | F20: Nos pasa 2 leads identificados. | H20: Luis | I20: Pendiente integrador
B21: DOSYS | C21: LeadGen | D21: 17.03 | E21: Contacto: Jon. Nos pidió precios y le parecen caros. | F21: Le escribió Jonathan pidiendo sus precios, no responde. Hay que llamarle pero no responde (11.03), le volvemos a escribir. | H21: Luis | I21: Sin respuesta
B22: SOLVENTUS SOFTWARE | C22: LeadGen | D22: 10.03 | E22: Contacto: Maxim y Enrique. Nos pidieron catálogo de dispositivos. | F22: Pendiente respuesta a mail de Juan. | H22: Luis | I22: Pendiente integrador
B23: DURNIA | C23: Partner autorizado | D23: 18.03 | E23: Contacto: Alberto. Se pone a analizar la colaboración el 18.03. | H23: Luis | I23: Pendiente integrador
B24: MASRISKALNET | C24: LeadGen | D24: 24.03 | E24: Contacto: Emilio. | F24: Nos pasa 2 leads identificados. | G24: 639184047 | H24: Luis | I24: Pendiente integrador
B25: NAIMITECH | C25: LeadGen | D25: 17.03 | E25: Contacto: Sofiane. Quiere modelo bidireccional. Queda pendiente enviarnos sus productos para que analice +O. | H25: Luis | I25: Pendiente integrador
B26: GNUO | C26: LeadGen | D26: 24.03 | E26: Contacto: José Antonio. No nos confirma slot para juntarnos con VVDD. | F26: Contrato compartido, pendiente firma. | H26: Luis | I26: Pendiente integrador
B27: ACHE INFORMÁTICA | C27: LeadGen | D27: 17.03 | E27: Contacto: Raúl. No contestan para juntarnos con VVDD. Les daba miedo perder leads porque tenían una cartera muy cuidada. | F27: Llamada el 11.03 pero contestador. | G27: 942344304 | H27: Luis | I27: Sin respuesta
B28: OMNIA SOL | C28: LeadGen | D28: 17.03 | E28: Contacto: Germán. No contestan para juntarnos con VVDD. | F28: Llamada el 11.03, se apuntan la llamada y responden. | H28: Luis | I28: Sin respuesta
B29: SUR COMPUTERS | C29: LeadGen | D29: 17.03 | E29: Contacto: José Manuel. Nos pidieron portfolio de licencias con precios. | H29: Luis | I29: Sin respuesta
B30: BINFOR SOLUTIONS | C30: LeadGen | D30: 24.03 | E30: Contacto: Tomás. | F30: Nos envía contrato firmado. | H30: Luis | I30: Pendiente integrador
B31: ELPIS INFORMATICA | C31: LeadGen | D31: 20.03 | E31: Contacto: Paco. | F31: Contrato firmado. Pendiente leads. Hold hasta 7 de abril. | G31: 977896847 | H31: Luis | I31: On hold
B32: BRAIN HARDWARE | C32: LeadGen | D32: 18.03 | E32: Contacto: Angel. | F32: Contrato compartido, pendiente firma. Dice que se pondrán en mayo. | H32: Luis | I32: On hold

Sheet Leads Dataqu
B3: Grupo | C3: Empresas | D3: CIF | E3: Cliente Orange
B4: Asociación Apromar | C4: Asociación Apromar | D4: G78295748 | E4: No
C5: Asociación Apromar | D5: E36115814 | E5: Sí
C6: Acuicultura del Delta SL | D6: B67507673 | E6: No
C7: Acuipalma SL | D7: B38707600 | E7: No
C8: Alevines de Guardamar SL | D8: B53341160 | E8: No
C9: Alicante Aquaculture SL | D9: B42508854 | E9: No
C10: Aquanaria SL | D10: B35236355 | E10: No
C11: Avramar SL (matriz española operativa) | D11: B12741278 | E11: No
C12: Caladeros del Mediterráneo SL | D12: B30704332 | E12: No
C13: Caviar Pirinea SL | D13: B22386841 | E13: No
C14: Culmarex SA (Cooke España) | D14: A30106264 | E14: No
C15: Cultivos Piscícolas Marinos SA | D15: A07086879 | E15: No
C16: Eurotrucha SLU | D16: B4201539 | E16: No
... C36: Valenciana de Acuicultura SA | D36: A46228078 | E36: No
B37: Schreiber Foods | C37: Schreiber Foods | D37: B82690082 | E37: Hasta diciembre
B38: Armadora Pereira | C38: Armadora Pereira | D38: A36630028 | E38: No
B39: Grupo Adarsa | C39: ASTURIANA DE AUTOMÓVILES Y REPUESTOS, S.A. | D39: A33022765 | E39: No
C40: INTEGRAL DE AUTOMOCIÓN 2000, S.A. | D40: A33552357 | E40: No
C41: LERCAUTO 96, S.A. | D41: A24326373 | E41: No
C42: ADARSA SUR, S.A.U. | D42: A21029822 | E42: No
C43: CISACAR, S.L. | D43: B33415019 | E43: No
C44: RADAUTO 96, S.L. | D44: B24327744 | E44: No
C45: UP2CAR, S.L. | D45: B33544784 | E45: No
C46: XXI BLG CORREDURÍA DE SEGUROS, S.L. | D46: B74048877 | E46: No
C47: ADARSA RENT, S.A. | D47: A74035999 | E47: No
C48: 21 JACARS, S.L. | D48: B74165259 | E48: No
C49: ADARSA TRUCKS, S.A. | D49: A23876972 | E49: No
C50: ADARSA NORTE, S.A. | D50: A39001888 | E50: No
C51: AGROTRACCIÓN VEHÍCULOS, S.A. | D51: A37003043 | E51: No

Sheet Sesiones
C2: Reuniones conseguidas VE | E2: Reuniones conseguidas (Strategy) | G2: Reuniones agendadas VE | I2: Reuniones agendadas (Strategy)
C3: (#) | D3: Empresa integradora | E3: (#) | F3: Empresa integradora | G3: (#) | H3: Empresa integradora | I3: (#) | J3: Empresa integradora
B4: 46027 | G4: 3 | H4: Loomis, Next Mobility, A4i (todas - Carlos Montero) | I4: 3 | J4: Loomis, Next Mobility, A4i (todas - Carlos Montero)
B5: Total | C5: =+SUBTOTAL(9,C6:C19) -> 37 | E5: =+SUBTOTAL(9,E6:E10) -> 5 | G5: =+SUBTOTAL(9,G8:G19) -> 37 | I5: =+SUBTOTAL(9,I6:I10) -> 5
B6: =+B4+7 -> 46034 | C6: 1 | D6: Nostravant
B7: =+B6+7 -> 46041 | C7: 4 | D7: Bookkercop, SW maquinaria, Dirbapont, Megavedra | E7: 2 | F7: Q2B, PC Service | G7: 1 | H7: Esker (Carlos Montero) | I7: 2 | J7: Q2B, PC Service
B8: =+B7+7 -> 46048 | C8: 2 | D8: Sysitec, PSA ingenieros | E8: 1 | F8: Twistic (Luis) | G8: 3 | H8: Nostravant, Megavedra, Bookkercorp, | I8: 1 | J8: Twistic (Luis)
B9: =+B8+7 -> 46055 | E9: 2 | F9: Tecnología Estratégica, Numericco | G9: 3 | H9: Software maquinaria, PSA ingenieros, Dirbapont | I9: 2 | J9: Tecnología Estratégica, Numericco
B10: =+B9+7 -> 46062 | C10: 5 | D10: Nexeinformatica,Grupo Open, Dosys, PC Chamartín, Mariskalnet | G10: 3 | H10: Sysitec, Grupo Open, Dosys | I10: 0
B11: =+B10+7 -> 46069 | C11: 8 | D11: Gnuo consultores, Cádizpyme, Durnia, solventussoftware, naimitech, DISA (Grupo Sertec), PIL, Brain Hardware | G11: 9 | H11: Nexeinformatica, PC Chamartín, Mariskalnet, Gnuo consultores, Cádizpyme, Durnia, solventussoftware, naimitech, PIL
B12: =+B11+7 -> 46076 | C12: 6 | D12: Binfor Solutions, Ache Informática, Omnia Soluciones, Redem, Alsys, Tecicom | G12: 5 | H12: Brain Hardware, Binfor Solutions, Omnia Soluciones, Ache Informática, Alsys
B13: =+B12+7 -> 46083 | C13: 4 | D13: Sur Computers, Elpis Informática, SYC Almería, Amiritmo | G13: 1 | H13: Redem, Sur Computers
B14: =+B13+7 -> 46090 | C14: 5 | D14: Digital HM, Maicrosoft, ISC Tech, Lisot, Aideea | G14: 6 | H14: Tecicom, Elpis Informática, SYC Almería, Amiritmo, Redem, ISC Tech
B15: =+B14+7 -> 46097 | C15: 2 | D15: Evolur, Itsoft | G15: 6 | H15: DISA (Grupo Sertec), Digital HM, Maicrosoft, Aideea, Lisot, Itsoft
B16: =+B15+7 -> 46104 | G16: 1 | H16: Evolur
B17: =+B16+7 -> 46111
B18: =+B17+7 -> 46118
B19: =+B18+7 -> 46125

Sheet Checkeo Semanal
B2: Checkeo Correos - Sesión 1.1
B3: FOTOS FIJAS CADA VIERNES
B4: Emails enviados | C4: Sesiones 1.1 | D4: Ratio de éxito
B5: =SUM(C8:C14) -> 261 | C5: =SUM(D8:D14) -> 32 | D5: =C5/B5 -> 0.12260536
B7: SEMANA | C7: Numero de correos enviados | D7: Sesiones 1:1 | E7: Ratio de éxito
B8: =+Sesiones!B9 -> 46055 | C8: 29 | D8: =Sesiones!C9+Sesiones!E9 -> 2 | E8: =D8/C8 -> 0.068965517
B9: =+Sesiones!B10 -> 46062 | C9: =C24-D24 -> 80 | D9: =Sesiones!C10+Sesiones!E10 -> 5 | E9: =D9/C9 -> 0.0625
B10: =+Sesiones!B11 -> 46069 | C10: =C25-D25 -> 21 | D10: =Sesiones!C11+Sesiones!E11 -> 8 | E10: =D10/C10 -> 0.38095238
B11: =+Sesiones!B12 -> 46076 | C11: =C26-D26 -> 40 | D11: =Sesiones!C12+Sesiones!E12 -> 6 | E11: =D11/C11 -> 0.15
B12: =+Sesiones!B13 -> 46083 | C12: =C27-D27 -> 37 | D12: =Sesiones!C13+Sesiones!E13 -> 4 | E12: =D12/C12 -> 0.10810811
B13: =+Sesiones!B14 -> 46090 | C13: =C28-D28 -> 38 | D13: =Sesiones!C14+Sesiones!E14 -> 5 | E13: =D13/C13 -> 0.13157895
B14: =+Sesiones!B15 -> 46097 | C14: =C29-D29 -> 16 | D14: =Sesiones!C15+Sesiones!E15 -> 2 | E14: =D14/C14 -> 0.125
B15: =+Sesiones!B16 -> 46104 | C15: =C30-D30 -> 0 | D15: =Sesiones!C16+Sesiones!E16 -> 0 | E15: =D15/C15 -> #DIV/0!
B16: =+Sesiones!B17 -> 46111 | C16: =C31-D31 -> 0 | D16: =Sesiones!C17+Sesiones!E17 -> 0 | E16: =D16/C16 -> #DIV/0!
B17: =+Sesiones!B18 -> 46118 | C17: =C32-D32 -> 0 | D17: =Sesiones!C18+Sesiones!E18 -> 0 | E17: =D17/C17 -> #DIV/0!
B18: =+Sesiones!B19 -> 46125 | C18: =C33-D33 -> 0 | D18: =Sesiones!C19+Sesiones!E19 -> 0 | E18: =D18/C18 -> #DIV/0!
B21: SEMANA | C21: CONTEO LUNES MAILS | D21: CONTEO VIERNES MAILS
B22: CONTEO GENERAL | C22: =COUNTIF('Leads Priorizados INT'!E:E,"0.*") + COUNTIF('Leads Priorizados INT'!E:E,"*Contacto fallido*") + COUNTIF('Leads Priorizados INT'!E:E,"99.*") + COUNTIF('Leads Priorizados INT'!E:E,"1.1*rechazada*") -> 1357
B23: =+Sesiones!B9 -> 46055
B24: =+Sesiones!B10 -> 46062 | C24: =1563+26 -> 1589 | D24: =1483+26 -> 1509
B25: =+Sesiones!B11 -> 46069 | C25: 1509 | D25: =1462+26 -> 1488
B26: =+Sesiones!B12 -> 46076 | C26: 1488 | D26: =1422+26 -> 1448
B27: =+Sesiones!B13 -> 46083 | C27: 1448 | D27: =1385+26 -> 1411
B28: =+Sesiones!B14 -> 46090 | C28: 1411 | D28: =1347+26 -> 1373
B29: =+Sesiones!B15 -> 46097 | C29: 1373 | D29: =1331+26 -> 1357
B30: =+Sesiones!B16 -> 46104 | C30: 1357 | D30: 1357
B31: =+Sesiones!B17 -> 46111
B32: =+Sesiones!B18 -> 46118
B33: =+Sesiones!B19 -> 46125

Sheet Leads Priorizados INT
C1: LEAD DUPLICADO 1614
E2: 46298
A3: ID | B3: Empresa | C3: VÁLIDO | D3: PRIORIZADO | E3: Estado | F3: DETALLE TRACKER | G3: OWNER | H3: Administrador | I3: Telf master | J3: Email 1 | K3: Teléfono web oficial | L3: Arquetipo | M3: CIF | N3: Descripción actividad | O3: Web | P3: Justificación IA | Q3: Estado actividad | R3: Categoría | S3: Provincia | T3: Código postal | U3: Ventas | V3: Empleados | W3: Sucursales | X3: Score Big Data | Y3: Tel 2 | Z3: Tel 3 | AA3: Tel 4 | AB3: Tel 5 | AC3: Contacto 2 | AD3: Contacto 3 | AE3: Contacto 4 | AF3: Contacto 5 | AG3: Cargo 1 | AH3: Cargo 2 | AI3: Cargo 3 | AJ3: Cargo 4 | AK3: Cargo 5 | AL3: Email 2 | AM3: Email 3 | AN3: Email 4 | AO3: Email 5 | AP3: Cliente Orange | AQ3: FOCO
A4: 1 | B4: J P C INFORMATICA Y COMUNICACIONES SL | D4: Y | E4: 0. Pendiente contactar | F4: Barcelona, llamar por la tarde | G4: María | I4: (+34) 932 924 824 | J4: info@jpcnet.com | L4: A. Informáticos | M4: B60854767 | N4: Venta, instalación y mantenimiento de hardware y servicios de comunicaciones | O4: NO WEB | P4: Venta de hardware, servicios básicos de informática y comunicaciones; no vertical; falta web → requiere validación. | Q4: Activa | AP4: No
A5: =+A4+1 -> 2 | B5: SOLUCION DISEÑO INNOVACION SL | D5: Y | E5: 1.0. Contacto fallido (sin descuelgue) | F5: Volver a llamar | G5: María | I5: 914454372 | J5: info@dsoluzion.com | L5: D. Desarrolladores de soluciones digitales básicas | M5: B84583905 | N5: Consultoría informática, diseño web y servicios de marketing digital | O5: Empresa diseño web Madrid. Conócenos. Dsoluzion | P5: Se orienta a marketing digital y diseño web; sin sector concreto; requiere validación por falta de web. | Q5: Activa | AP5: No
A6: =+A5+1 -> 3 | B6: SISTEMAS DE OFICINA DE LUGO SA | D6: Y | E6: 1.1 Contactado: propuesta "rechazada" | F6: Llamar mañana antes de las 4pm | G6: Juan | H6: Jesus Martin Mariscal | I6: 982 28 44 62 | J6: s.o.lugo@lugo.canon.es | K6: evolvegalicia | L6: A. Informáticos | M6: A27142462 | N6: Venta y alquiler de equipos de oficina (ordenadores, centralitas, programas) | O6: NO WEB | P6: Se dedica a venta y alquiler de equipos y programas de oficina, sin desarrollo propio. Clasificada como informáticos. | Q6: Activa | R6: No_Cliente | S6: Lugo | T6: 27002 | U6: 1139933 | V6: 12 | W6: 1 | X6: 0.1977 | Y6: 982284462 | Z6: 982284113 | AG6: Administrador | AH6: Director Financiero | AI6: Consejero | AJ6: Consejero Delegado | AK6: Administrador | AP6: No
A7: =+A6+1 -> 4 | B7: CRYSTAL MEDIA SHOPS SL | E7: 99. Descartado | G7: Juan | H7: Gonzalo Fernando Garcia De Blanes Hernandez | I7: 913 337 818 | J7: info@crystalmedia.com | K7: No existe correo | L7: A. Informáticos | M7: B60929882 | N7: Comercialización de productos electrónicos, multimedia, informática, fotografía y software | O7: NO WEB | P7: Actividad centrada en retail de informática/electrónica, sin foco en software propio. Multi-sector. Clasificada como informáticos. | Q7: Activa | R7: Cliente_OSP | S7: Barcelona | T7: 08005 | U7: 16883376 | V7: 60 | W7: 13 | X7: 0.1936 | Y7: 932253444 | Z7: 934991173 | AA7: 932254460 | AB7: 913337285 | AC7: Garcia De Blanes Hernandez Gonzalo Fernando | AG7: Administrador | AH7: Director Financiero | AI7: Consejero | AJ7: Consejero Delegado | AK7: Administrador | AL7: admin@crystalmedia.com | AM7: revelado@revelado.com | AP7: No
A8: =+A7+1 -> 5 | B8: TAMAINUT IT SL | C8: Y | D8: Y | E8: 1.0. Contacto fallido (sin descuelgue) | G8: Juan | H8: Gemma Plana Vila | I8: 918558782 | L8: B. Integradores TI generalistas | M8: B85824654 | N8: Servicios TI, mantenimiento de sistemas, consultoría, hosting, dominios | O8: https://tamainut.com/ | P8: Web oficial activa, portfolio incluye mantenimiento TI, consultoría, hosting y dominios. Multi-sector, servicios TI completos. Clasificada como integrador TI generalista. | Q8: Activa | R8: No_Cliente | S8: Madrid | T8: 28410 | U8: 1067729 | V8: 7 | W8: 1 | X8: 0.1872 | AC8: Javier Onielfa Perez | AG8: Administrador | AH8: Director Financiero | AI8: Consejero | AJ8: Consejero Delegado | AK8: Administrador | AP8: No
A9: =+A8+1 -> 6 | B9: PROYECTA 4 INTERNET SL | D9: N | E9: 99. Descartado | G9: Juan | H9: Laura Llago | I9: 918445346 | L9: B. Integradores TI generalistas | M9: B83907287 | N9: Comercialización de productos informáticos y telefonía | O9: NO WEB | P9: Su objeto social es la comercialización de productos informáticos y telecomunicaciones. No presenta sector específico. La falta de registros desde 2009 e insolvencia en 2012 apuntan a inactividad. | Q9: No Activa | R9: Cliente_OSP | S9: Madrid | T9: 28792 | U9: 857764 | V9: 7 | W9: 1 | X9: 0.5369 | Y9: 619885169 | AC9: Jose Manuel Novoa Perez | AD9: Andre Luitz | AE9: Frank Mackel | AF9: Terje Schroeder John | AG9: Administrador | AH9: Director Financiero | AI9: Consejero | AJ9: Consejero Delegado | AK9: Administrador | AP9: No
A10: =+A9+1 -> 7 | B10: SOLUCIONES INFORMATICAS GEDRA S.L | D10: N | E10: 99. Descartado | F10: Número outdated | G10: Blanca | H10: German Apalategui Muga | I10: 912601559 | L10: A. Informáticos | M10: B84385558 | N10: Importación, venta, mantenimiento y comercialización de equipos informáticos | O10: NO WEB | P10: Actividad centrada en comercialización, montaje y mantenimiento de equipos informáticos. Multi-sector y orientado a hardware, por lo que se clasifica como informático. | Q10: No Activa | R10: No_Cliente | S10: Madrid | T10: 28017 | U10: 3622658 | V10: 7 | W10: 1 | X10: 0.2213 | AC10: Jose Manuel Llado Arburua | AD10: Santiago Satrustegui Perez Villaamil | AE10: Clara Llado Garcia Lomas | AF10: Maria Cristina Rembado Thomas | AG10: Administrador | AH10: Director Financiero | AI10: Consejero | AJ10: Consejero Delegado | AK10: Administrador | AP10: No
A11: =+A10+1 -> 8 | B11: SERVITEC VENDING SL | D11: N | E11: 99. Descartado | F11: RECONTACTO. Experto vertical Hostelería TPVs… | G11: Juan | H11: Aitor Lopez Aberasturi Ortiz Pinedo | I11: 932653592 | L11: A. Informáticos | M11: B64101041 | N11: Compra, venta/alquiler y mantenimiento de máquinas expendedoras | O11: NO WEB | P11: Enfoque en equipos/servicios técnicos (hardware). Sin vertical TI específico ni web oficial. Clasificación “informáticos”; faltan evidencias recientes concluyentes. | Q11: No Activa | R11: No_Cliente | S11: Barcelona | T11: 08759 | U11: 1179833 | V11: 1 | W11: 1 | X11: 0.2163 | AG11: Administrador | AH11: Director Financiero | AI11: Consejero | AJ11: Consejero Delegado | AK11: Administrador | AP11: No
A12: =+A11+1 -> 9 | B12: CONSULTORIA TECNICA DE REPARACIONES INFORMATICAS SL | E12: 99. Descartado | G12: Juan | I12: 913 265 438 | L12: A. Informáticos | M12: B83625350 | N12: Empresa con base técnica consolidada en hardware y software, enfocada a mantenimiento y soporte IT, con capacidad para evolucionar hacia soluciones de digitalización empresarial, ciberseguridad básica y gestión documental. | O12: consultinfor.com | P12: se dedica al desarrollo, montaje y mantenimiento de sistemas informáticos, con capacidad de digitalizar infraestructuras pero sin foco en servicios cloud, web o IoT. | Q12: Activa | S12: Madrid | T12: MADRID | V12: 1 | AP12: No
A13: =+A12+1 -> 10 | B13: REPARAR PC MICRO COMPUTER SL | E13: 1.2 Contactado: propuesta "en valoración" | F13: Mail enviado 04/02 a la 13:22 | G13: Juan | I13: +34 66/5689151 | K13: 91 553 16 00 | L13: A. Informáticos | M13: B88099577 | N13: Taller multimarca en Madrid con servicios de reparación, montaje de ordenadores y recuperación de datos, sin ofertas de servicios digitales o cloud. | O13: Reparar portátil Madrid - reparación de ordenadores en Madrid | P13: Reparación de ordenadores, consolas, montaje de PCs a medida, antivirus, redes. | Q13: Activa | S13: Madrid | T13: MADRID | V13: 1 | AP13: No
A14: =+A13+1 -> 11 | B14: FARMERS WIFE SL | C14: Y | D14: Y | E14: 1.0. Contacto fallido (sin descuelgue) | G14: Carlota | H14: Seneca Martin Martin | I14: 971732623 | J14: info@farmerswife.com | K14: 971 730 777 | L14: C. Integradores TI sectoriales | M14: B57323909 | N14: Consulting informático; diseño e implantación de programas y sistemas; compraventa de productos TI | O14: www.farmerswife.com | P14: Web oficial activa, especializada en soluciones de gestión para productoras audiovisuales (broadcast/media). Vertical claro (audiovisual). Clasificada como integrador TI sectorial. | Q14: Activa | R14: Cliente_OSP | S14: Illes Balears | T14: 07015 | U14: 1469734 | V14: 15 | W14: 3 | X14: 0.1807 | Y14: 971730777 | Z14: 695846228 | AA14: 638589501 | AB14: 607767572 | AG14: Administrador | AH14: Director Financiero | AI14: Consejero | AJ14: Consejero Delegado | AK14: Administrador | AP14: No
A15: =+A14+1 -> 12 | B15: BRN BASIC SOLUTIONS SL | D15: Y | E15: 1.0. Contacto fallido (sin descuelgue) | G15: Carlota | H15: Rafael Erhardt Oraa | I15: 915743300 | L15: D. Desarrolladores de soluciones digitales básicas | M15: B86128766 | N15: Estudios, trabajos y aplicaciones informáticas; adaptación de servicios relacionados con procesamiento de información | O15: https://www.linkedin.com/company/brn-basic-solutions-sl | P15: Realiza desarrollo de aplicaciones informáticas y procesamiento de información; ofrece soluciones digitales básicas. EmpresiaeInformaEmpresite EspañaAxesor | Q15: Activa | R15: Cliente_OSP | S15: Madrid | T15: 28009 | U15: 852756 | V15: 8 | W15: 1 | X15: 0.4159 | Y15: 629221122 | Z15: 609779977 | AC15: Rafael Erhardt | AD15: Francisco Javier Martinez Sancho | AE15: Tamaya Gallastegui | AG15: Administrador | AH15: Director Financiero | AI15: Consejero | AJ15: Consejero Delegado | AK15: Administrador | AP15: No
A16: =+A15+1 -> 13 | B16: POLARIS INFORMÁTICA Y COMUNICACIONES SA | D16: Y | E16: 1.0. Contacto fallido (sin descuelgue) | F16: Volver a llamar, pone que estaban ocupados | G16: Carlota | I16: 914 422 017 | L16: A. Informáticos | M16: A81148314 | N16: Montaje, comercialización, mantenimiento, alquiler y reparación de equipos informáticos, accesorios, y venta de programas informáticos a través de tienda especializada. | O16: https://www.polaris.es/ | P16: Activa como minorista de hardware e informática, con servicios clásicos de asesoría y reparación; claramente en el arquetipo Informáticos (hardware/software local). | Q16: Activa | S16: =_xlfn.XLOOKUP(B16,'BBDD Completa'!E:E,'BBDD Completa'!F:F,"Not found") -> Not found | AP16: No
A17: =+A16+1 -> 14 | B17: BUSINESS & DECISION ESPAÑA SA | D17: Y | E17: 1.0. Contacto fallido (sin descuelgue) | G17: Venta especialista | H17: Catharina Joanna Peeters | I17: 917677034 | 91 515 9547 | J17: info@ivc.es | L17: E. Consultoras innovación digital | M17: A82945791 | N17: Consultoría TI, business intelligence, big data y transformación digital | O17: https://www.businessdecision.com | P17: Ofrece BI, big data, transformación digital e IA; multi-sector; corresponde a consultora de innovación digital. | Q17: Activa | R17: Cliente_TML | S17: Madrid | T17: 28004 | U17: 2122537 | V17: 43 | W17: 1 | X17: 0.3247 | Y17: 917607207 | Z17: 910069581 | AA17: 917677035 | AB17: 917677032 | AC17: Peeters Catharina Joanna | AD17: Luc Louis Cock | AG17: Administrador | AH17: Director Financiero | AI17: Consejero | AJ17: Consejero Delegado | AK17: Administrador | AP17: No
A18: =+A17+1 -> 15 | B18: MONTREL INGENIERIA INFORMATICA SA | D18: Y | E18: 1.0. Contacto fallido (sin descuelgue) | G18: Carlota | L18: B. Integradores TI generalistas | M18: A41110530 | N18: Ingeniería informática, automatización y telecomunicaciones | O18: https://www.montrel.es | P18: Amplio portfolio en TI, automatización y telecom; multi-sector; encaja en integradores TI generalistas. | Q18: Activa | AP18: No
A19: =+A18+1 -> 16 | B19: QUALITY MOLINS SL | D19: Y | E19: 99. Descartado | G19: Carlota | L19: A. Informáticos | M19: B61444547 | N19: Servicios de informática, venta de hardware y soluciones TI | O19: NO WEB | P19: Venta y soporte informático; multisector; encaja en Informáticos. | Q19: No Activa | AP19: No
A20: =+A19+1 -> 17 | B20: SW HOSTING & COMMUNICATIONS TECHNOLOGIES SL | D20: Y | E20: 1.0. Contacto fallido (sin descuelgue) | G20: Carlota | L20: B. Integradores TI generalistas | M20: B55113515 | N20: Servicios de hosting, cloud, servidores, comunicaciones y soluciones digitales | O20: https://www.swhosting.com | P20: Ofrece hosting, cloud, servidores dedicados, comunicaciones y soporte TI; multi-sector; encaja como integrador TI generalista. | Q20: Activa | AP20: No
A21: =+A20+1 -> 18 | B21: ITEC4 SOFTWARE SL | D21: Y | E21: 1.0. Contacto fallido (sin descuelgue) | G21: Carlota | H21: Abel Soto Guerrero | I21: 615599253 | L21: D. Desarrolladores de soluciones digitales básicas | M21: B65937013 | N21: Desarrollo de software de gestión, consultoría tecnológica y soluciones digitales | O21: NO WEB | P21: Ofrece software de gestión empresarial, apps a medida y consultoría TI; multi-sector; encaja en desarrolladores de soluciones digitales básicas. | Q21: Activa | R21: No_Cliente | S21: Barcelona | T21: 08370 | U21: 517372 | V21: 1 | W21: 2 | X21: 0.2675 | AC21: Gonzalo Soto Mejia | AD21: Abel Alejandro Soto Guerrero | AG21: Administrador | AH21: Director Financiero | AI21: Consejero | AJ21: Consejero Delegado | AK21: Administrador | AP21: No
A22: =+A21+1 -> 19 | B22: FRUTO DIGITAL SL | D22: Y | E22: 99. Descartado | G22: Carlota | H22: Jesus Duque Alcorta | I22: 917137751 | L22: D. Desarrolladores de soluciones digitales básicas | M22: B86031135 | N22: Consultoría de marketing digital, desarrollo web y publicidad online | O22: https://www.frutodigital.com | P22: Ofrece servicios de marketing digital, desarrollo web y publicidad online; multi-sector; encaja en desarrolladores digitales básicos. | Q22: No Activa | R22: No_Cliente | S22: Madrid | T22: 28522 | U22: 459096 | V22: 1 | W22: 2 | X22: 0.2601 | AC22: Francisco Bellil | AD22: Andreas Wolff | AE22: Karl Kupila | AF22: Christian Foltyn | AG22: Administrador | AH22: Director Financiero | AI22: Consejero | AJ22: Consejero Delegado | AK22: Administrador | AP22: No
A23: =+A22+1 -> 20 | B23: COBERTURA TECNOLÓGICA SL | D23: Y | E23: 1.0. Contacto fallido (sin descuelgue) | G23: Carlota | H23: Demetrio Suarez Castro | I23: 947472819 | J23: cobertec@cobertec.com | L23: B. Integradores TI generalistas | M23: B09401738 | N23: Servicios informáticos: programación, venta, mantenimiento | O23: NO WEB | P23: Ofrece un portfolio amplio: asesoría informática, mantenimiento, venta y reparación de hardware. Actúa multi-sector y sin verticalización específica. Se clasifica como integrador TI generalista. | Q23: Activa | R23: Cliente_OSP | S23: Burgos | T23: 09006 | U23: 331656 | V23: 5 | W23: 3 | X23: 0.2461 | Y23: 946404787 | Z23: 685106848 | AA23: 672243221 | AB23: 627410676 | AG23: Administrador | AH23: Director Financiero | AI23: Consejero | AJ23: Consejero Delegado | AK23: Administrador | AP23: No
A24: =+A23+1 -> 21 | B24: ENIM SOFT SL | D24: Y | E24: 1.0. Contacto fallido (sin descuelgue) | G24: Carlota | H24: Pedro Fernandez Gonzalez | L24: D. Desarrolladores de soluciones digitales básicas | M24: B65351884 | N24: Desarrollo de software, comercialización, mantenimiento, hardware, asesoramiento | O24: https://www.enimsoft.com/ | P24: Ofrece desarrollo de software, mantenimiento y venta de hardware, junto con asesoría técnica. No está enfocada a un único sector, sino a servicios TI multi-sector. Se clasifica como integrador TI generalista. | Q24: Activa | R24: No_Cliente | S24: Barcelona | T24: 08243 | U24: 1003660 | V24: 7 | W24: 1 | X24: 0.2391 | AG24: Administrador | AH24: Director Financiero | AI24: Consejero | AJ24: Consejero Delegado | AK24: Administrador | AP24: No
A25: =+A24+1 -> 22 | B25: OPCON INFORMATICA SL | D25: Y | E25: 99. Descartado | F25: Está cerrado según Google Maps | G25: Susana | H25: Guillermo Navarro Marques | I25: 986436171 | J25: opcon@opconinformatica.com | L25: B. Integradores TI generalistas | M25: B36858512 | N25: Venta de consumibles, hardware, instalación y configuración de redes, soporte | O25: https://www.facebook.com/Opcon.Informatica.Vigo/ | P25: Ofrece hardware, instalación y mantenimiento de redes informáticas, con servicios de soporte. Multi-sector, propio de integrador TI generalista. | Q25: No Activa | R25: Cliente_OSP | S25: Pontevedra | T25: 36202 | U25: 674924 | V25: 4 | W25: 3 | X25: 0.2216 | Y25: 986415550 | Z25: 986430238 | AA25: 635678736 | AB25: 636679570 | AC25: Clotilde Fernandez Alvarez | AD25: Diego Sebastian Mendez Rami | AG25: Administrador | AH25: Director Financiero | AI25: Consejero | AJ25: Consejero Delegado | AK25: Administrador | AL25: info@opconinformatica.com | AP25: No
A26: =+A25+1 -> 23 | B26: ARROBA 2 SOLUCIONES SL | D26: Y | E26: 99. Descartado | G26: Carlota | H26: Jose Antonio Ruiz Helguera | I26: 675740147 | L26: B. Integradores TI generalistas | M26: B84181924 | N26: Prestación de servicios informáticos | O26: https://www.linkedin.com/company/arroba-soluciones-informaticas-sl?utm_source=chatgpt.com | P26: Empresa dedicada a servicios TI genéricos, abarcando distintas áreas. Multi-sector. Clasificada como integrador TI generalista. | Q26: No Activa | R26: Cliente_OSP | S26: Madrid | T26: 28027 | U26: 945305 | V26: 7 | W26: 1 | X26: 0.2188 | Y26: 675740148 | AC26: Jose Julio Beraza Velasco | AD26: Agustin Herrero Marcos | AE26: Jon Gorrochategui Hernandez | AG26: Administrador | AH26: Director Financiero | AI26: Consejero | AJ26: Consejero Delegado | AK26: Administrador | AP26: No
A27: =+A26+1 -> 24 | B27: DISTRIBUCION DE SISTEMAS Y CONSULTING INFORMATICO SL | D27: Y | E27: 1.2 Contactado: propuesta "en valoración" | F27: 24 DISTRIBUCION DE SISTEMAS Y CONSULTING INFORMATICO SL 0. Pendiente contactar Venta especialista Jose Vicente Serrano Ortiz 913294461 A. Informáticos B80056765 Venta de paquetes de gestión, desarrollo a medida, consultoría TI y venta de equipos Distribucion De Sistemas Y Consulting Informatico Sl - Teléfono y dirección | Empresite Activa Cliente_OSP Madrid 28042 7,876,768 € 110 3 0.2182 913294461 917476498 934738032 699981852 Administrador Director Financiero Consejero Consejero Delegado Administrador info@codisys.es msanchez@codisys.es No Consultoría informática y servicios IT. ✔ Desarrollo de software personalizado. ✔ Venta de soluciones tecnológicas completas (software + hardware). ✔ Soporte técnico y servicios post-venta. ✔ Proyectos tecnológicos para sectores como retail, hostelería, administración pública, etc 28-01 913294461- Gk. Pendiente mandar email con modelo colaborativo a info@codisys.es Att. RRHH | G27: Venta especialista | H27: Jose Vicente Serrano Ortiz | I27: 913294461 | L27: A. Informáticos | M27: B80056765 | N27: Venta de paquetes de gestión, desarrollo a medida, consultoría TI y venta de equipos | O27: Distribucion De Sistemas Y Consulting Informatico Sl - Teléfono y dirección | Empresite | P27: Portfolio de Business Apps (TPV/retail), infraestructura y soporte; evidencias en su web corporativa. Foco vertical claro en retail/HORECA (sectorial). Se clasifica como integrador TI sectorial por soluciones estandarizadas para punto de venta. | Q27: Activa | R27: Cliente_OSP | S27: Madrid | T27: 28042 | U27: 7876768 | V27: 110 | W27: 3 | X27: 0.2182 | Y27: 913294461 | Z27: 917476498 | AA27: 934738032 | AB27: 699981852 | AG27: Administrador | AH27: Director Financiero | AI27: Consejero | AJ27: Consejero Delegado | AK27: Administrador | AL27: info@codisys.es | AM27: msanchez@codisys.es | AP27: No
A28: =+A27+1 -> 25 | B28: SIT WORLD WIDE SL | D28: Y | E28: 1.0. Contacto fallido (sin descuelgue) | G28: Carlota | H28: Daniel Gomez | L28: D. Desarrolladores de soluciones digitales básicas | M28: B65186165 | N28: Comercialización y servicios/asesoría de productos informáticos y telecomunicaciones | O28: www.sitmobile.com | P28: Ofrece plataforma de mensajería/SMS y servicios digitales (comunicaciones) — categoría Business Apps/Internet. Multisector sin vertical único. Se clasifica como desarrollador de soluciones digitales (servicios online y plataformas). | Q28: Activa | R28: No_Cliente | S28: Barcelona | T28: 08007 | U28: 1231336 | V28: 1 | W28: 1 | X28: 0.2181 | AC28: Rosario Bioque | AD28: Daniel Antonio Gomez Primo | AG28: Administrador | AH28: Director Financiero | AI28: Consejero | AJ28: Consejero Delegado | AK28: Administrador | AP28: No
A29: =+A28+1 -> 26 | B29: CAST SOFTWARE ESPAÑA SL | D29: Y | E29: 1.0. Contacto fallido (sin descuelgue) | G29: Carlota | H29: Jose Manuel Suso Beitia | I29: 914136283 | L29: E. Consultoras innovación digital | M29: B82690728 | N29: Asesoramiento, adaptación, fabricación y comercialización de software | O29: www.castsoftware.com | P29: Oferta de software intelligence/analítica avanzada de sistemas (Cloud, calidad, cumplimiento) — categorías IA/Analítica/Business Apps. Multisector corporativo. Se clasifica como consultora/servicios de innovación digital. | Q29: Activa | R29: No_Cliente | T29: 28002 | U29: 899022 | V29: 5 | W29: 1 | X29: 0.2175 | Y29: 915155672 | Z29: 913091179 | AA29: 638198725 | AC29: Francisco Javier Fernandez Calleja | AG29: Administrador | AH29: Director Financiero | AI29: Consejero | AJ29: Consejero Delegado | AK29: Administrador | AP29: No
A30: =+A29+1 -> 27 | B30: OPENTIC SERVEIS INFORMATICS SL | D30: Y | E30: 1.0. Contacto fallido (sin descuelgue) | G30: Carlota | H30: Sergio Peña | I30: 937517955 | L30: D. Desarrolladores de soluciones digitales básicas | M30: B65493355 | N30: Desarrollo de aplicaciones informáticas y servicios varios informáticos | O30: NO WEB | P30: Se centra en el desarrollo de aplicaciones y servicios informáticos; su actividad está claramente en el ámbito digital (apps, servicios TI). Empresite EspañaeInforma | Q30: Activa | R30: No_Cliente | S30: Barcelona | T30: 08330 | U30: 1082599 | V30: 8 | W30: 1 | X30: 0.3969 | Y30: 937904039 | Z30: 669842080 | AA30: 626164787 | AC30: Antonio Roda Baños | AD30: Ramon Soto Muñoz | AE30: Sergio Peña Pueyo | AG30: Administrador | AH30: Director Financiero | AI30: Consejero | AJ30: Consejero Delegado | AK30: Administrador | AP30: No
A31: =+A30+1 -> 28 | B31: WEB CARGO SL | C31: Y | D31: Y | E31: 99. Descartado | F31: 8-1 933 79 93 01 Es web cargo, pero la empresa es extranjera. - 934 65 67 31 No disponible - Mando correo | G31: Venta especialista | H31: Joaquim Santos Lopez | I31: 934656731 | J31: sales@webcargo.com | K31: 933 79 93 01 / 934 65 67 31 | L31: D. Desarrolladores de soluciones digitales básicas | M31: B64924376 | N31: Desarrollo de herramientas informáticas web | O31: https://es.webcargonet.com/ | P31: Web activa, especializada en soluciones web (logística, carga aérea). Vertical claro en transporte/logística → sectorial. Reclasificado como C. | Q31: No Activa | R31: No_Cliente | S31: Barcelona | T31: 08915 | U31: 1377966 | V31: 24 | W31: 3 | X31: 0.1945 | Y31: 933799301 | Z31: 931407997 | AA31: 722608878 | AB31: 678504763 | AG31: Administrador | AH31: Director Financiero | AI31: Consejero | AJ31: Consejero Delegado | AK31: Administrador | AP31: No
A32: =+A31+1 -> 29 | B32: GALEA CONSULTING DE SERVICIOS INTEGRALES SL | E32: 1.0. Contacto fallido (sin descuelgue) | F32: Ofrece productos y consultoría | G32: María | I32: +34 91/3833779 | J32: no hay | K32: 913 83 37 79 | L32: B. Integradores TI generalistas | M32: B83195420 | N32: Es una empresa del sector de las TIC que comercializa tecnologías informáticas de última generación y ofrece un servicio de consultoría y asistencia al cliente. | O32: https://www.galeaconsulting.com/ | P32: Es una empresa del sector de las TIC que comercializa tecnologías informáticas de última generación y ofrece un servicio de consultoría y asistencia al cliente. | Q32: Activa | S32: Madrid | T32: MADRID | V32: 11 | X32: galea@galeaconsulting.com | AP32: No
A33: =+A32+1 -> 30 | B33: TIC-SYSTEMS SUPPORT SERVICE GROUP SL. | E33: 1.0. Contacto fallido (sin descuelgue) | G33: Juan | H33: Carmen | I33: 93 153 79 40 | J33: info@tic-systems.com | K33: 931860202 | L33: C. Integradores TI sectoriales | M33: B66206004 | N33: Mantenimiento informático presencial y también en remoto para responder a cualquier urgencia en la máxima brevedad. Redes, servidores y comunicaciones, seguridad informática (ciberseguridad), VoIP y servicios Cloud, diseño web y tienda online… | O33: Servicios informáticos para empresas en Barcelona | Tic-Systems | P33: Tic‑Systems es una IT boutique barcelonesa con 20 años de experiencia, que ofrece mantenimiento, infraestructuras, ciberseguridad, VoIP, cloud, web/e‑commerce y digitalización integral como agente Kit Digital | Q33: Activa | S33: Barcelona | T33: L'HOSPITALET DE LLOBREGAT | V33: 1 | X33: info@tic-systems.com | AP33: No
A34: =+A33+1 -> 31 | B34: NUBUS TECHNOLOGIES CORPORATION, SOCIEDAD LIMITADA | E34: 1.0. Contacto fallido (sin descuelgue) | F34: Horario 9-18, me tienen que volver a llamar | G34: María | I34: +34 62/6179256 | K34: 911 44 38 38/931 78 02 25 | L34: B. Integradores TI generalistas | M34: B55756506 | N34: Consultoria integral de IT + venta y reparacion de todos dispositivos (PCs, routers, etc…) | O34: Contáctanos - Nubus Technologies | P34: Nubus Technologies ofrece servicios gestionados de TI, ciberseguridad, cloud y backup para empresas, ayudando a digitalizar procesos y garantizar la seguridad y disponibilidad de la infraestructura. | Q34: Activa | S34: Cataluña | T34: EL ROURELL | V34: 0 | X34: administracion@nubustech.com | AP34: No
A35: =+A34+1 -> 32 | B35: SIT SPORTS SL | D35: N | E35: 1.2 Contactado: propuesta "en valoración" | F35: 8-1 915 00 28 34 Contacto con Pilar, me indica que a priori no estan interesados en nada, pero aun asi su correo es psegovia@sitgrupo.es | G35: Venta especialista | K35: 915 00 28 34 | L35: - | M35: B66238056 | N35: Tecnología para deporte, gestión digital y plataformas asociadas | O35: Home | SIT Grupo | P35: Ofrece soluciones digitales para el deporte; verticalizado en sector deportivo; requiere validación por falta de web. | Q35: Activa | S35: Madrid | AP35: No
A36: =+A35+1 -> 33 | B36: ANUBIS SERVICIOS INFORMATICOS SLL | D36: N | E36: 1.3 Contactado "muerto" | F36: Enviado mail 16/10 | G36: Carlota | J36: sserrano@anubisgestion.com | K36: 957 49 00 50 | L36: A. Informáticos | M36: B91727762 | N36: Servicios de instalación y mantenimiento informático | O36: NO WEB | P36: Instalación y soporte técnico TI; multi-sector; falta web oficial → requiere validación. | Q36: Activa | S36: Córdoba | AP36: No
A37: =+A36+1 -> 34 | B37: SAMURAI 2010 SL | D37: N | E37: 1.0. Contacto fallido (sin descuelgue) | F37: Llamar de nuevo. Comunica | G37: Juan | J37: office@wadyproperties.com | K37: 922 71 22 54 | L37: D. Desarrolladores de soluciones digitales básicas | M37: B76527936 | N37: Desarrollo de software y consultoría TI | O37: NO WEB | P37: Desarrollo de soluciones digitales y servicios TI; multi-sector; requiere validación. | Q37: Activa | AP37: No
A38: =+A37+1 -> 35 | B38: GESTION Y ANALISIS DE PROCESOS SL | D38: N | E38: 1.3 Contactado "muerto" | F38: Enviado mail 16/10 (están dentro del grupo Inforges) | G38: Carlota | H38: Michel Boufedji Martial | I38: 954231451 | J38: marketing@inforges.es | L38: B. Integradores TI generalistas | M38: B91818542 | N38: Fabricación, venta de hardware y desarrollo de software | O38: https://gapconsult.es/nosotros/ | P38: Combina hardware y desarrollo de software/aplicaciones, lo cual es típico de integradores TI que ofrecen servicios completos; enfoque multi-sector. | Q38: Activa | R38: No_Cliente | S38: Sevilla | T38: 41013 | U38: 1065626 | V38: 1 | W38: 1 | X38: 0.24 | Y38: 955549521 | Z38: 932651950 | AA38: 605065563 | AB38: 639714805 | AC38: Jean Marc Lazzari | AD38: Jean Marie Buisson Jacques | AE38: James Albert Rullaud Christophe | AF38: Jose Manuel Dafonte Perez | AG38: Administrador | AH38: Director Financiero | AI38: Consejero | AJ38: Consejero Delegado | AK38: Administrador | AP38: No
A39: =+A38+1 -> 36 | B39: GUSTO DELITIA SL | D39: N | E39: 1.0. Contacto fallido (sin descuelgue) | F39: Apagado o fuera de cobertura | G39: Juan | H39: Jose Angel Garrido Miguel | I39: 938320234 | L39: B. Integradores TI generalistas | M39: B63833099 | N39: Distribución y comercialización de software de terceros, soporte técnico y mantenimiento | O39: NO WEB | P39: Se centra en distribución de software, servicios de soporte técnico y comercialización de productos informáticos. Multi-sector, sin especialización concreta. Se clasifica como integrador TI generalista. | Q39: Activa | R39: No_Cliente | S39: Barcelona | T39: 08242 | U39: 982538 | V39: 3 | W39: 1 | X39: 0.2357 | AC39: Miguel Angel Mingo Collantes | AD39: Alberto Mingo Santibañez | AG39: Administrador | AH39: Director Financiero | AI39: Consejero | AJ39: Consejero Delegado | AK39: Administrador | AP39: No
A40: =+A39+1 -> 37 | B40: AVESOFT SL | D40: N | E40: 1.0. Contacto fallido (sin descuelgue) | F40: Apagado o fuera de cobertura | G40: Juan | H40: Jose Maria Lazaro Correcher | I40: 928263687 | J40: averand@hotmail.com | L40: B. Integradores TI generalistas | M40: B35660216 | N40: Gestión y servicios de recursos informáticos, asesoramiento técnico | O40: NO WEB | P40: Proporciona gestión y soporte de recursos informáticos junto con asesoramiento técnico. Multi-sector, clasificada como integrador TI generalista. | Q40: Activa | R40: No_Cliente | S40: Las Palmas | T40: 35017 | U40: 562942 | V40: 0 | W40: 1 | X40: 0.2317 | Y40: 928354866 | Z40: 608473548 | AA40: 649449550 | AB40: 630904498 | AC40: Felix Vega Lagos | AG40: Administrador | AH40: Director Financiero | AI40: Consejero | AJ40: Consejero Delegado | AK40: Administrador | AP40: No
A41: =+A40+1 -> 38 | B41: SABER NUEVAS TECNOLOGÍAS SL | D41: N | E41: 99. Descartado | G41: Carlota | H41: David Martin Torres | I41: 976555522 | L41: B. Integradores TI generalistas | M41: B99183576 | N41: Estudio de procesos, programación, registro de datos, distribución de software | O41: NO WEB | P41: Su actividad combina programación, distribución de software y servicios de registro y análisis de datos. Multi-sector, sin verticalización clara. Clasificada como integrador TI generalista. | Q41: No Activa | R41: No_Cliente | S41: Zaragoza | T41: 50009 | U41: 1209290 | V41: 1 | W41: 1 | X41: 0.2308 | Y41: 976436030 | AC41: Jesus Blanco Garcillan | AG41: Administrador | AH41: Director Financiero | AI41: Consejero | AJ41: Consejero Delegado | AK41: Administrador | AP41: No
A42: =+A41+1 -> 39 | B42: COMPUTER GLOBAL SOFTWARE SL | D42: N | E42: 99. Descartado | F42: 2 teléfonos no válidos. Usar para llamar en otro momento el que no está marcado en rojo | G42: Susana | H42: Fernando Ortiz Garcia | I42: 924248450 | J42: ruben.montero@xone.es | K42: 924207371 / 902052574 | L42: D. Desarrolladores de soluciones digitales básicas | M42: B06373864 | N42: Elaboración, instalación, mantenimiento y comercialización de programas de ordenador | O42: NO WEB | P42: Su actividad consiste en desarrollo, instalación y mantenimiento de software. Sin evidencia de sector único, multi-sector. Clasificada como desarrollador de soluciones digitales básicas. | Q42: Activa | R42: Cliente_OSP | S42: Badajoz | T42: 06001 | U42: 967870 | V42: 17 | W42: 6 | X42: 0.2286 | Y42: 924207371 | Z42: 956496575 | AA42: 956181130 | AB42: 685102990 | AC42: Rafael Rodriguez Garcia | AD42: Angel Ramirez Navarro | AE42: Fernando Mansilla Anguera | AG42: Administrador | AH42: Director Financiero | AI42: Consejero | AJ42: Consejero Delegado | AK42: Administrador | AL42: contacta@xone.es | AP42: No
A43: =+A42+1 -> 40 | B43: GENEK LOGISTICS SL | D43: N | E43: 99. Descartado | F43: Comunicaba todo el rato | G43: Susana | H43: Ramon Rufian Milla | I43: 977650557 | L43: A. Informáticos | M43: B43793769 | N43: Servicios de montaje, logística y transporte de productos informáticos | O43: NO WEB | P43: Presta servicios de montaje y logística vinculados a equipos informáticos. Enfocado en hardware y soporte, sin software avanzado. Clasificado como informático tradicional. | Q43: Activa | R43: No_Cliente | S43: Tarragona | T43: 43008 | U43: 1089817 | V43: 1 | W43: 2 | X43: 0.2284 | AC43: Antonio Casado Valencia | AG43: Administrador | AH43: Director Financiero | AI43: Consejero | AJ43: Consejero Delegado | AK43: Administrador | AP43: No
A44: =+A43+1 -> 41 | B44: HABLA Y COMUNICA SL | D44: N | E44: 99. Descartado | G44: Juan | H44: Equipo 100 | I44: 635878167 | J44: victor.navas@hablaycomunica.com | K44: 933560570 | L44: A. Informáticos | M44: B65885568 | N44: Venta al público de telefonía y accesorios; activación de líneas | O44: NO WEB | P44: Actividad centrada en venta y soporte de telefonía, más hardware y accesorios. Multi-sector, sin innovación digital. Se clasifica como informático tradicional. | Q44: Activa | R44: Cliente_OSP | S44: Barcelona | T44: 08038 | U44: 542573 | V44: 4 | W44: 1 | X44: 0.2249 | AG44: Administrador | AH44: Director Financiero | AI44: Consejero | AJ44: Consejero Delegado | AK44: Administrador | AP44: SI
A45: =+A44+1 -> 42 | B45: VALLE GRAN REY INFORMATICA SL | D45: N | E45: 1.1 Contactado: propuesta "rechazada" | F45: 8-1 922 805 999 Cliente descontento con MasOrange ya que ha estado 3 semanas sin fibra en plena campaña de navidad, indica que hasta que no se solucione y pase el tiempo no querrá hacer nada. Su correo es comercial@cibermatika.com | G45: Venta especialista | H45: Concepcion Mayoral Palau | I45: 922805223 | K45: 922805223 | L45: A. Informáticos | M45: B38867297 | N45: Venta, distribución, instalación y reparación de equipos informáticos y de oficina | O45: NO WEB | P45: Se dedica a la venta y reparación de equipos informáticos y accesorios. Multi-sector y sin innovación digital. Clasificada como informático tradicional. | Q45: No Activa | R45: No_Cliente | S45: Santa Cruz de Tenerife | T45: 38870 | U45: 875481 | V45: 7 | W45: 2 | X45: 0.222 | AC45: Juan Jose Azcarate Morera | AD45: Alfonso Torres Sanchez | AE45: Elena Gomez Pozuelo | AG45: Administrador | AH45: Director Financiero | AI45: Consejero | AJ45: Consejero Delegado | AK45: Administrador | AP45: No
A46: =+A45+1 -> 43 | B46: VENTURE SYSTEMS 21 SA | D46: N | E46: 99. Descartado | F46: 8-1 915 628 901 Aparece en internet como inactiva. Llamo en horario de atencion pero aun asi salta el contestador | G46: Venta especialista | H46: Manuel Angel Bernardez Loira | I46: 915628901 | L46: B. Integradores TI generalistas | M46: A85996221 | N46: Análisis de procesos, tratamiento mecánico de datos, tabulación y centro de cálculo | O46: NO WEB | P46: Actividad de procesamiento de datos, centro de cálculo y servicios de análisis de procesos informáticos. Multi-sector, encaja como integrador TI generalista. | Q46: No Activa | R46: No_Cliente | S46: Madrid | T46: 28006 | U46: 366734 | V46: 3 | W46: 1 | X46: 0.2217 | AC46: Jesus Palacios Parra | AG46: Administrador | AH46: Director Financiero | AI46: Consejero | AJ46: Consejero Delegado | AK46: Administrador | AP46: No
A47: =+A46+1 -> 44 | B47: CHIP WORK INFORMATICA Y COMUNICACIONES | E47: 1.1 Contactado: propuesta "rechazada" | G47: Juan | I47: 981 39 71 18 | J47: info@chipwork.net | K47: 981 397 118 | L47: A. Informáticos | M47: B15724222 | N47: Venta, Instalación y Mantenimiento | Q47: Activa | AP47: No
A48: =+A47+1 -> 45 | B48: BANANA COMPUTER SOCIEDAD LIMITADA | C48: Y | D48: Y | E48: 99. Descartado | F48: Productos apple | G48: Carlota | H48: Antonio Sanchez Azorin | I48: 928912410 | J48: protecciondatos@bananacomputer.com | K48: NO HAY | L48: A. Informáticos | M48: B35290634 | N48: Comercio mayorista y minorista de hardware/software, importación y distribución | O48: https://tienda.bananacomputer.com/trabaja-con-nosotros/ | P48: Web activa como retailer de informática y electrónica en Canarias. Actividad centrada en hardware y venta al por mayor/menor. Clasificada como informáticos. | Q48: Activa | R48: No_Cliente | S48: Las Palmas | T48: 35006 | U48: 17900986 | V48: 40 | W48: 7 | X48: 0.2066 | Y48: 928275624 | Z48: 928912756 | AA48: 928242828 | AB48: 928207418 | AC48: Francisco Jose Boyer Abad | AG48: Administrador | AH48: Director Financiero | AI48: Consejero | AJ48: Consejero Delegado | AK48: Administrador | AL48: laura@bananacomputer.com | AM48: ovidia@bananacomputer.com | AN48: leticia@bananacomputer.com | AO48: atencionalcliente@bananacomputer.com | AP48: No
A49: =+A48+1 -> 46 | B49: NALCOM SERVICIOS INFORMATICOS INTEGRALES SL | E49: 99. Descartado | F49: Consultoria Tech | G49: Blanca | I49: +34 91/3013709 | J49: info@nalcom.com | K49: 913013709 | L49: D. Desarrolladores de soluciones digitales básicas | M49: B82826587 | N49: Otros servicios relacionados con las tecnologías de la información y la informática | O49: Consultoría Informática en Madrid - Desarrollo de software a medida | P49: Consultoría TI, software industrial (SCADA), hardware, soporte | Q49: Activa | S49: Madrid | T49: MADRID | V49: 5 | X49: info@nalcom.com | AP49: No
A50: =+A49+1 -> 47 | B50: TWOAPART SL | C50: Y | D50: Y | E50: 99. Descartado | F50: No existe telefono, web ni mail de contacto | G50: Venta especialista | H50: Ximena Maier Pan Soraluce | L50: D. Desarrolladores de soluciones digitales básicas | M50: B86505427 | N50: Desarrollo, mantenimiento y explotación de redes sociales a través de redes telemáticas | O50: NO WEB | P50: Perfil de LinkedIn confirma la actividad digital / redes sociales. | Q50: No Activa | R50: No_Cliente | S50: Madrid | T50: 28914 | U50: 7911475 | V50: 12 | W50: 1 | X50: 0.1773 | AG50: Administrador | AH50: Director Financiero | AI50: Consejero | AJ50: Consejero Delegado | AK50: Administrador | AP50: No
A51: =+A50+1 -> 48 | B51: HITWARE SL | D51: N | E51: 99. Descartado | F51: Datos incorrectos de contacto | G51: Carlota | H51: Gabino Fernandez Fanjul | I51: 616959349 | J51: mgamadrid@gmail.com | K51: 913 61 38 50 | L51: B. Integradores TI generalistas | M51: B81500811 | N51: Desarrollo y venta de productos y servicios telemáticos, hardware y periféricos | O51: NO WEB | P51: Combina servicios telemáticos (software) con venta/arriendo de hardware informático; diversificado y multi-sector, típico de integradores TI generalistas. | Q51: No Activa | R51: No_Cliente | S51: Madrid | T51: 28027 | U51: 1136875 | V51: 5 | W51: 2 | X51: 0.2412 | AC51: Jose Ignacio Garrido Pardo | AG51: Administrador | AH51: Director Financiero | AI51: Consejero | AJ51: Consejero Delegado | AK51: Administrador | AP51: No
A52: =+A51+1 -> 49 | B52: EMAGANET CONSULTORIA SL | D52: N | E52: 1.0. Contacto fallido (sin descuelgue) | F52: Número de telefono erróneo | G52: Juan | H52: Federico Sanchez Guedj | I52: 645925228 | J52: info@emaganet.com | K52: 645 92 52 28 | L52: E. Consultoras innovación digital | M52: B84727296 | N52: Diseño, programación y mantenimiento web; consultoría tecnológica y e-commerce | O52: NO WEB | P52: Actividad centrada en programación web, e-commerce y consultoría tecnológica, abarcando soporte integral de TI para pymes y empresas; por eso se clasifica como integrador generalista. | Q52: Activa | R52: No_Cliente | S52: Madrid | T52: 28053 | U52: 928786 | V52: 7 | W52: 1 | X52: 0.2402 | AC52: Didier Jean Louis | AG52: Administrador | AH52: Director Financiero | AI52: Consejero | AJ52: Consejero Delegado | AK52: Administrador | AP52: No
A53: =+A52+1 -> 50 | B53: I- SISTEMAS OFIMÁTICA E INFORMÁTICA PROFESIONAL (SISTEMAS DE OFICINA DE OURENSE SL) | E53: 1.1 Contactado: propuesta "rechazada" | F53: No les interesa la propuesta | G53: Susana | J53: info@i-sistemas.com | K53: 988 233 952 | L53: A. Informáticos | M53: B3030513 | N53: No disponemos ni subcontratamos con terceras empresas ningún servicio o suministro de nuestra cadena de valor. | O53: ▷ i-sistemas - Especialistas en Informática para empresas | Q53: No Activa | S53: Orense | AP53: No
A54: =+A53+1 -> 51 | B54: BUSINESS SERVICOM ORENSE SL | E54: 1.3 Contactado "muerto" | F54: Reminder 4-nov | G54: Susana | J54: ventas@businessservicom.com | K54: 604 02 15 96 | L54: B. Integradores TI generalistas | M54: B32204067 | O54: BUSINESS SERVICOM - Contacto | Q54: No Activa | S54: Orense | AP54: No
A55: =+A54+1 -> 52 | B55: HEALTHYPC / PROINF INFORMATICA SC | E55: 1.0. Contacto fallido (sin descuelgue) | F55: Volver a llamar (he llamado 3 veces y ocupado) | G55: Juan | I55: 981 59 45 05 | J55: info@healthypc.es | K55: 606 039 056 | L55: A. Informáticos | M55: J70908868 | O55: Contacto - HealthyPc Servicio Técnico Informático | Reparación Apple/Pc, Portátiles y sobremesa, Smartphone, Tablets, equipos de audio y Tv | Q55: Activa | S55: Santiago de Compostela | AP55: No
A56: =+A55+1 -> 53 | B56: INFORMATICA MARFER SL | E56: 1.3 Contactado "muerto" | F56: 16/10/2025 (reminder) | G56: Susana | H56: Shih Kai Wang | I56: 982263084 | J56: correo@imarfer.com / alvaro@imarfer.com | K56: 982 263 084 | L56: A. Informáticos | M56: B27227073 | N56: COMERCIO AL MENOR DE ORDENADORES Y PROGRAMAS INFORMATICOS. . | O56: KIT DIGITAL LUGO | Q56: Activa | S56: Lugo | AP56: SI
A57: =+A56+1 -> 54 | B57: CROWNET GALICIA SLU | E57: 1.0. Contacto fallido (sin descuelgue) | F57: comunicaba todo el rato | G57: Juan | J57: correo@crownetgalicia.com | K57: 982 81 25 88 | L57: B. Integradores TI generalistas | M57: B27279363 | O57: Crownet Galicia - Servicios y soluciones informáticas | Q57: Activa | S57: Lugo | AP57: No
A58: =+A57+1 -> 55 | B58: MALAGAMICRO | E58: 1.3 Contactado "muerto" | F58: 16/10/2025 (reminder) | G58: Susana | K58: 951 629 472 | L58: B. Integradores TI generalistas | M58: B92187475 | O58: Contacto - Malagamicro. Empresa de Servicio Técnico y Mantenimiento Informático en Málaga | Q58: Activa | S58: Málaga | AP58: No
A59: =+A58+1 -> 56 | B59: OLINET SLU | E59: 99. Descartado | F59: 5-10 952207135 (1) No contestan // 11-11 952207135 (1) No contestan // 21-11 952207135 (1) No contestan | G59: Venta especialista | J59: info@olinet.es | K59: 952 207 135 | L59: B. Integradores TI generalistas | M59: B29194503 | O59: Mantenimiento informático para empresas en Málaga - Olinet SL | Q59: Activa | S59: Málaga | AP59: No
A60: =+A59+1 -> 57 | B60: NOVANET SOLUCIONES INFORMATICAS | E60: 1.2 Contactado: propuesta "en valoración" | F60: 27-01 951156270- Llamar mañana por la mañana para hablar con Miguel Ángel. | G60: Venta especialista | H60: Miguel Ángel Moreno () | J60: info@malaganovanet.com | K60: 951 15 62 70 / 951 10 99 99 | L60: B. Integradores TI generalistas | M60: B42810812 | O60: Servicios de Mantenimiento Informatico a Empresas en Málaga | Q60: Activa | S60: Málaga | AP60: No
A61: =+A60+1 -> 58 | B61: INFORMATICA ISEMAT SL | D61: Y | E61: 1.3 Contactado "muerto" | G61: Anna | H61: Manuel Fernando Gomez Carpintero Nuñez De Arenas | I61: 924262666 | J61: isemat@isemat.com | L61: D. Desarrolladores de soluciones digitales básicas | M61: B06315709 | N61: Venta de productos y consumibles informáticos; desarrollo de software | O61: https://www.isemat.com/ | P61: Combina venta de productos informáticos y consumibles con desarrollo de software y asesoramiento. No especializado en un sector concreto, encaja como soluciones digitales básicas. Faltan datos recientes, requiere validación. | Q61: No Activa | R61: Cliente_OSP | S61: Badajoz | T61: 06008 | U61: 808119 | V61: 3 | W61: 5 | X61: 0.5217 | Y61: 924262826 | Z61: 924041747 | AA61: 924903386 | AB61: 685339974 | AC61: Fernando Peces Castillo | AD61: Luis Arenal Conde | AE61: Alfonso Careaga Bravo | AF61: Maria Via Melich | AG61: Administrador | AH61: Director Financiero | AI61: Consejero | AJ61: Consejero Delegado | AK61: Administrador | AL61: info@tiendabrowser.com | AP61: No
A62: =+A61+1 -> 59 | B62: NESTOLA NETSYSTEM MEDIA SL | C62: Y | D62: Y | E62: 1.2 Contactado: propuesta "en valoración" | F62: 26.01 Reasignado a Juan. Intenta recontacto | Enviada invitación, mandar mensaje una vez aceptada | G62: Juan | H62: Manuel Esteban Mozos | I62: 917505039 | J62: info@netsystem.es | K62: 629 178 908 | L62: B. Integradores TI generalistas | M62: B83650390 | N62: Servicios y asesoramiento informático; compraventa, instalación y reparación de material informático | O62: www.netsystem.es | P62: Web oficial activa, ofrece soporte TI completo: hardware, mantenimiento, asesoría. Multi-sector. Clasificada como integrador TI generalista. | Q62: Activa | R62: No_Cliente | S62: Madrid | T62: 28050 | U62: 1027279 | V62: 7 | W62: 2 | X62: 0.1844 | Y62: 917505129 | AC62: Manuel Esteban De Los Mozos | AG62: Administrador | AH62: Director Financiero | AI62: Consejero | AJ62: Consejero Delegado | AK62: Administrador | AP62: No
A63: =+A62+1 -> 60 | B63: SINE 95 SL | C63: Y | D63: Y | E63: 1.3 Contactado "muerto" | G63: Susana | H63: Jose Simon Ibañez Chaler | I63: 918326659 | K63: 915 91 65 88 | L63: B. Integradores TI generalistas | M63: B81063745 | N63: Desarrollo de software para entornos IBM, consultoría e ingeniería de sistemas | O63: www.sine95.com | P63: Web oficial activa. Portfolio en software IBM, consultoría y sistemas. Multi-sector. Clasificada como integrador TI generalista. | Q63: No Activa | R63: Cliente_OSP | S63: Madrid | T63: 28043 | U63: 1548561 | V63: 24 | W63: 1 | X63: 0.1751 | Y63: 917478091 | AG63: Administrador | AH63: Director Financiero | AI63: Consejero | AJ63: Consejero Delegado | AK63: Administrador | AP63: No
A64: =+A63+1 -> 61 | B64: BEONPRICE SL | C64: Y | D64: Y | E64: 1.3 Contactado "muerto" | G64: Susana | H64: Luis Manuel Aranda Parras | I64: 923100220 | K64: NO HAY | L64: C. Integradores TI sectoriales | M64: B37517844 | N64: Programación informática y consultoría; gestión de recursos informáticos; portales web | O64: www.beonprice.com | P64: Web oficial activa, empresa especializada en Revenue Management para el sector hotelero. Vertical turismo/hotelero. Clasificada como integrador TI sectorial. | Q64: No Activa | R64: No_Cliente | S64: Salamanca | T64: 37185 | U64: 615144 | V64: 15 | W64: 2 | X64: 0.1705 | Y64: 685694941 | Z64: 667668195 | AA64: 657663471 | AB64: 616559302 | AG64: Administrador | AH64: Director Financiero | AI64: Consejero | AJ64: Consejero Delegado | AK64: Administrador | AP64: No
A65: =+A64+1 -> 62 | B65: INFORMÁTICA 222 | E65: 1.3 Contactado "muerto" | F65: 45938 | G65: Susana | H65: Carlos Villar | J65: jcvillar@i-222.com | K65: 981 160 096 | L65: B. Integradores TI generalistas | M65: B15167224 | O65: Informática 222 | Q65: Activa | S65: A Coruña | AP65: No
A66: =+A65+1 -> 63 | B66: Processos i Comunicacions Informàtiques S L | C66: Y | D66: Y | E66: 1.2 Contactado: propuesta "en valoración" | F66: Enviar correo a Ana | G66: Juan | J66: info@procesos.com | K66: 932 107 910 / 936 764 388 | L66: B. Integradores TI generalistas | M66: B59163766 | N66: Ofrecen un portfolio integral de servicios TI para empresas: mantenimiento informático, consultoría, renting tecnológico, cloud, servidores, comunicaciones unificadas y seguridad (firewall, pentesting, copias blindadas). Además, incluyen desarrollo web (WordPress, Django, e-commerce, SEO) y soluciones de digitalización con Kit Digital. | O66: Inicio - Procesos Soluciones TI | P66: Cubren todas las áreas básicas de TI (workplace, cloud, ciberseguridad, business apps), atendiendo a pymes y empresas de múltiples sectores, sin especialización vertical concreta. | Q66: Activa | S66: Barcelona | T66: 08024 | AP66: No
A67: =+A66+1 -> 64 | B67: ACCON SOFTWARE SL | C67: Y | D67: Y | E67: 1.2 Contactado: propuesta "en valoración" | F67: Enviar correo a Jordi | G67: Juan | H67: Jordi Accon | J67: info@accon.com | K67: 934 882 416 | L67: B. Integradores TI generalistas | M67: B62203542 | N67: mpresa con más de 20 años ofreciendo servicios integrales de TI: mantenimiento informático, suministro tecnológico, servicios de infraestructura (virtualización, almacenamiento, redes), consultoría, ciberseguridad, desarrollo de software, diseño web y soluciones cloud. También es agente digitalizador del Kit Digital. | O67: Servicios informáticos para empresas | P67: Cubre de forma transversal todas las necesidades TI de empresas (workplace, cloud, ciberseguridad, desarrollo web/software), atendiendo a múltiples sectores y sin una especialización vertical única. | Q67: Activa | S67: Barcelona | AP67: No
A68: =+A67+1 -> 65 | B68: TENDENCIAS ORIGINALES DOCUMENTADAS IT SL | E68: 1.3 Contactado "muerto" | F68: Enviado correo 16/10 | G68: Carlota | H68: Mario Martínez Contreras | I68: 666 448 027 | J68: aoliver@todoit.es | K68: 666 44 80 27 | L68: D. Desarrolladores de soluciones digitales básicas | M68: B86396835 | N68: Actividades de consultoría informática | O68: www.todoit.es | P68: todoIT provee infraestructura TI, soporte integral, soluciones audiovisuales, control de acceso y Kit Digital completo (web, marketing, CRM, ciberseguridad y procesos) para pymes. | Q68: Activa | S68: Madrid | T68: POZUELO DE ALARCON | V68: 1 | X68: aoliver@todoit.es | AP68: No
A69: =+A68+1 -> 66 | B69: IN2 INGENIERIA DE LA INFORMACION SL | C69: Y | D69: Y | E69: 1.3 Contactado "muerto" | F69: Absorbidos por ALTIA. Comprobar si llamar a ALTIA | G69: Susana | H69: Rosario Aranda Hidalgo | I69: 936672490 | J69: in-2@in-2.com | K69: 661 29 68 61 | L69: B. Integradores TI generalistas | M69: B60645900 | N69: Consultoría informática, proyectos TI, venta de hardware y software | O69: www.in2.es | P69: Web oficial activa. Consultoría TI y desarrollo de proyectos, con venta de software/hardware. Multi-sector. Clasificada como integrador TI generalista. | Q69: No Activa | R69: No_Cliente | S69: Barcelona | T69: 08012 | U69: 5606724 | V69: 97 | W69: 6 | X69: 0.1735 | Y69: 934453400 | Z69: 695910231 | AA69: 687807258 | AB69: 686416311 | AC69: Carlos Daniel Mateu Aranda | AG69: Administrador | AH69: Director Financiero | AI69: Consejero | AJ69: Consejero Delegado | AK69: Administrador | AL69: bolsadetrabajo@in2.es | AM69: contacto@in2.es | AN69: luis.fernandez@in2.es | AO69: daniel.flores@in2.es | AP69: No
A70: =+A69+1 -> 67 | B70: SOFTEC INTERNET SL | D70: Y | E70: 1.3 Contactado "muerto" | G70: Susana | H70: Angel Ramirez Navarro | I70: 942354160 | J70: info@register.es | L70: B. Integradores TI generalistas | M70: B39492566 | N70: Servicios informáticos y electrónicos variados: programación, asesoramiento informático, etc. | O70: www.softec-internet.com | P70: Proporciona un amplio rango de servicios TI (programación, asesoría, electrónica); tiene web activa y balances recientes. Empresite EspañaEmpresiaDatos CIF | Q70: Activa | R70: No_Cliente | S70: Cantabria | T70: 39011 | U70: 1033509 | V70: 16 | W70: 3 | X70: 0.3911 | Y70: 942266407 | Z70: 942322243 | AA70: 942266406 | AB70: 942266340 | AC70: Carlos Kinder Espinosa | AG70: Administrador | AH70: Director Financiero | AI70: Consejero | AJ70: Consejero Delegado | AK70: Administrador | AL70: dominios@register.es | AM70: soporte@register.es | AN70: corporativoteka@register.es | AO70: gestion@register.es | AP70: No
A71: =+A70+1 -> 68 | B71: EINZELNET EXECUTIVE SERVICES SL | D71: Y | E71: 1.3 Contactado "muerto" | G71: Susana | H71: Diana Paloma Robledo Reyes | I71: 917986705 | J71: rrhh@einzelnet.com | L71: B. Integradores TI generalistas | M71: B86515517 | N71: Proyectos informáticos y telemáticos para clientes empresariales | O71: https://einzelnet.com/ | P71: Actividad centrada en proyectos TI, servicios telemáticos y soluciones corporativas para distintos clientes. Multi-sector, por lo que se clasifica como integrador TI generalista. | Q71: No Activa | R71: No_Cliente | S71: Madrid | T71: 28021 | U71: 1288078 | V71: 27 | W71: 1 | X71: 0.232 | Y71: 915052019 | AC71: Paloma Robledo Reyes | AD71: Christine Amelie Marie Andree Allain Launay | AE71: Romain Selimir Claude Allain Launay | AF71: Julien Hugues Johan | AG71: Administrador | AH71: Director Financiero | AI71: Consejero | AJ71: Consejero Delegado | AK71: Administrador | AP71: No
A72: =+A71+1 -> 69 | B72: SOLUCIONES INFORMATICAS ADV SA | D72: Y | E72: 1.0. Contacto fallido (sin descuelgue) | F72: 28-01 986 37 87 61-Llamar en otro momento está ocupado. | G72: Carlota | J72: siadv@siadv.com | K72: 918 82 29 29 | L72: D. Desarrolladores de soluciones digitales básicas | M72: A81165374 | N72: Desarrollo y comercialización de software de gestión empresarial | O72: https://www.siadv.com/# | P72: Desarrollo de aplicaciones de gestión empresarial; sin vertical sectorial; requiere validación por falta de web oficial. | Q72: Activa | S72: Madrid | AP72: No
A73: =+A72+1 -> 70 | B73: CONSULTORÍA Y COMUNICACIONES DE NAVARRA SL | D73: N | E73: 1.3 Contactado "muerto" | F73: Enviado 16/10 | G73: Carlota | H73: Miguel Angel Marti Melendo / Kike Mendoza (correo) /Virginia Montalbán (madrid) | I73: 948290202 | J73: comunicacion@cyc.es / kikem@cyc.es /virginiam@cyc.es (madrid) | K73: 948 29 02 02 | L73: B. Integradores TI generalistas | M73: B31549256 | N73: Servicios informáticos y comunicaciones, junto con operaciones relacionadas con el mercado inmobiliario | O73: Contacto - CYC | P73: Ofrecía servicios TI amplios (consultoría, comunicaciones); no presenta actividad reciente ni cierre registrado, por lo que requiere validación. | Q73: No Activa | R73: No_Cliente | S73: Navarra | T73: 31192 | U73: 3591903 | V73: 55 | W73: 3 | X73: 0.3297 | AG73: Administrador | AH73: Director Financiero | AI73: Consejero | AJ73: Consejero Delegado | AK73: Administrador | AL73: albertoa@cyc.es | AM73: info@cyc.es | AN73: jmanuel@cyc.es | AO73: jmanuelg@cyc.es | AP73: No
A74: =+A73+1 -> 71 | B74: INNOVATEC GALICIA SOLUCIONES DIGITALES (SERVICIOS DE INNOVACIÓN TECNOLÓGICA DE GALICIA SL) | E74: 1.0. Contacto fallido (sin descuelgue) | F74: 3-2 981 27 15 25 Fuera de horario de atencion. Llamar antes de las 16:00 . Llamada 3 veces y no pueden atender llamada | G74: Juan | I74: 981 27 15 25 | J74: soporte@innovatecgalicia.es | K74: 981 27 15 25 | L74: A. Informáticos | M74: B70101696 | N74: Contamos con un equipo de profesionales especializados y técnicos certificados en distintas tecnologías y ámbitos de la informática. | O74: Servicios Informáticos | Soporte y Servicios Infomáticos | Innovatec | Q74: Activa | S74: A Coruña | AP74: No
A75: =+A74+1 -> 72 | B75: GALITEC CONSULTORES INFORMATICOS SL | E75: 1.1 Contactado: propuesta "rechazada" | F75: 8-1 986 37 87 61 David me indica llamar Mañana por la mañana preguntar por Roberto o Miguel. Mandar correo tambien a galitec@galitecconsultores.com // 9-1 986 37 87 61 Contacto con Miguel y no estan interesados en la parte Telco, le entra una llamada y pide si se le puede llamar en otro momento. Hablar de soluciones digitales y Leadgen 30-01 986 37 87 61- Miguel comenta que no le interesa colaborar. | G75: Venta especialista | J75: galitec@galitecconsultores.com | K75: 986 37 87 61 | L75: C. Integradores TI sectoriales | M75: B36938397 | O75: Galitec Consumibles toner y cartuchos de tinta | Q75: Activa | S75: Vigo | AP75: No
A76: =+A75+1 -> 73 | B76: GLOBAL TECNOLOGIA INFORMATICA DE SERVICIOS INTEGRADOS SL | E76: 1.3 Contactado "muerto" | F76: Mail enviado 8.10. Esperando re-llamada CEO. | G76: Blanca | H76: Juan Carlos Reyes (CEO), jcreyes@globaltis.com | I76: 916 651 232 | J76: atencioncliente@globaltis.com | K76: 916 65 12 32 | L76: B. Integradores TI generalistas | M76: B83542357 | N76: Otros servicios relacionados con las tecnologías de la información y la informática | O76: Home Globaltis - Globaltis | Q76: Activa | S76: Madrid | T76: MADRID | V76: 2 | X76: jcreyes@globaltis.com | AP76: No
A77: =+A76+1 -> 74 | B77: R & J CONSULTORIA INTEGRAL DE SOFTWARE S.L. | E77: 2.3 Rechaza tras Sesión 1:1 | F77: Pendiente reagendar reunión (no presentado 16-oct) | G77: Carlota | I77: +34 91/6303005 | J77: gabriela.quintero@consultoria-integral.net | K77: 916 30 30 05 | L77: A. Informáticos | M77: B82228644 | N77: Actividades de consultoría informática | O77: https://www.consultoria-integral.net/ | P77: Consultora IT en Las Rozas que desarrolla e integra sistemas informáticos a medida, con servicios de software y posible seguridad y backup incluidos. | Q77: No Activa | S77: Madrid | T77: LAS ROZAS DE MADRID | V77: 8 | X77: jljerez@vianuwe.com | AP77: No
A78: =+A77+1 -> 75 | B78: ELKARMEDIA SL | C78: Y | D78: Y | E78: 1.3 Contactado "muerto" | F78: 23.09 | G78: Blanca | H78: Miguel Angel Arce Valle | I78: 943857150 | J78: info@elkarmedia.com | K78: 943 85 08 74 | L78: D. Desarrolladores de soluciones digitales básicas | M78: B20554911 | N78: Desarrollo de aplicaciones informáticas; formación; mantenimiento de sistemas | O78: www.elkarmedia.eus | P78: Web activa, dedicada a desarrollo de software y formación tecnológica. Multi-sector. Clasificada como desarrollador digital básico. | Q78: Activa | R78: No_Cliente | S78: Guipúzcoa | T78: 20720 | U78: 734440 | V78: 14 | W78: 1 | X78: 0.184 | Y78: 943080088 | Z78: 943025100 | AA78: 943850874 | AB78: 943025101 | AG78: Administrador | AH78: Director Financiero | AI78: Consejero | AJ78: Consejero Delegado | AK78: Administrador | AP78: No
A79: =+A78+1 -> 76 | B79: COMPUHELP | E79: 1.3 Contactado "muerto" | F79: 23.09 | G79: Blanca | H79: info@compuhelp.es - a la atención de Jorge Albeza | L79: A. Informáticos | M79: B82687013 | Q79: No Activa | AP79: No
A80: =+A79+1 -> 77 | B80: CIP Informática (CENTRO INFORMATICO POZUELO SL) | E80: 1.3 Contactado "muerto" | F80: 23.09 | G80: Blanca | H80: Mail a comercial@CIPinformatica.com y llamar por la mañana (10am) | I80: 91 351 36 77 | L80: A. Informáticos | M80: B81384414 | O80: Contacto - Centro Informático Pozuelo | Q80: Activa | AP80: No
A81: =+A80+1 -> 78 | B81: GHM Informática | E81: 1.3 Contactado "muerto" | F81: 23.09 | G81: Blanca | H81: Mail a info@ghminformatica.com y llamar por la mañana | I81: 916868042 | L81: A. Informáticos | M81: B86821865 | O81: Tienda de Informática en Leganés - GHM Informática | Q81: Activa | AP81: No
A82: =+A81+1 -> 79 | B82: INTEGRAL DATA SERVICES SL (PROXYMA) | C82: Y | D82: Y | E82: 1.3 Contactado "muerto" | F82: 45938 | G82: Carlota | H82: Juan Manuel | J82: info@proxyma.es | K82: 900 834 423 (gratuito) / 930 181 607 | L82: B. Integradores TI generalistas | M82: B60889748 | N82: Proxyma ofrece mantenimiento informático para empresas en Barcelona, incluyendo soporte correctivo, preventivo y evolutivo. Sus servicios abarcan estaciones de trabajo (Windows y Mac), servidores físicos/virtuales, redes, impresoras, comunicaciones y copias de seguridad. Además, realizan instalación de redes y cableado, venta de hardware/software y soporte remoto. | O82: PROXYMA | Empresa mantenimiento informático y redes Barcelona | P82: Cubre de forma integral las necesidades TI de pymes (workplace, redes, servidores, seguridad básica), sin especialización vertical. | Q82: Activa | S82: Barcelona | T82: 08012 | AP82: No
A83: =+A82+1 -> 80 | B83: Oter informatica SL | C83: Y | D83: Y | E83: 1.3 Contactado "muerto" | F83: 45938 | G83: Marta | H83: Alejandro Oter Muñoz | J83: oter@oterinformatica.com / comercial@oterinformatica.com | K83: 936551449 | L83: B. Integradores TI generalistas | M83: B63451736 | N83: Ofrece un servicio integral de mantenimiento informático y soporte TI para pymes, con modalidades de tarifa plana, pago por servicio o bonos. Sus servicios incluyen soporte remoto y presencial, monitorización 24/7, consultoría IT, migración a la nube, teletrabajo, seguridad informática e instalación de infraestructuras TI. También realizan venta de hardware y software. | O83: Suba sus servidores a la nube – Suba sus servidores a la nube | P83: Cubren de forma completa las necesidades TI de empresas (workplace, cloud, seguridad, comunicaciones, soporte), sin especialización vertical en un sector concreto | Q83: Activa | S83: Barcelona | T83: 08019 | AP83: No
A84: =+A83+1 -> 81 | B84: DEINFO SERVICIOS INFORMATICOS SL | C84: Y | D84: Y | E84: 1.3 Contactado "muerto" | F84: 45938 | G84: Marta | H84: Jose María Serra Cabrera | J84: deinfo@deinfo.es /administracion@deinfo.es | K84: 934 176 400 | L84: B. Integradores TI generalistas | M84: B59753278 | N84: Empresa fundada en 1988 en Barcelona, especializada en servicios integrales de TI: dirección y consultoría IT, mantenimiento de sistemas, soporte técnico remoto y presencial, ciberseguridad, teletrabajo y escritorios virtuales, cloud (Microsoft 365, Azure, Google Workspace), telefonía IP, instalaciones y equipamiento, desarrollo en entorno Odoo e incluso peritaje informático judicial. | O84: Servicios – DEINFO | P84: Su portfolio cubre todas las áreas básicas de TI para empresas (workplace, cloud, comunicaciones, seguridad, business apps), atendiendo a múltiples sectores sin especialización vertical. | Q84: Activa | S84: Barcelona | AP84: No
A85: =+A84+1 -> 82 | B85: GROUPmee | C85: Y | D85: Y | E85: 1.3 Contactado "muerto" | F85: 45938 | G85: Marta | H85: Alberto Ayuso | J85: hola@groupmee.com / alberto.garcia@groupme.com | K85: 930 409 993 / 630950573 | L85: B. Integradores TI generalistas | M85: B66962893 | N85: Nacida de la unión de INNOVAmee y SAPmee, ofrece un portfolio integral de servicios TI: mantenimiento informático para empresas, ciberseguridad, cloud, consultoría IT, así como soluciones de negocio con SAP, Asana, Holded, Pipedrive y Factorial. También es agente digitalizador del Kit Digital. | O85: Contacto – Groupmee | P85: Su oferta cubre todas las necesidades básicas y avanzadas de TI para pymes y medianas empresas (workplace, cloud, business apps, seguridad), en múltiples sectores, sin una especialización vertical única. | Q85: No Activa | S85: Barcelona | AP85: No
A86: =+A85+1 -> 83 | B86: Efimatica Assesorament Informatic SL | C86: Y | D86: Y | E86: 1.3 Contactado "muerto" | F86: 45938 | G86: Marta | J86: web@efimatica.com | K86: 972 411 600 | L86: C. Integradores TI sectoriales | M86: B172219455 | N86: Empresa con sede en Girona especializada en soluciones tecnológicas para el sector turístico y HORECA. Ofrece software de gestión hotelera (Obehotel), carta digital para restaurantes, servicios de ciberseguridad, infraestructura TI y soporte técnico. También es agente digitalizador del Kit Digital. | O86: Contactar - Efimatica | P86: Su oferta está claramente verticalizada en turismo y restauración, con productos tecnológicos estandarizados para ese sector. Por ello se clasifica como integrador TI sectorial. | Q86: No Activa | S86: Girona | AP86: No
A87: =+A86+1 -> 84 | B87: CIS Informatica SL | C87: Y | D87: Y | E87: 1.3 Contactado "muerto" | F87: 10/10/2025 (reminder) | G87: Susana | H87: José Félix Tezanos Tortajada | J87: cis@cisinformatica.cat | K87: 972 22 89 43 | L87: B. Integradores TI generalistas | M87: B127421927 | N87: Empresa ubicada en Girona especializada en servicios integrales de TI para pymes: soporte técnico y remoto, mantenimiento de sistemas, ciberseguridad (auditoría, firewall, antivirus, backup cloud), soluciones cloud, instalación de redes y comunicaciones (wifi, telefonía IP, fibra), cámaras de seguridad y desarrollo de páginas web y ERP sectoriales (comercio, hostelería, gestión de proyectos). También es agente digitalizador del Kit Digital. | O87: Contacte » CIS Informàtica | P87: Cubre todas las áreas esenciales de TI (workplace, cloud, ciberseguridad, business apps, comunicaciones), trabajando con empresas de distintos sectores, sin una verticalización única. | Q87: No Activa | S87: Girona | AP87: No
A88: =+A87+1 -> 85 | B88: OX-ONE NETWORKS SL | E88: 4.1 Activado: en proceso de firma | F88: 12.01 - Pendiente recibir confirmación contrato modificado y enviar a Raquel Muñoz. | G88: Carlota | H88: Gonzalo González (director de desarrollo de negocio) | I88: + 34 914855315 / +34 607110458 | J88: gonzalo.gonzalez@ox-one.com | K88: 911 115 838 | L88: B. Integradores TI generalistas | M88: B82904566 | N88: Otros servicios relacionados con las tecnologías de la información y la informática | O88: https://www.ox-one.com/que-hacemos | P88: Ox‑One Networks es una consultora tecnológica de Alcorcón especializada en redes, seguridad, cloud edge y monitorización, con servicios 24/7 y gestión de redes sociales para pymes. | Q88: Activa | S88: Madrid | T88: POZUELO DE ALARCON | V88: 4 | X88: info@ox-one.com | AP88: No
A89: =+A88+1 -> 86 | B89: ASISTENCIA TECNICA EN COMUNICACIONES SL | D89: Y | E89: 1.3 Contactado "muerto" | G89: Anna | H89: Ana Patricia Botin Sanz Sautuola O Shea | I89: 965 92 29 82 / 608 14 01 24 | J89: atc@atcinformatica.com | K89: 965 92 29 82 / 608 14 01 24 | L89: A. Informáticos | M89: B03784816 | N89: Comercio de equipos de oficina | O89: NO WEB | P89: Comercializa equipos de oficina/hardware, sin componente de software o digitalización, lo que la clasifica como informático tradicional. | Q89: Activa | R89: No_Cliente | S89: Araba | T89: 01322 | U89: 654690 | V89: 8 | W89: 2 | X89: 0.2433 | Y89: 965921636 | AC89: Matias Rodriguez Inciarte | AD89: Roberto Fernandez Diaz | AE89: Ignacio Berdugo Gomez Torre | AF89: Angel Gabilondo Pujol | AG89: Administrador | AH89: Director Financiero | AI89: Consejero | AJ89: Consejero Delegado | AK89: Administrador | AP89: No
A90: =+A89+1 -> 87 | B90: SEMIC | E90: 1.3 Contactado "muerto" | G90: Anna | L90: - | M90: A31016322 | Q90: Activa | AP90: No
A91: =+A90+1 -> 88 | B91: SEACOMM SOLUCIONES INTEGRALES DE TELECOMUNICACIONES SL | D91: Y | E91: 1.3 Contactado "muerto" | G91: Anna | I91: 911733880 | L91: B. Integradores TI generalistas | M91: B86811189 | N91: Servicios TI: Comunicaciones unificadas, Networking, Ciberseguridad, Infraestructura TIC, Wireless, Servicios y Mantenimiento, Audiovisuales, Edificación (seguridad/monitoreo) | O91: www.seacomm.es | P91: Ofrece comunicaciones unificadas, networking, ciberseguridad (auditoría, ISO27001, vulnerabilidades, SOC), infraestructura TIC (continuidad, recuperación), soporte 24/7 y audiovisuales con instalación; es multi-sector (no especializado verticalmente) y cubre un ciclo completo de servicios TI; encaja como Integrador TI generalista. | Q91: Activa | R91: No_Cliente | S91: Madrid | T91: 28023 | U91: 460336 | V91: 6 | W91: 1 | X91: 0.0373 | Y91: 678433022 | Z91: 600571845 | AP91: SI
A92: =+A91+1 -> 89 | B92: LOGISTICA INTEGRAL TENERIFE SL | D92: Y | E92: 1.3 Contactado "muerto" | G92: Anna | H92: Raul Rafael Portaencasa Galan | I92: 922102113 | L92: — (No aplica a TI) | M92: B38530705 | N92: Servicios de transporte y logística integral | O92: https://www.logisticatenerife.com | P92: Empresa de logística, no encaja en arquetipos TI; sigue activa con web corporativa. | Q92: No Activa | R92: No_Cliente | S92: Santa Cruz de Tenerife | T92: 38600 | U92: 389953 | V92: 1 | W92: 2 | X92: 0.2832 | Y92: 922394415 | AC92: Raul Portaencasa Galan | AD92: Enrique Molina | AG92: Administrador | AH92: Director Financiero | AI92: Consejero | AJ92: Consejero Delegado | AK92: Administrador | AP92: No
A93: =+A92+1 -> 90 | B93: NIVEL IV SERVICIOS INFORMATICOS GALLEGOS SL | D93: Y | E93: 1.3 Contactado "muerto" | G93: Anna | L93: A. Informáticos | M93: B36294368 | N93: Servicios informáticos, soporte técnico y consultoría TI | O93: https://www.niveliv.es | P93: Servicios TI básicos y soporte técnico; multi-sector; encaja con Informáticos. | Q93: No Activa | AP93: No
A94: =+A93+1 -> 91 | B94: DISTRITO K SL | D94: Y | E94: 1.3 Contactado "muerto" | G94: Anna | H94: Aktiengesellschaft Heyde | I94: 981235313 | J94: distritok@distritok.com | L94: D. Desarrolladores de soluciones digitales básicas | M94: B82270474 | N94: Distribución de software musical, consultoría y soluciones digitales | O94: https://www.distritok.com | P94: Soluciones digitales y distribución de software en sector cultural; multisector. | Q94: Activa | R94: No_Cliente | S94: A Coruña | T94: 15005 | U94: 3211075 | V94: 30 | W94: 1 | X94: 0.2817 | Y94: 981168070 | AG94: Administrador | AH94: Director Financiero | AI94: Consejero | AJ94: Consejero Delegado | AK94: Administrador | AP94: No
A95: =+A94+1 -> 92 | B95: NETDIFFUSION SL | D95: Y | E95: 1.3 Contactado "muerto" | G95: Anna | H95: Alvaro Nicolas Sanchez Garcia Viedma | I95: 932805333 | L95: D. Desarrolladores de soluciones digitales básicas | M95: B64603565 | N95: Desarrollo web, marketing digital y comunicación online | O95: https://www.netdiffusion.net/ | P95: Ofrece servicios digitales (web, marketing, SEO/SEM); multisector; encaja en desarrolladores digitales básicos. | Q95: Activa | R95: No_Cliente | S95: Barcelona | T95: 08028 | U95: 1020113 | V95: 7 | W95: 2 | X95: 0.2806 | Y95: 630963290 | AC95: Juan Carlos Sanchez Peiro | AG95: Administrador | AH95: Director Financiero | AI95: Consejero | AJ95: Consejero Delegado | AK95: Administrador | AP95: No
A96: =+A95+1 -> 93 | B96: SOFT FUTUR SOFTWARE FACTORY SL | D96: Y | E96: 1.3 Contactado "muerto" | G96: Anna | H96: Pascal Moraux | L96: D. Desarrolladores de soluciones digitales básicas | M96: B25350515 | N96: Desarrollo de software de gestión empresarial y apps | O96: https://soft-futur.com/ | P96: Desarrollo de software de gestión y soluciones digitales; multisector; encaja en desarrolladores. | Q96: No Activa | R96: No_Cliente | S96: Córdoba | T96: 14940 | U96: 1058734 | V96: 1 | W96: 1 | X96: 0.2795 | AC96: Jose Matias Azuara Garcia | AD96: Marie Bernadette Fistarol Claire | AE96: Olivier Jolland | AF96: Tessi | AG96: Administrador | AH96: Director Financiero | AI96: Consejero | AJ96: Consejero Delegado | AK96: Administrador | AP96: No
A97: =+A96+1 -> 94 | B97: NAUDIT HIGH PERFORMANCE COMPUTING AND NETWORKING INGENIERIA SL | D97: Y | E97: 1.3 Contactado "muerto" | G97: Anna | H97: Jane Bisset Nicola | I97: 918960075 | L97: E. Consultoras innovación digital | M97: B85196439 | N97: Auditoría de redes, calidad de servicio, ciberseguridad y HPC | O97: https://www.naudit.es | P97: Especializada en redes, big data, análisis de rendimiento y ciberseguridad avanzada; encaja como consultora de innovación digital. | Q97: No Activa | R97: No_Cliente | S97: Madrid | T97: 28049 | U97: 436819 | V97: 1 | W97: 1 | X97: 0.2599 | AC97: Jaime Aperador Garza | AG97: Administrador | AH97: Director Financiero | AI97: Consejero | AJ97: Consejero Delegado | AK97: Administrador | AP97: No
A98: =+A97+1 -> 95 | B98: D.F. SISTEMES SL | D98: Y | E98: 1.3 Contactado "muerto" | G98: Anna | H98: Beatriz Gurruchaga Sanchez | I98: 971861072 | J98: sistemas@dfsistemes.es | L98: C. Integradores TI sectoriales | M98: B07696719 | N98: Desarrollo de software, venta y mantenimiento de hardware, soluciones sectoriales | O98: www.dfsistemes.es | P98: Ofrece software, mantenimiento y hardware con soluciones sectoriales como ERP para retail y agro. Evidencia clara de verticalización sectorial. Se clasifica como integrador TI sectorial. | Q98: Activa | R98: No_Cliente | S98: Illes Balears | T98: 07440 | U98: 464703 | V98: 7 | W98: 2 | X98: 0.249 | Y98: 971860524 | Z98: 971860317 | AC98: Javier Polidura Arruga | AG98: Administrador | AH98: Director Financiero | AI98: Consejero | AJ98: Consejero Delegado | AK98: Administrador | AL98: comercial@dfsistemes.es | AM98: suport@dfsistemes.es | AN98: programacion@dfsistemes.es | AP98: No
A99: =+A98+1 -> 96 | B99: QUOPIAM INFORMÁTICA SL | D99: Y | E99: 1.3 Contactado "muerto" | G99: Anna | H99: Thomas Briffett Duncan | I99: 938513954 | J99: info@quopiam.com | L99: B. Integradores TI generalistas | M99: B64510480 | N99: Software, mantenimiento, redes, asesoramiento informático | O99: www.quopiam.com | P99: Presta servicios de software, creación web, mantenimiento y redes, cubriendo TI completos. No se observa especialización sectorial. Se clasifica como integrador TI generalista. | Q99: Activa | R99: No_Cliente | S99: Barcelona | T99: 08560 | U99: 2140082 | V99: 11 | W99: 2 | X99: 0.2459 | Y99: 661931027 | Z99: 661358948 | AA99: 664359611 | AB99: 650090429 | AG99: Administrador | AH99: Director Financiero | AI99: Consejero | AJ99: Consejero Delegado | AK99: Administrador | AP99: No
A100: =+A99+1 -> 97 | B100: PERI COMPUTER SYSTEMS SL | D100: Y | E100: 1.3 Contactado "muerto" | G100: Anna | H100: Evangelina Martinez Alfaro | I100: 932656083 | J100: info@atmbcn.com | L100: A. Informáticos | M100: B63485841 | N100: Instalación, reparación y mantenimiento de equipos informáticos y tratamiento de datos | O100: https://pericomputer.com/ | P100: Actividad basada en instalación, reparación y mantenimiento de equipos informáticos, junto a servicios de tratamiento de datos. Es multi-sector y encaja en informáticos tradicionales. | Q100: Activa | R100: Cliente_JZ | S100: Barcelona | T100: 08026 | U100: 389829 | V100: 4 | W100: 1 | X100: 0.2382 | Y100: 931256890 | Z100: 606540635 | AA100: 606540051 | AC100: Marta De Teresa Pertusa | AD100: Laura Molina | AE100: Expal Systems | AG100: Administrador | AH100: Director Financiero | AI100: Consejero | AJ100: Consejero Delegado | AK100: Administrador | AP100: No
...

Sheet Plan de Visitas Integradores
A1: MASORANGE | BASE DE INTEGRADORES + PLAN DE VISITAS
A2: Objetivo: localizar integradores, agruparlos por ubicación y proponer una secuencia de visitas eficiente para generar confianza comercial con el menor coste de desplazamiento.
A4: BASE DE INTEGRADORES
A5: Zona de visita | B5: Empresa | C5: Estado del integrador | D5: Ciudad / pueblo | E5: Provincia | F5: Dirección exacta | G5: Cluster geográfico | H5: Formato recomendado | I5: Prioridad | J5: Nota estratégica
A6: Madrid y alrededores | B6: Binfor Solutions | D6: Alcorcón | E6: Madrid | F6: C/ Sapporo, 2, local | G6: Madrid Sur | H6: Presencial prioritario | I6: A | J6: Añade densidad en el cinturón sur de Madrid.
A7: Madrid y alrededores | B7: Brain Hardware, S.L. | D7: Fuenlabrada | E7: Madrid | F7: Plaza de Melendra, 2 | G7: Madrid Sur | H7: Presencial prioritario | I7: A | J7: La web comercial ubica la oficina en Plaza de Melendra; directorio mercantil refleja otra dirección histórica.
A8: Madrid y alrededores | B8: Next Mobility | D8: Las Rozas de Madrid | E8: Madrid | F8: C/ Comunidad de Madrid, 41, local 110 | G8: Madrid Oeste | H8: Presencial prioritario | I8: A | J8: Completa una jornada muy densa junto a Pozuelo.
A9: Madrid y alrededores | B9: Deiteco | D9: Fuenlabrada | E9: Madrid | F9: C/ de Hontanar, 6 | G9: Madrid Sur | H9: Presencial prioritario | I9: A | J9: Muy eficiente visitarlo junto a Brain Hardware y Binfor en cinturón sur.
A10: Madrid y alrededores | B10: Covernet | D10: Pozuelo de Alarcón | E10: Madrid | F10: C/ Vía de las Dos Castillas, 23, Chalet 19 | G10: Madrid Oeste | H10: Presencial prioritario | I10: A | J10: Se puede agrupar con OX-ONE y Next Mobility en un mismo día.
A11: Madrid y alrededores | B11: OX-ONE NETWORKS SL | D11: Pozuelo de Alarcón | E11: Madrid | F11: C/ Mimosas, 15 | G11: Madrid Oeste | H11: Presencial prioritario | I11: A | J11: Muy rentable en la misma jornada que Covernet.
A12: Madrid y alrededores | B12: Cobitratel | D12: Azuqueca de Henares | E12: Guadalajara | F12: C/ La Victoria, 4 | G12: Corredor del Henares | H12: Híbrido | I12: C | J12: Empresa con varias sucursales; para ruta se prioriza Azuqueca por cercanía al corredor Madrid-Henares.
A13: Madrid y alrededores | B13: NaimiTech, S.L. | D13: Illescas | E13: Toledo | F13: Illescas, Toledo (sin calle detallada en aviso legal) | G13: Toledo / Madrid Sur | H13: Híbrido | I13: C | J13: Buen candidato de extensión de la ruta Madrid Sur si confirma interés.
A14: Cataluña | B14: Lisot | D14: Barcelona | E14: Barcelona | F14: C/ Casp, 118 | G14: Cataluña / Barcelona | H14: Presencial prioritario | I14: A | J14: Refuerza la lógica de hacer una jornada de Barcelona capital.
A15: Cataluña | B15: Ocvistas | D15: Barcelona | E15: Barcelona | F15: Av. de Roma, 155, P. Plta. Pta. 1 | G15: Cataluña / Barcelona | H15: Presencial prioritario | I15: A | J15: Suma densidad en Barcelona capital junto a Lisot.
A16: Cataluña | B16: Maxen | D16: Cabrera de Mar | E16: Barcelona | F16: C/ Sant Joan 35A, soterrani | G16: Cataluña / Barcelona | H16: Presencial en ruta | I16: B | J16: Encaja en ruta Barcelona-Tarragona; combinar con Barcelona ciudad y Tarragona.
A17: Cataluña | B17: Elpis Informática, S.L. | D17: Tarragona | E17: Tarragona | F17: C/ del Ferro, parcela 61, nave 22 | G17: Cataluña / Tarragona | H17: Presencial en ruta | I17: B | J17: Buen cierre de la ruta de Cataluña antes de volver a Barcelona.
... A33: Comunidad Valenciana | B33: Dataqu | D33: Valencia | E33: Valencia | F33: Valencia, España (sin calle pública visible) | G33: Levante | H33: Híbrido | I33: C | J33: La web actual sitúa la sede en Valencia; una fuente anterior apuntaba Valladolid. Validar antes de agendar.
B34: Sisytec | D34: Espinardo (Murcia) | E34: Murcia | F34: C/ Central, 10, 7ª planta | G34: Murcia | H34: Remoto primero | I34: C | J34: Se usa la oficina comercial de Espinardo; datos mercantiles antiguos apuntan a Librilla.
A35: Aragón / Meseta Norte | B35: Audinfor | D35: Zaragoza | E35: Zaragoza | F35: C/ Marcelino Álvarez, 84 | G35: Aragón | H35: Presencial en ruta | I35: B | J35: Tomada la oficina de Zaragoza como HQ; también tienen oficina en Madrid.
A36: Aragón / Meseta Norte | B36: Digital Hand Made, S.L. | D36: Zaragoza | E36: Zaragoza | F36: C/ Acacias, 9, local | G36: Aragón | H36: Presencial en ruta | I36: B | J36: Muy eficiente si se programa en el mismo bloque que Audinfor.
A37: Aragón / Meseta Norte | B37: Mariskalnet Informática | D37: Medina del Campo | E37: Valladolid | F37: C/ Ribera del Zapardiel, 16 | G37: Castilla y León | H37: Híbrido | I37: C | J37: Encaja como parada táctica si se activa ruta Zaragoza-Meseta Norte.
A38: Extremadura | B38: GNUO Consultores | D38: Badajoz | E38: Badajoz | F38: PCTEX, Av. Investigación s/n, despacho B24 | G38: Extremadura | H38: Remoto primero | I38: C | J38: Presencial solo si responde al primer contacto; geográficamente aislado para una ruta inicial.
A39: Extremadura | B39: Micro Sip | D39: Navalmoral de la Mata | E39: Cáceres | F39: C/ Gabriel y Galán, 2 | G39: Extremadura Norte | H39: Remoto primero | I39: C | J39: Usar la dirección comercial/tienda; el domicilio social publicado en registros es distinto.
A42: PLAN ESTRATÉGICO DE VISITAS | secuencia recomendada
A43: Bloque | B43: Territorio | C43: Nº empresas | D43: Ciudades clave | E43: Secuencia propuesta | F43: Días sugeridos | G43: Formato dominante | H43: Objetivo comercial
A44: Onda 1 | B44: Madrid y corredor | C44: 8 | D44: Las Rozas, Pozuelo, Alcorcón, Fuenlabrada, Illescas, Azuqueca | E44: Día 1: Las Rozas + Pozuelo. Día 2: Alcorcón + Fuenlabrada. Día 3 opcional: Illescas + Azuqueca si hay interés. | F44: 2-3 días | G44: Presencial prioritario | H44: Abrir pipeline con el máximo ROI comercial y mínimo desplazamiento.
A45: Onda 2 | B45: Cataluña | C45: =COUNTIF($A$6:$A$39,"Cataluña") -> 5 | D45: Barcelona, Cabrera de Mar, Cervelló, Tarragona | E45: Día 1: Barcelona capital. Día 2: Cabrera de Mar / Cervelló + Tarragona. | F45: 1,5-2 días | G45: Mixto presencial | H45: Consolidar confianza en un hub tecnológico con varias cuentas cercanas.
A46: Onda 3 | B46: Andalucía | C46: =COUNTIF($A$6:$A$39,"Andalucía") -> 5 | D46: Sevilla, Puerto de Santa María, Málaga, Mijas, Puente Genil | E46: Día 1: Sevilla + Cádiz. Día 2: Málaga + Mijas. Fedesoft solo si encaja agenda o se confirma tracción previa. | F46: 2-3 días | G46: Presencial en ruta | H46: Dar cobertura regional sin abrir demasiados días fuera.
A47: Onda 4 | B47: Norte | C47: =COUNTIF($A$6:$A$39,"Norte") -> 5 | D47: Gijón, Santander, Bilbao, Donostia | E47: Ruta lineal: Gijón -> Santander -> Bilbao -> Donostia. | F47: 2-3 días | G47: Mixto | H47: Cubrir corredor cantábrico con buena narrativa de cercanía.
A48: Onda 4B | B48: Galicia | C48: =COUNTIF($A$6:$A$39,"Galicia") -> 2 | D48: Santiago de Compostela, Pontevedra | E48: Jornada compacta Santiago + Pontevedra, idealmente en viaje dedicado o ligado a otra acción comercial en la zona. | F48: 1 día | G48: Presencial en ruta | H48: Dar masa crítica a Galicia sin sobredimensionar el viaje.
A49: Onda 5 | B49: Comunidad Valenciana | C49: 2 | D49: Alicante, Sant Joan dAlacant, Valencia, Murcia | E49: Día 1: Alicante + Sant Joan dAlacant. Día 2 opcional: Valencia / Murcia solo si validan interés y dirección. | F49: 1,5-2 días | G49: Híbrido | H49: Priorizar Alicante y dejar Valencia/Murcia condicionados a validación previa.
A50: Onda 6 | B50: Aragón / Meseta Norte | C50: =COUNTIF($A$6:$A$39,"Aragón / Meseta Norte") -> 3 | D50: Zaragoza, Medina del Campo | E50: Jornada principal en Zaragoza. Medina del Campo como extensión táctica solo si aparece oportunidad real. | F50: 1-1,5 días | G50: Mixto | H50: Capturar oportunidades puntuales sin romper la lógica de eficiencia.
A51: Backlog | B51: Extremadura | C51: =COUNTIF($A$6:$A$39,"Extremadura") -> 2 | D51: Badajoz, Navalmoral de la Mata | E51: Primero email + llamada + videollamada. Visita física solo si existe oportunidad avanzada. | F51: Remoto primero | G51: Remoto primero | H51: Evitar coste comercial alto en zonas aisladas.
A53: LISTA DE INTEGRADORES: PENDIENTE AGENDAR REUNIÓN CON NEGOCIO (POTENCIALES A ANALIZAR)
A54: Integrador | B54: Comentario
A55: NaimiTech, S.L.
A56: Ache Enseñanza e Informática SLL
A57: Omnia Soluciones
A58: Sur Computers, S.L.
A59: Fi-4 Open Source, S.L. (Amiritmo)
A60: Digital Hand Made, S.L.
A61: LISOT, S.L.
A62: INNOVA TELECOM, S.L. (ITSOFT)

Sheet Estado Contratos
H2: Parte I | L2: Parte II | O2: Parte III
B3: Integrador | C3: NIF | D3: Stakeholder | E3: Datos contacto | F3: Teléfono | G3: Localización | H3: Revisión contrato | I3: Declaración responsable | J3: Envío a legal | K3: DocuSign | L3: CIF | M3: Razón Social | N3: Datos bancarios | O3: Requisitos SFID | P3: Creación SFID | Q3: Comentarios
B4: Responsable | H4: Integrador | I4: Integrador | J4: Raquel Muñoz | K4: Legal MOG | L4: Integrador | M4: Integrador | N4: Integrador | O4: Integrador
B5: Cover Net | C5: B82483280 | D5: Marta Florez /Felipe | E5: marta@covernet.net / comercial@coverspi.com | H5: Recibido | I5: Recibido | J5: Recibido | K5: Recibido | L5: Recibido | M5: Recibido | N5: Recibido | O5: Recibido | P5: Recibido
B6: Land M | D6: Lucas | E6: lucas@landm.net | F6: 699056779 | H6: Pendiente | I6: Pendiente | J6: Pendiente | K6: Pendiente | L6: Pendiente | M6: Pendiente | N6: Pendiente | O6: Pendiente | P6: Pendiente | Q6: Llamada 20/10
B7: Deiteco | C7: B42760140 | D7: Úrsula y Jorge | E7: info@deiteco.com | H7: Recibido | I7: Recibido | J7: Pendiente | K7: Pendiente | L7: Recibido | M7: Recibido | N7: Recibido | O7: Pendiente | P7: Pendiente
B8: Monkinet | D8: José María | E8: jose@monkinet.io | H8: Pendiente | I8: Pendiente | J8: Pendiente | K8: Pendiente | L8: Pendiente | M8: Pendiente | N8: Pendiente | O8: Pendiente | P8: Pendiente | Q8: Llamada 20/10
B9: Maxen | C9: B6389475 | D9: Miquel Xena / Rubén Escandell | E9: mxena@maxen.es / rescandell@maxen.es | G9: Barcelona | H9: Recibido | I9: Recibido | J9: Recibido | K9: Recibido | L9: Recibido | M9: Recibido | N9: Recibido | O9: Recibido | P9: Recibido
B10: Paperlabs | C10: B70576863 | D10: Carlos Borja Ortiz | H10: Pendiente | I10: Pendiente | J10: Pendiente | K10: Pendiente | L10: Pendiente | M10: Pendiente | N10: Pendiente | O10: Pendiente | P10: Pendiente | Q10: Retraso en envío de documentación 12/2025
B11: Duo IT | D11: Luis Ángel | H11: Pendiente | I11: Recibido | J11: Pendiente | K11: Pendiente | L11: Pendiente | M11: Pendiente | N11: Pendiente | O11: Pendiente | P11: Pendiente
B12: Dataqu | Q12: LeadGen
B13: Octivitas | Q13: LeadGen

Sheet Leads Grupo Apromar
B3: Grupo Apromar
B5: Empresa | C5: CIF | D5: Empleados | E5: Facturación (mil EUR) | F5: Localización | G5: Qué hacen | H5: Web | I5: Qué ofrece Apromar | J5: Beneficio potencial de MasOrange
B6: Acuicultura del Delta SL | C6: B67507673 | D6: 40 | E6: 11120 | F6: Tarragona | G6: Piscifactoría dedicada a la cría y comercialización de dorada y lubina, con enfoque en producción responsable y sostenible en costa mediterránea. | H6: https://acuidelta.com/ | I6: Acceso a inteligencia sectorial, informes de mercado y apoyo en iniciativas de sostenibilidad y competitividad para productores de dorada y lubina. | J6: IoT para monitorización de parámetros productivos, conectividad robusta entre instalaciones, cloud para análisis de datos y ciberseguridad para continuidad operativa.
B7: Acuipalma SL | C7: B38707600 | D7: 65 | E7: 19888 | F7: Santa Cruz de Tenerife | G7: Empresa de acuicultura en Canarias centrada en dorada y lubina, con instalaciones de preengorde de juveniles y planta de envasado asociada a su operación. | I7: Representación sectorial y acceso a información e innovación aplicable a producción acuícola en entorno insular. | J7: Conectividad estable multi-sede, ciberseguridad y digitalización de puestos de trabajo mediante servicios gestionados.
B8: Alevines de Guardamar SL | C8: B53341160 | D8: 7 | E8: 382 | F8: Alicante | G8: Operador especializado en fase de alevinaje y preengorde de dorada y lubina, con diversificación hacia corvina y seriola. | I8: Innovación aplicada en fases tempranas de producción (alevines/preengorde) y acceso a conocimiento sectorial. | J8: Sensórica IoT para control de agua y parámetros críticos, cloud para trazabilidad y ciberseguridad para protección de sistemas.
B9: Alicante Aquaculture | C9: B42508854 | D9: 1 | E9: 45 | F9: Alicante | G9: Proyecto enfocado en la producción de Seriola dumerili (pez limón), con modelo de producción en tierra y orientación sostenible. | H9: https://alicanteaquaculture.com | I9: Visibilidad sectorial y acceso a innovación y contexto de mercado para especies en expansión. | J9: Digitalización integral con IoT industrial, cloud y ciberseguridad para estandarizar y escalar operación.
B10: Aquanaria SL | C10: B35236355 | D10: 130 | E10: 30038 | F10: Las Palmas | G10: Productor de lubina orientado a alta gastronomía, con posicionamiento internacional y comunicación centrada en calidad diferenciada. | H10: https://www.aquanaria.com/ | I10: Información sectorial y posicionamiento dentro del entorno productor para reforzar reputación y competitividad. | J10: Ciberseguridad avanzada, modern workplace y posibles herramientas digitales para gestión comercial y exportación.
B11: Avramar SL | C11: B12741278 | E11: 79274 | F11: Valencia | G11: Productor mediterráneo integrado con oferta de lubina, dorada, corvina y pargo rosado, con control de trazabilidad en su cadena productiva. | H11: https://avramar.eu/ | I11: Acceso a innovación sectorial e inteligencia de mercado relevante para operación multi-especie e integrada. | J11: Conectividad multi-site, cloud para consolidación de datos productivos, IoT operativo y servicios de ciberseguridad gestionados.
B12: Caladeros del Mediterráneo | C12: B30704332 | D12: 107 | E12: 47721 | F12: Murcia | G12: Grupo vinculado al atún rojo fresco y ultracongelado, con énfasis en trazabilidad y técnicas de manipulación específicas. | H12: https://ricardofuentes.com/ | I12: Representación sectorial y acceso a información estratégica en una cadena con alta exigencia de trazabilidad y mercado internacional. | J12: Soluciones de conectividad segura, cloud para trazabilidad y protección de cadena comercial mediante ciberseguridad.
B13: Caviar Pirinea SL | C13: B22386841 | D13: 27 | E13: 28132 | F13: Navarra | G13: Productor y comercializador de esturión y trucha, especializado en caviar y productos transformados (ahumados, huevas, conservas). | H13: https://caviarpirinea.com/ | I13: Innovación sectorial y visibilidad dentro del ecosistema acuícola para productos premium de alto valor. | J13: Ciberseguridad para protección de negocio premium, cloud y herramientas digitales para canal B2B y B2C.
B14: Cooke (Grupo) | C14: A30106264 | D14: 278 | E14: 212084 | F14: Murcia | G14: Productor de lubina, dorada y corvina bajo modelo de acuicultura responsable e integración vertical de la cadena. | H14: https://www.cookeespana.com/ | I14: Información sectorial e innovación aplicable a producción integrada multi-especie. | J14: IoT, cloud, ciberseguridad y workplace a escala para operación multi-centro con soporte gestionado.
B15: Cultivos Piscícolas Marinos SA | C15: A07086879 | D15: 44 | E15: 3536 | F15: Cádiz | G15: Empresa con hatchery propio que cultiva, cría y engorda lenguado, comunicando procesos controlados con agua de mar filtrada. | H15: https://solee-gourmet.com/ | I15: Innovación y conocimiento sectorial aplicable a especies técnicas con procesos productivos complejos. | J15: Monitorización IoT, conectividad robusta, cloud productivo y seguridad para entornos técnicos complejos.
B16: Eurotrucha SL | C16: B4201539 | D16: 19 | E16: 3709 | F16: Madrid | G16: Operador de acuicultura de agua dulce centrado en desarrollo de alevines y trucha preengordada. | H16: https://piszolla.com/eurotrucha/ | I16: Acceso a innovación y buenas prácticas sectoriales en acuicultura de agua dulce. | J16: IoT en entornos de agua dulce, conectividad en zonas remotas y ciberseguridad gestionada.
B17: Futuna Blue España SL | C17: B72084254 | D17: 24 | E17: 1382 | F17: Cádiz | G17: Proyecto acuícola centrado en Seriola dumerili, desarrollando fases tempranas de producción con enfoque sostenible. | H17: https://futunablue.com/ | I17: Apoyo en innovación y contexto sectorial para proyectos de escalado en especies emergentes. | J17: Infraestructura digital integral con IoT, cloud y ciberseguridad para proyectos en crecimiento.
B18: Geremar SL | C18: B81247512 | D18: 35 | E18: 12834 | F18: Las Palmas | G18: Empresa comercializadora vinculada a productoras de dorada y lubina en Canarias, coordinando la venta de la producción del grupo. | H18: https://geremar.com/ | I18: Información sectorial y representación que refuerza posicionamiento comercial y coordinación productiva. | J18: Modern workplace, conectividad corporativa y ciberseguridad gestionada para coordinación comercial.
B19: Insuiña (Nueva Pescanova) | C19: B36021954 | D19: 160 | E19: 29438 | F19: Pontevedra | G19: Operación de acuicultura de rodaballo con hatchery propio y centros de engorde integrados dentro de grupo empresarial. | H19: https://www.nuevapescanova.com/ | I19: Innovación aplicada e inteligencia sectorial útil para producción integrada de especies de alto valor. | J19: Conectividad multi-centro, cloud productivo, IoT y ciberseguridad integrada en entorno industrial.
B20: Mundova SLU | C20: B02603108 | D20: 1 | E20: 121 | F20: Albacete | G20: Piscifactoría de trucha en agua dulce con modelo de cultivo integral que incluye ova embrionada, alevines y trucha comercial, con comunicación de trazabilidad y sanidad. | H20: https://www.mundova.com/ | I20: Innovación y conocimiento sectorial para mejorar eficiencia, sostenibilidad y posicionamiento en acuicultura de agua dulce. | J20: IoT para control de agua y energía, conectividad estable y ciberseguridad para garantizar continuidad operativa.
B21: Ocean Aquaculture Global | C21: B44736262 | D21: 1 | E21: 143 | F21: Madrid | G21: Desarrolla proyectos de acuicultura offshore (“far offshore, deep water”) para producir pescado de forma sostenible en el sur de España; comunica la creación de granjas marinas en alta mar y misión de producción sostenible. | H21: https://oceanaquaculture.blue/ | I21: Acceso a red sectorial e innovación/benchmarking muy útil para proyectos nuevos y escalado (especies emergentes), además de inteligencia sectorial y posicionamiento dentro de la acuicultura española. | J21: Conectividad y ciberseguridad para operación distribuida, IoT para monitorización y cloud para consolidación de datos; integradores pueden desplegar y operar red+seguridad+plataforma de datos como servicio.
B22: Ovapiscis SA | C22: A27192772 | D22: 38 | E22: 9445 | F22: Lugo | G22: Produce huevos embrionados de trucha arco iris a gran escala; indica fotoperiodos controlados para producir huevos todo-hembras durante todo el año y disponibilidad semanal. | H22: https://www.ovapiscis.com/ | I22: Innovación y buenas prácticas sectoriales para optimizar reproducción/calidad sanitaria y continuidad productiva; además de contexto de mercado y visibilidad en el ecosistema acuícola. | J22: IoT (control de incubación/agua), cloud para trazabilidad de lotes y reporting, y ciberseguridad para continuidad; integradores: sensórica+red+seguridad gestionada.
B23: Perla de Sarrión SL | C23: B44258382 | D23: 15 | E23: 2604 | F23: Teruel | G23: Opera una piscifactoría de esturión y vende online esturión, caviar y otros productos; la web identifica la piscifactoría cerca de Sarrión (Teruel) y comercializa productos premium con entrega internacional. | H23: https://esturion.store/ | I23: Visibilidad y posicionamiento sectorial para producto premium, acceso a información/estándares del sector y oportunidades de innovación en procesos y sostenibilidad. | J23: Ciberseguridad para negocio premium (protección de eCommerce y pagos), cloud/workplace y herramientas digitales para canal B2C/B2B; integradores: tienda/seguridad/operación gestionada.
... B25: Piscifactorías Albaladejo SL | C25: B73111205 | D25: 40 | E25: 10167 | F25: Murcia | G25: Marca/empresa del entorno “Pescados Albaladejo”: comunica actividad histórica de comercialización de pescado (venta mayorista/detalle) y, en su división/área de acuicultura marina, declara dedicarse al engorde de atún rojo. | H25: https://somospescadosalbaladejo.com/ | I25: Acceso a información sectorial y posicionamiento dentro del ecosistema productor; soporte para competitividad y sostenibilidad y entorno de innovación aplicable a acuicultura/comercialización. | J25: Conectividad para sedes/centros, ciberseguridad, workplace; si hay operación de engorde (acuicultura), IoT para control/monitorización y cloud para datos; integradores: paquete completo con soporte recurrente.
B26: Piscifactorías Hermanos Fariña SL | C26: B15249261 | D26: 6 | E26: 512 | F26: A Coruña | G26: Explotación de piscicultura en aguas continentales (acuicultura de agua dulce) según fuentes empresariales; no se ha localizado web oficial pública propia con detalle operativo. | I26: Acceso a conocimiento sectorial e innovación para eficiencia y sostenibilidad en acuicultura; y representación/visibilidad como productor. | J26: Conectividad estable en ubicaciones rurales, IoT para parámetros de agua/energía y ciberseguridad; integradores: despliegue y mantenimiento de sensórica+conectividad+seguridad.
B27: Piscifactorías del Mediterráneo SL | C27: B30827224 | D27: 40 | E27: 20001 | F27: Murcia | G27: Empresa dedicada a la acuicultura del atún rojo en Cartagena (según descripción pública corporativa) y vinculada a web corporativa de grupo; se encuadra en actividades de acuicultura/transformación/comercialización. | H27: https://ricardofuentes.com/ | I27: Entorno sectorial y visibilidad para una actividad altamente regulada y orientada a mercado; acceso a información e iniciativas sectoriales. | J27: Conectividad robusta, ciberseguridad y cloud para trazabilidad/operación; integradores: proyectos “llave en mano” con operación y seguridad gestionada.
B28: Piscifactoría Las Fuentes SL | C28: B18019604 | F28: Granada | G28: Criadero de trucha común y actividad de piscifactoría; además ofrece área natural/recreativa y actividades de “pesca familiar”, y comunica cooperación en repoblaciones de trucha autóctona. | H28: https://piscifactorialasfuentes.es/ | I28: Innovación y conocimiento sectorial aplicable a agua dulce (mejora de procesos y sostenibilidad), además de visibilidad y contexto del mercado acuícola. | J28: Conectividad, IoT para control de agua, cloud para trazabilidad y ciberseguridad; integradores: paquete “monitorización + seguridad + comunicaciones” para operación y experiencia visitante.
B29: Piscilor SA | C29: A27012475 | D29: 10 | E29: 1065 | F29: Lugo | G29: Gestión de viveros y criaderos de trucha arco iris (acuicultura de agua dulce) según fuentes empresariales; se describe como criadero/producción de trucha. | I29: Acceso a innovación y buenas prácticas para acuicultura continental (trucha), además de información sectorial y visibilidad. | J29: IoT (agua/oxigenación/energía), conectividad y ciberseguridad; integradores: gestión remota y mantenimiento preventivo con servicios gestionados.
B30: Piszolla SL | C30: B19029271 | D30: 132 | E30: 26.819 | F30: Guadalajara | G30: Cultivo, producción y comercialización de trucha arco iris; comunica más de 30 años de experiencia y operación de múltiples piscifactorías controlando el proceso completo para garantizar frescura, trazabilidad y calidad. | H30: https://piszolla.com/ | I30: Innovación y benchmarking en acuicultura continental (trucha) para reforzar calidad, trazabilidad y competitividad, además de visibilidad sectorial. | J30: IoT + cloud + ciberseguridad y workplace para estandarizar operación multi-granja; integradores: modernización de puestos + seguridad + conectividad y soporte.
B31: Profand Piscifactorías de Galicia SL | C31: B36779684 | D31: 25 | E31: 3275 | F31: Pontevedra | G31: Unidad vinculada al grupo Profand; comunica pertenencia a una multinacional de productos del mar y, en documentación pública del propio grupo, aparece como beneficiaria de modernización de piscifactoría con sistema de recirculación. | H31: https://profand.com/ | I31: Acceso al ecosistema sectorial, visibilidad y contexto de innovación/competitividad aplicable a proyectos de piscifactoría y modernización. | J31: Conectividad multi-centro + ciberseguridad + cloud; si hay recirculación/RAS, IoT para sensórica y control; integradores: implantación y operación de sistemas (red/seguridad/datos).
B32: Riofrío 1963 SL | C32: B19689462 | D32: 21 | E32: 1228 | F32: Cádiz | G32: Comercializa caviar a través de tienda online; comunica ser caviar ecológico y presenta catálogo de productos de caviar bajo marca Riofrío. | H32: https://www.caviarderiofrio.com/ | I32: Posicionamiento sectorial y acceso a información/innovación relevante para producto premium (calidad, reputación, sostenibilidad). | J32: Ciberseguridad (marca premium), cloud/workplace y herramientas digitales para relación con clientes y pedidos; integradores: eCommerce/CRM/seguridad y servicios gestionados.
B33: RiverFresh Iregua SLU | C33: B26499814 | D33: 42 | E33: 5780 | F33: La Rioja | G33: Proyecto de acuicultura de trucha arco iris (marca Riverfresh) enfocado en sostenibilidad y salud; comunica selección de ubicaciones por calidad del agua, mejora continua de instalaciones y producto trucha arco iris. | H33: http://www.riverfreshiregua.com/ | I33: Innovación y conocimiento sectorial para eficiencia/sostenibilidad en trucha, además de visibilidad y contexto de mercado. | J33: Conectividad (sedes y plantas), IoT para control productivo, cloud para analítica y ciberseguridad; integradores: despliegue industrial completo con soporte.
B34: Stolt Sea Farm SA | C34: A28682987 | D34: 303 | E34: 107.232 | F34: A Coruña | G34: Empresa de acuicultura “land-based” (en tierra) de alta tecnología; se presenta como proveedor líder de rodaballo (turbot) y lenguado (sole) producidos de forma ambientalmente responsable. | H34: https://www.stoltseafarm.com/ | I34: Innovación aplicada e inteligencia sectorial muy relevante para especies técnicas (rodaballo/lenguado) y operaciones multi-centro, además de visibilidad. | J34: Conectividad multi-centro, IoT (RAS/controles), cloud para consolidación y ciberseguridad; integradores: operación gestionada con SLAs y seguridad.
B35: Tuna Graso SAU | C35: A30712616 | D35: 10 | E35: 26016 | F35: Murcia | G35: Actividad ligada al atún rojo; figura vinculada a web corporativa de grupo y a la actividad de atún rojo con captura sostenible (ike jime) y trazabilidad del producto. | H35: https://ricardofuentes.com/ | I35: Representación sectorial y acceso a información/innovación útil en una actividad de alta exigencia de control y mercado internacional. | J35: Conectividad segura + cloud para trazabilidad y ciberseguridad para proteger cadena; integradores: seguridad gestionada + comunicaciones corporativas.
B36: Valenciana de Acuicultura SA | C36: A46228078 | D36: 17 | E36: 4746 | F36: Valencia | G36: Productor de anguilas desde 1984; comunica ser pionera en sistemas de recirculación de agua y especifica capacidad anual de producción de anguilas y suministro regular todo el año. | H36: https://valaqua.com/ | I36: Acceso a innovación y contexto sectorial para producción técnica (recirculación/eficiencia) y posicionamiento en el ecosistema acuícola español. | J36: IoT para control de recirculación/producción, conectividad estable, cloud y ciberseguridad; integradores: sensórica+plataforma+seguridad y mantenimiento continuo.

Sheet BBDD Completa
A1: cif | B1: FILTRADO | C1: FILTRADO | D1: Categoría | E1: Razón social | F1: Provincia | G1: Código postal | H1: Ventas | I1: Empleados | J1: Sucursales | K1: Objeto Social | L1: Score Big Data | M1: Tel 1 | N1: Tel 2 | O1: Tel 3 | P1: Tel 4 | Q1: Tel 5 | R1: Contacto 1 | S1: Contacto 2 | T1: Contacto 3 | U1: Contacto 4 | V1: Contacto 5 | W1: Cargo 1 | X1: Cargo 2 | Y1: Cargo 3 | Z1: Cargo 4 | AA1: Cargo 5 | AB1: Email 1 | AC1: Email 2 | AD1: Email 3 | AE1: Email 4 | AF1: Email 5
